Workbook
Name K: '1_First_Price'!$C$3
Name K_2: '2_Second_Price'!$C$3
Name N_a: '1_First_Price'!$C$1
Name N_a2: '2_Second_Price'!$C$1
Name N_c1: '1_First_Price'!$C$4
Name N_c12: '2_Second_Price'!$C$4
Name N_c2: '1_First_Price'!$C$5
Name N_c22: '2_Second_Price'!$C$5
Name xi: '1_First_Price'!$C$2
Name xi_2: '2_Second_Price'!$C$2

Sheet 00_READ_ME
A1: AUCTION MECHANISMS | RESEARCH PORTFOLIO
A2: Optimal bidding, seller revenue and Monte Carlo evidence | Keman Xiang
A4: THE DECISION PROBLEM
A5: Case context
A6: A seller (CA) allocates a single parcel of land through a sealed-bid auction. Competing buyers privately know their willingness to pay; neither the seller nor competing buyers observes another buyer’s true value before bidding.
A8: Two competing auction designs
A9: First-price: the highest bidder wins and pays their own bid (Dutch-equivalent allocation/payment). Second-price: the highest bidder wins but pays the second-highest bid (English-equivalent allocation/payment).
A11: The buyer’s optimization problem
A12: You are bidder 1. Select a bidding fraction x of your private valuation to maximize expected net surplus, balancing the probability of winning against the payment conditional on winning.
A14: The seller’s decision problem
A15: CA evaluates expected revenue across bidder populations and bidding behavior. A strategy that raises revenue for the seller need not be individually optimal for bidder 1.
A17: Research questions
... A48: 1_First_Price and 2_Second_Price contain the original auction calculations and 12 original charts. MC_Random_N2, N5 and N10 contain frozen private valuations.

Sheet 01_RESEARCH_MODEL
A1: RESEARCH MODEL | ECONOMIC ENVIRONMENT
A2: A one-unit, independent-private-values auction with risk-neutral buyers
A4: MARKET AND INFORMATION STRUCTURE
A5: Asset and seller
A6: CA sells one indivisible parcel of land. There is exactly one winner; competition is among N = 2, 5 or 10 prospective buyers.
A8: Private values
A9: Each buyer i draws v_i independently from Uniform[0,1] million dollars. Each buyer knows their own v_i and the common distribution, but not the realized values of competitors.
A11: Risk neutrality and incentives
A12: A buyer receives value v_i only upon winning and pays according to the mechanism. The optimization criterion is expected monetary surplus, not risk-adjusted utility.
A14: Strategy set and focal bidder
A15: Bidder 1 chooses b_1(x) = x*v_1, x in {0.1,0.2,...,1.0}. Other bidders follow mechanism-specific bidding rules held fixed within each experiment.
A19: ALLOCATION, PAYMENT AND PAYOFFS
... A49: Revenue equivalence concerns equilibrium expected revenue, not revenue for every off-equilibrium x or identical revenue on each simulated path. Deviations at K=1,000 can arise from sampling variability.

Sheet 02_SIMULATION_DESIGN
A1: SIMULATION DESIGN | CONTROLLED COMPARISON
A2: A reproducible 2 x 3 x 10 experiment with 1,000 independent valuation draws per N
A4: EXPERIMENT FACTORS
A5: Dimension | B5: Setting | C5: Why it matters
A6: Mechanism | B6: First-price; second-price | C6: Changes payment rule and competing-bid assumptions
A7: Bidders (N) | B7: 2, 5, 10 | C7: Tests how competition changes surplus and revenue
A8: Bidder 1 fraction (x) | B8: 0.1 to 1.0, step 0.1 | C8: Tests bid shading against win probability
A9: Replications (K) | B9: 1,000 for each N | C9: Monte Carlo estimation of conditional expected outcomes
A10: Random valuations | B10: Frozen Uniform[0,1] draws | C10: Makes numerical results reproducible
A11: Outputs | B11: Surplus and seller revenue | C11: Separates buyer and seller objectives
A14: REPLICATION PROCEDURE
A15: 1 | Generate a valuation vector
A16: For each N and replicate k, read one row of MC_Random_N2/N5/N10. Columns B onward are private valuations for bidder 1 and N-1 competitors.
A18: 2 | Form the bids
A19: Set b_1=x*v_1. For first-price, competitor bids are (1-1/N)*v_i. For second-price, competitor bids are v_i.
A21: 3 | Determine allocation and payment
A22: The highest bid wins. First-price winner pays highest bid; second-price winner pays second-highest bid. Bidder 1 receives zero surplus if they lose.
A24: 4 | Store the sample-path outcome
A25: Each of the 12 data tables records 1,000 rows (replications) by 10 columns (strategy x). One table per mechanism x N x outcome.
A27: 5 | Estimate and compare
A28: Take column averages to obtain ES_N(x) and ER_N(x). Find surplus-maximizing x; compare seller revenue at the respective equilibrium strategies.
A30: 6 | Diagnose simulation noise
... A47: Continuous Uniform valuations imply exact ties occur with probability zero theoretically. The spreadsheet uses >= comparisons to assign a win in a numerical tie; ties are not a material theoretical driver.

Sheet 08_CALCULATION_GUIDE
A1: CALCULATION GUIDE | MODEL AUDIT TRAIL
A2: A cell-level reader’s guide to sample paths, simulation grids, STAT and questions
A4: ORIGINAL WORKSHEETS AND THE SAMPLE PATH
A5: 1_First_Price | sample path
A6: Inputs C1:C5 specify bidder count N, strategy x, replications K and alternative bidder counts. Columns G:L contain bidder ID, valuation v, bid, winning indicator, payment and surplus for a representative auction. P2 records the highest bid, the seller’s first-price revenue.
A8: 2_Second_Price | sample path
A9: The same bidder-level logic applies, but opponents bid their full valuations and the winning payment equals the second-highest bid. P2 uses the second-largest bid to represent seller revenue.
A11: What a sample path is
A12: One simulated auction realization: draw private values, calculate each bid, identify the winner, apply the payment rule and compute each bidder’s realized surplus. It is a single outcome, not an expected value.
A14: STAT / expected-value summaries
A15: STAT-style summary cells average the 1,000 sample-path outputs for each strategy. ES(x) estimates bidder 1 expected surplus; ER(x) estimates CA expected revenue. Averages are Monte Carlo estimators, not individual bids or probabilities.
A17: Frozen valuation worksheets
... A22: ALL 12 MONTE CARLO TABLES | EXACT CELL MAP
A23: Mechanism | B23: N | C23: Outcome | D23: Sample-path grid | E23: Strategies (x) | F23: STAT range | G23: Meaning | H23: Replications
A24: First-price | B24: 2 | C24: Surplus | D24: T2:AC1001 | E24: T1:AC1 | F24: AG1:AG10 | G24: Bidder 1 net surplus | H24: 1000
A25: First-price | B25: 2 | C25: Revenue | D25: AQ2:AZ1001 | E25: AQ1:AZ1 | F25: BD1:BD10 | G25: Seller payment | H25: 1000
A26: Second-price | B26: 2 | C26: Surplus | D26: T2:AC1001 | E26: T1:AC1 | F26: AG1:AG10 | G26: Bidder 1 net surplus | H26: 1000
A27: Second-price | B27: 2 | C27: Revenue | D27: AP2:AY1001 | E27: AP1:AY1 | F27: BC1:BC10 | G27: Seller payment | H27: 1000
A28: First-price | B28: 5 | C28: Surplus | D28: CH2:CQ1001 | E28: CH1:CQ1 | F28: CU1:CU10 | G28: Bidder 1 net surplus | H28: 1000
A29: First-price | B29: 5 | C29: Revenue | D29: DE2:DN1001 | E29: DE1:DN1 | F29: DR1:DR10 | G29: Seller payment | H29: 1000
A30: Second-price | B30: 5 | C30: Surplus | D30: BU2:CD1001 | E30: BU1:CD1 | F30: CH1:CH10 | G30: Bidder 1 net surplus | H30: 1000
A31: Second-price | B31: 5 | C31: Revenue | D31: CQ2:CZ1001 | E31: CQ1:CZ1 | F31: DD1:DD10 | G31: Seller payment | H31: 1000
A32: First-price | B32: 10 | C32: Surplus | D32: EK2:ET1001 | E32: EK1:ET1 | F32: EX1:EX10 | G32: Bidder 1 net surplus | H32: 1000
A33: First-price | B33: 10 | C33: Revenue | D33: FG2:FP1001 | E33: FG1:FP1 | F33: FT1:FT10 | G33: Seller payment | H33: 1000
A34: Second-price | B34: 10 | C34: Surplus | D34: DV2:EE1001 | E34: DV1:EE1 | F34: EI1:EI10 | G34: Bidder 1 net surplus | H34: 1000
A35: Second-price | B35: 10 | C35: Revenue | D35: ER2:FA1001 | E35: ER1:FA1 | F35: FE1:FE10 | G35: Seller payment | H35: 1000
A38: QUESTION-BY-QUESTION RESEARCH OBJECTIVES
A39: First-price | Q(a)
A40: For N=2, calculate and plot bidder 1 ES(x) across ten x values; find surplus-maximizing x*; calculate and plot seller ER(x). Separates the two objective functions in a simple two-bidder market.
A42: First-price | Q(b)
A43: Ask whether CA can attain the highest revenue shown across x. Tests the distinction between an ex-post seller-favorable bid and the bidder’s privately optimal strategy.
A45: First-price | Q(c)
A46: Repeat the surplus and revenue exercise for N=5 and N=10. Isolate the effect of stronger competition on bid shading, surplus and revenue.
A48: First-price | Q(d)
A49: Generalize to arbitrary N. Identify equilibrium x*=(N-1)/N and equilibrium expected seller revenue (N-1)/(N+1).
A51: Second-price | Q(a)
A52: For N=2, evaluate surplus-maximizing x and seller revenue across x. Highlight the payment rule based on the second-highest bid.
A54: Second-price | Q(b)
... A91: SD measures path-to-path dispersion; SE=SD/sqrt(K) measures uncertainty in the estimated mean; approximate 95% CI uses mean +/-1.96 SE.

Sheet 1_First_Price
A1: INPUT | B1: N_a | C1: 10 | E1: Qa) | F1: SAMPLE PATH | G1: ID | H1: vi | I1: bi | J1: wi | K1: payi | L1: Si | N1: STAT | O1: S1(x) | P1: =L2 -> 0 | R1: DATA TABLE | S1: =P1 -> 0 | T1: 0.1 | U1: 0.2 | V1: 0.3 | W1: 0.4 | X1: 0.5 | Y1: 0.6 | Z1: 0.7 | AA1: 0.8 | AB1: 0.9 | AC1: 1 | AE1: 0.1 | AF1: ES(0.1) | AG1: =AVERAGE(T2:T1001) -> 0.059761192 | AO1: DATA TABLE | AP1: =P2 -> 0.74418577 | AQ1: 0.1 | AR1: 0.2 | AS1: 0.3 | AT1: 0.4 | AU1: 0.5 | AV1: 0.6 | AW1: 0.7 | AX1: 0.8 | AY1: 0.9 | AZ1: 1 | BB1: 0.1 | BC1: ER(0.1) | BD1: =AVERAGE(AQ2:AQ1001) -> 0.25572136 | BH1: Qb) | BI1: CA can not achieve the maximal expected revenue among R2(x). | BS1: Qc) | BT1: N=5 | BU1: ID | BV1: vi | BW1: bi | BX1: wi | BY1: payi | BZ1: Si | CB1: STAT | CC1: S1(x) | CD1: =BZ2 -> 0 | CF1: DATA TABLE | CG1: =CD1 -> 0 | CH1: 0.1 | CI1: 0.2 | CJ1: 0.3 | CK1: 0.4 | CL1: 0.5 | CM1: 0.6 | CN1: 0.7 | CO1: 0.8 | CP1: 0.9 | CQ1: 1 | CS1: 0.1 | CT1: ES(0.1) | CU1: =AVERAGE(CH2:CH1001) -> 0 | DC1: DATA TABLE | DD1: =CD2 -> 0.76371113 | DE1: 0.1 | DF1: 0.2 | DG1: 0.3 | DH1: 0.4 | DI1: 0.5 | DJ1: 0.6 | DK1: 0.7 | DL1: 0.8 | DM1: 0.9 | DN1: 1 | DP1: 0.1 | DQ1: ER(0.1) | DR1: =AVERAGE(DE2:DE1001) -> 0.63560466 | DV1: N=10 | DW1: SAMPLE PATH | DX1: ID | DY1: vi | DZ1: bi | EA1: wi | EB1: payi | EC1: Si | EE1: STAT | EF1: S1(x) | EG1: =EC2 -> 0 | EI1: DATA TABLE | EJ1: =EG1 -> 0 | EK1: 0.1 | EL1: 0.2 | EM1: 0.3 | EN1: 0.4 | EO1: 0.5 | EP1: 0.6 | EQ1: 0.7 | ER1: 0.8 | ES1: 0.9 | ET1: 1 | EV1: 0.1 | EW1: ES(0.1) | EX1: =AVERAGE(EK2:EK1001) -> 0 | FE1: DATA TABLE | FF1: =EG2 -> 0.86317859 | FG1: 0.1 | FH1: 0.2 | FI1: 0.3 | FJ1: 0.4 | FK1: 0.5 | FL1: 0.6 | FM1: 0.7 | FN1: 0.8 | FO1: 0.9 | FP1: 1 | FR1: 0.1 | FS1: ER(0.1) | FT1: =AVERAGE(FG2:FG1001) -> 0.80898303 | FV1: Qd) | FW1: Under the assumed independent uniform private valuations and symmetric risk-neutral equilibrium, the optimal first-price bidding strategy is x*=(N-1)/N. Thus, x*=0.5, 0.8, and 0.9 for N=2, 5, and 10, respectively.
B2: xi | C2: 0.1 | G2: 1 | H2: =RAND() -> 0.72843531 | I2: =xi*H2 -> 0.072843531 | J2: =IF(I2=MAX(I2:I3),1,0) -> 0 | K2: =J2*I2 -> 0 | L2: =J2*(H2-K2) -> 0 | O2: R2(x) | P2: =MAX(I2:I3) -> 0.74418577 | S2: {=_xlfn.SEQUENCE(1000)} -> 1 | T2: =IF(T$1*MC_Random_N2!$B2>=0.5*MC_Random_N2!$C2,MC_Random_N2!$B2*(1-T$1),0) -> 0 | U2: =IF(U$1*MC_Random_N2!$B2>=0.5*MC_Random_N2!$C2,MC_Random_N2!$B2*(1-U$1),0) -> 0 | V2: =IF(V$1*MC_Random_N2!$B2>=0.5*MC_Random_N2!$C2,MC_Random_N2!$B2*(1-V$1),0) -> 0 | W2: =IF(W$1*MC_Random_N2!$B2>=0.5*MC_Random_N2!$C2,MC_Random_N2!$B2*(1-W$1),0) -> 0 | X2: =IF(X$1*MC_Random_N2!$B2>=0.5*MC_Random_N2!$C2,MC_Random_N2!$B2*(1-X$1),0) -> 0 | Y2: =IF(Y$1*MC_Random_N2!$B2>=0.5*MC_Random_N2!$C2,MC_Random_N2!$B2*(1-Y$1),0) -> 0 | Z2: =IF(Z$1*MC_Random_N2!$B2>=0.5*MC_Random_N2!$C2,MC_Random_N2!$B2*(1-Z$1),0) -> 0 | AA2: =IF(AA$1*MC_Random_N2!$B2>=0.5*MC_Random_N2!$C2,MC_Random_N2!$B2*(1-AA$1),0) -> 0.098422842 | ... AC2: =IF(AC$1*MC_Random_N2!$B2>=0.5*MC_Random_N2!$C2,MC_Random_N2!$B2*(1-AC$1),0) -> 0 | AE2: 0.2 | AF2: ES(0.2) | AG2: =AVERAGE(U2:U1001) -> 0.10789344 | AP2: {=_xlfn.SEQUENCE(1000)} -> 1 | AQ2: =MAX(AQ$1*MC_Random_N2!$B2,0.5*MC_Random_N2!$C2) -> 0.36866346 | AR2: =MAX(AR$1*MC_Random_N2!$B2,0.5*MC_Random_N2!$C2) -> 0.36866346 | AS2: =MAX(AS$1*MC_Random_N2!$B2,0.5*MC_Random_N2!$C2) -> 0.36866346 | AT2: =MAX(AT$1*MC_Random_N2!$B2,0.5*MC_Random_N2!$C2) -> 0.36866346 | AU2: =MAX(AU$1*MC_Random_N2!$B2,0.5*MC_Random_N2!$C2) -> 0.36866346 | AV2: =MAX(AV$1*MC_Random_N2!$B2,0.5*MC_Random_N2!$C2) -> 0.36866346 | AW2: =MAX(AW$1*MC_Random_N2!$B2,0.5*MC_Random_N2!$C2) -> 0.36866346 | AX2: =MAX(AX$1*MC_Random_N2!$B2,0.5*MC_Random_N2!$C2) -> 0.39369137 | ... AZ2: =MAX(AZ$1*MC_Random_N2!$B2,0.5*MC_Random_N2!$C2) -> 0.49211421 | BB2: 0.2 | BC2: ER(0.2) | BD2: =AVERAGE(AR2:AR1001) -> 0.26535513 | BI2: Because the bider will choose the optimal strategy x* to maximaze his surplus, thus R2(x*) will not be the maximal value. | BU2: {=_xlfn.SEQUENCE(5)} -> 1 | BV2: =RAND() -> 0.035776351 | BW2: =xi*BV2 -> 0.0035776351 | BX2: =IF(BW2=MAX($BW$2:$BW$6),1,0) -> 0 | BY2: =BX2*BW2 -> 0 | BZ2: =BX2*(BV2-BY2) -> 0 | CC2: R2(x) | CD2: =MAX(BW2:BW6) -> 0.76371113 | CG2: {=_xlfn.SEQUENCE(1000)} -> 1 | CH2: =IF(CH$1*MC_Random_N5!$B2>=0.8*MAX(MC_Random_N5!$C2:$F2),MC_Random_N5!$B2*(1-CH$1),0) -> 0 | CI2: =IF(CI$1*MC_Random_N5!$B2>=0.8*MAX(MC_Random_N5!$C2:$F2),MC_Random_N5!$B2*(1-CI$1),0) -> 0 | CJ2: =IF(CJ$1*MC_Random_N5!$B2>=0.8*MAX(MC_Random_N5!$C2:$F2),MC_Random_N5!$B2*(1-CJ$1),0) -> 0 | CK2: =IF(CK$1*MC_Random_N5!$B2>=0.8*MAX(MC_Random_N5!$C2:$F2),MC_Random_N5!$B2*(1-CK$1),0) -> 0 | CL2: =IF(CL$1*MC_Random_N5!$B2>=0.8*MAX(MC_Random_N5!$C2:$F2),MC_Random_N5!$B2*(1-CL$1),0) -> 0 | CM2: =IF(CM$1*MC_Random_N5!$B2>=0.8*MAX(MC_Random_N5!$C2:$F2),MC_Random_N5!$B2*(1-CM$1),0) -> 0 | CN2: =IF(CN$1*MC_Random_N5!$B2>=0.8*MAX(MC_Random_N5!$C2:$F2),MC_Random_N5!$B2*(1-CN$1),0) -> 0 | CO2: =IF(CO$1*MC_Random_N5!$B2>=0.8*MAX(MC_Random_N5!$C2:$F2),MC_Random_N5!$B2*(1-CO$1),0) -> 0 | ... CQ2: =IF(CQ$1*MC_Random_N5!$B2>=0.8*MAX(MC_Random_N5!$C2:$F2),MC_Random_N5!$B2*(1-CQ$1),0) -> 0 | CS2: 0.2 | CT2: ES(0.2) | CU2: =AVERAGE(CI2:CI1001) -> 0.0014045626 | DD2: {=_xlfn.SEQUENCE(1000)} -> 1 | DE2: =MAX(DE$1*MC_Random_N5!$B2,0.8*MAX(MC_Random_N5!$C2:$F2)) -> 0.78035436 | DF2: =MAX(DF$1*MC_Random_N5!$B2,0.8*MAX(MC_Random_N5!$C2:$F2)) -> 0.78035436 | DG2: =MAX(DG$1*MC_Random_N5!$B2,0.8*MAX(MC_Random_N5!$C2:$F2)) -> 0.78035436 | DH2: =MAX(DH$1*MC_Random_N5!$B2,0.8*MAX(MC_Random_N5!$C2:$F2)) -> 0.78035436 | DI2: =MAX(DI$1*MC_Random_N5!$B2,0.8*MAX(MC_Random_N5!$C2:$F2)) -> 0.78035436 | DJ2: =MAX(DJ$1*MC_Random_N5!$B2,0.8*MAX(MC_Random_N5!$C2:$F2)) -> 0.78035436 | DK2: =MAX(DK$1*MC_Random_N5!$B2,0.8*MAX(MC_Random_N5!$C2:$F2)) -> 0.78035436 | DL2: =MAX(DL$1*MC_Random_N5!$B2,0.8*MAX(MC_Random_N5!$C2:$F2)) -> 0.78035436 | ... DN2: =MAX(DN$1*MC_Random_N5!$B2,0.8*MAX(MC_Random_N5!$C2:$F2)) -> 0.78035436 | DP2: 0.2 | DQ2: ER(0.2) | DR2: =AVERAGE(DF2:DF1001) -> 0.63565573 | DX2: {=_xlfn.SEQUENCE(10)} -> 1 | DY2: =RAND() -> 0.79417796 | DZ2: =xi*DY2 -> 0.079417796 | EA2: =IF(DZ2=MAX($DZ$2:$DZ$11),1,0) -> 0 | EB2: =EA2*DZ2 -> 0 | EC2: =EA2*(DY2-EB2) -> 0 | EF2: R2(x) | EG2: =MAX(DZ2:DZ11) -> 0.86317859 | EJ2: {=_xlfn.SEQUENCE(1000)} -> 1 | EK2: =IF(EK$1*MC_Random_N10!$B2>=0.9*MAX(MC_Random_N10!$C2:$K2),MC_Random_N10!$B2*(1-EK$1),0) -> 0 | EL2: =IF(EL$1*MC_Random_N10!$B2>=0.9*MAX(MC_Random_N10!$C2:$K2),MC_Random_N10!$B2*(1-EL$1),0) -> 0 | EM2: =IF(EM$1*MC_Random_N10!$B2>=0.9*MAX(MC_Random_N10!$C2:$K2),MC_Random_N10!$B2*(1-EM$1),0) -> 0 | EN2: =IF(EN$1*MC_Random_N10!$B2>=0.9*MAX(MC_Random_N10!$C2:$K2),MC_Random_N10!$B2*(1-EN$1),0) -> 0 | EO2: =IF(EO$1*MC_Random_N10!$B2>=0.9*MAX(MC_Random_N10!$C2:$K2),MC_Random_N10!$B2*(1-EO$1),0) -> 0 | EP2: =IF(EP$1*MC_Random_N10!$B2>=0.9*MAX(MC_Random_N10!$C2:$K2),MC_Random_N10!$B2*(1-EP$1),0) -> 0 | EQ2: =IF(EQ$1*MC_Random_N10!$B2>=0.9*MAX(MC_Random_N10!$C2:$K2),MC_Random_N10!$B2*(1-EQ$1),0) -> 0 | ER2: =IF(ER$1*MC_Random_N10!$B2>=0.9*MAX(MC_Random_N10!$C2:$K2),MC_Random_N10!$B2*(1-ER$1),0) -> 0 | ... ET2: =IF(ET$1*MC_Random_N10!$B2>=0.9*MAX(MC_Random_N10!$C2:$K2),MC_Random_N10!$B2*(1-ET$1),0) -> 0 | EV2: 0.2 | EW2: ES(0.2) | EX2: =AVERAGE(EL2:EL1001) -> 0 | FF2: {=_xlfn.SEQUENCE(1000)} -> 1 | FG2: =MAX(FG$1*MC_Random_N10!$B2,0.9*MAX(MC_Random_N10!$C2:$K2)) -> 0.86230175 | FH2: =MAX(FH$1*MC_Random_N10!$B2,0.9*MAX(MC_Random_N10!$C2:$K2)) -> 0.86230175 | FI2: =MAX(FI$1*MC_Random_N10!$B2,0.9*MAX(MC_Random_N10!$C2:$K2)) -> 0.86230175 | FJ2: =MAX(FJ$1*MC_Random_N10!$B2,0.9*MAX(MC_Random_N10!$C2:$K2)) -> 0.86230175 | FK2: =MAX(FK$1*MC_Random_N10!$B2,0.9*MAX(MC_Random_N10!$C2:$K2)) -> 0.86230175 | FL2: =MAX(FL$1*MC_Random_N10!$B2,0.9*MAX(MC_Random_N10!$C2:$K2)) -> 0.86230175 | FM2: =MAX(FM$1*MC_Random_N10!$B2,0.9*MAX(MC_Random_N10!$C2:$K2)) -> 0.86230175 | FN2: =MAX(FN$1*MC_Random_N10!$B2,0.9*MAX(MC_Random_N10!$C2:$K2)) -> 0.86230175 | ... FP2: =MAX(FP$1*MC_Random_N10!$B2,0.9*MAX(MC_Random_N10!$C2:$K2)) -> 0.86230175 | FR2: 0.2 | FS2: ER(0.2) | FT2: =AVERAGE(FH2:FH1001) -> 0.80898303 | FW2: The bidding strategy that maximizes Bidder 1's expected surplus does not necessarily maximize the auctioneer's revenue. These are different optimization objectives.
B3: K | C3: 1000 | G3: 2 | H3: =RAND() -> 0.82687308 | I3: =(1-1/N_a)*H3 -> 0.74418577 | J3: =IF(I3=MAX(I2:I3),1,0) -> 1 | K3: =J3*I3 -> 0.74418577 | L3: =J3*(H3-K3) -> 0.082687308 | S3: 2 | T3: =IF(T$1*MC_Random_N2!$B3>=0.5*MC_Random_N2!$C3,MC_Random_N2!$B3*(1-T$1),0) -> 0 | U3: =IF(U$1*MC_Random_N2!$B3>=0.5*MC_Random_N2!$C3,MC_Random_N2!$B3*(1-U$1),0) -> 0 | V3: =IF(V$1*MC_Random_N2!$B3>=0.5*MC_Random_N2!$C3,MC_Random_N2!$B3*(1-V$1),0) -> 0 | W3: =IF(W$1*MC_Random_N2!$B3>=0.5*MC_Random_N2!$C3,MC_Random_N2!$B3*(1-W$1),0) -> 0 | X3: =IF(X$1*MC_Random_N2!$B3>=0.5*MC_Random_N2!$C3,MC_Random_N2!$B3*(1-X$1),0) -> 0 | Y3: =IF(Y$1*MC_Random_N2!$B3>=0.5*MC_Random_N2!$C3,MC_Random_N2!$B3*(1-Y$1),0) -> 0 | Z3: =IF(Z$1*MC_Random_N2!$B3>=0.5*MC_Random_N2!$C3,MC_Random_N2!$B3*(1-Z$1),0) -> 0 | AA3: =IF(AA$1*MC_Random_N2!$B3>=0.5*MC_Random_N2!$C3,MC_Random_N2!$B3*(1-AA$1),0) -> 0 | ... AC3: =IF(AC$1*MC_Random_N2!$B3>=0.5*MC_Random_N2!$C3,MC_Random_N2!$B3*(1-AC$1),0) -> 0 | AE3: 0.3 | AF3: ES(0.3) | AG3: =AVERAGE(V2:V1001) -> 0.13555542 | AP3: 2 | AQ3: =MAX(AQ$1*MC_Random_N2!$B3,0.5*MC_Random_N2!$C3) -> 0.34061444 | AR3: =MAX(AR$1*MC_Random_N2!$B3,0.5*MC_Random_N2!$C3) -> 0.34061444 | AS3: =MAX(AS$1*MC_Random_N2!$B3,0.5*MC_Random_N2!$C3) -> 0.34061444 | AT3: =MAX(AT$1*MC_Random_N2!$B3,0.5*MC_Random_N2!$C3) -> 0.34061444 | AU3: =MAX(AU$1*MC_Random_N2!$B3,0.5*MC_Random_N2!$C3) -> 0.34061444 | AV3: =MAX(AV$1*MC_Random_N2!$B3,0.5*MC_Random_N2!$C3) -> 0.34061444 | AW3: =MAX(AW$1*MC_Random_N2!$B3,0.5*MC_Random_N2!$C3) -> 0.34061444 | AX3: =MAX(AX$1*MC_Random_N2!$B3,0.5*MC_Random_N2!$C3) -> 0.34061444 | ... AZ3: =MAX(AZ$1*MC_Random_N2!$B3,0.5*MC_Random_N2!$C3) -> 0.34061444 | BB3: 0.3 | BC3: ER(0.3) | BD3: =AVERAGE(AS2:AS1001) -> 0.28180076 | BU3: 2 | BV3: =RAND() -> 0.49287614 | BW3: =(1-1/N_c1)*BV3 -> 0.39430091 | BX3: =IF(BW3=MAX($BW$2:$BW$6),1,0) -> 0 | BY3: =BX3*BW3 -> 0 | BZ3: =BX3*(BV3-BY3) -> 0 | CG3: 2 | CH3: =IF(CH$1*MC_Random_N5!$B3>=0.8*MAX(MC_Random_N5!$C3:$F3),MC_Random_N5!$B3*(1-CH$1),0) -> 0 | CI3: =IF(CI$1*MC_Random_N5!$B3>=0.8*MAX(MC_Random_N5!$C3:$F3),MC_Random_N5!$B3*(1-CI$1),0) -> 0 | CJ3: =IF(CJ$1*MC_Random_N5!$B3>=0.8*MAX(MC_Random_N5!$C3:$F3),MC_Random_N5!$B3*(1-CJ$1),0) -> 0 | CK3: =IF(CK$1*MC_Random_N5!$B3>=0.8*MAX(MC_Random_N5!$C3:$F3),MC_Random_N5!$B3*(1-CK$1),0) -> 0 | CL3: =IF(CL$1*MC_Random_N5!$B3>=0.8*MAX(MC_Random_N5!$C3:$F3),MC_Random_N5!$B3*(1-CL$1),0) -> 0 | CM3: =IF(CM$1*MC_Random_N5!$B3>=0.8*MAX(MC_Random_N5!$C3:$F3),MC_Random_N5!$B3*(1-CM$1),0) -> 0 | CN3: =IF(CN$1*MC_Random_N5!$B3>=0.8*MAX(MC_Random_N5!$C3:$F3),MC_Random_N5!$B3*(1-CN$1),0) -> 0 | CO3: =IF(CO$1*MC_Random_N5!$B3>=0.8*MAX(MC_Random_N5!$C3:$F3),MC_Random_N5!$B3*(1-CO$1),0) -> 0 | ... CQ3: =IF(CQ$1*MC_Random_N5!$B3>=0.8*MAX(MC_Random_N5!$C3:$F3),MC_Random_N5!$B3*(1-CQ$1),0) -> 0 | CS3: 0.3 | CT3: ES(0.3) | CU3: =AVERAGE(CJ2:CJ1001) -> 0.002438488 | DD3: 2 | DE3: =MAX(DE$1*MC_Random_N5!$B3,0.8*MAX(MC_Random_N5!$C3:$F3)) -> 0.60867849 | DF3: =MAX(DF$1*MC_Random_N5!$B3,0.8*MAX(MC_Random_N5!$C3:$F3)) -> 0.60867849 | DG3: =MAX(DG$1*MC_Random_N5!$B3,0.8*MAX(MC_Random_N5!$C3:$F3)) -> 0.60867849 | DH3: =MAX(DH$1*MC_Random_N5!$B3,0.8*MAX(MC_Random_N5!$C3:$F3)) -> 0.60867849 | DI3: =MAX(DI$1*MC_Random_N5!$B3,0.8*MAX(MC_Random_N5!$C3:$F3)) -> 0.60867849 | DJ3: =MAX(DJ$1*MC_Random_N5!$B3,0.8*MAX(MC_Random_N5!$C3:$F3)) -> 0.60867849 | DK3: =MAX(DK$1*MC_Random_N5!$B3,0.8*MAX(MC_Random_N5!$C3:$F3)) -> 0.60867849 | DL3: =MAX(DL$1*MC_Random_N5!$B3,0.8*MAX(MC_Random_N5!$C3:$F3)) -> 0.60867849 | ... DN3: =MAX(DN$1*MC_Random_N5!$B3,0.8*MAX(MC_Random_N5!$C3:$F3)) -> 0.60867849 | DP3: 0.3 | DQ3: ER(0.3) | DR3: =AVERAGE(DG2:DG1001) -> 0.63589002 | DX3: 2 | DY3: =RAND() -> 0.95908732 | DZ3: =(1-1/N_c2)*DY3 -> 0.86317859 | EA3: =IF(DZ3=MAX($DZ$2:$DZ$11),1,0) -> 1 | EB3: =EA3*DZ3 -> 0.86317859 | EC3: =EA3*(DY3-EB3) -> 0.095908732 | EJ3: 2 | EK3: =IF(EK$1*MC_Random_N10!$B3>=0.9*MAX(MC_Random_N10!$C3:$K3),MC_Random_N10!$B3*(1-EK$1),0) -> 0 | EL3: =IF(EL$1*MC_Random_N10!$B3>=0.9*MAX(MC_Random_N10!$C3:$K3),MC_Random_N10!$B3*(1-EL$1),0) -> 0 | EM3: =IF(EM$1*MC_Random_N10!$B3>=0.9*MAX(MC_Random_N10!$C3:$K3),MC_Random_N10!$B3*(1-EM$1),0) -> 0 | EN3: =IF(EN$1*MC_Random_N10!$B3>=0.9*MAX(MC_Random_N10!$C3:$K3),MC_Random_N10!$B3*(1-EN$1),0) -> 0 | EO3: =IF(EO$1*MC_Random_N10!$B3>=0.9*MAX(MC_Random_N10!$C3:$K3),MC_Random_N10!$B3*(1-EO$1),0) -> 0 | EP3: =IF(EP$1*MC_Random_N10!$B3>=0.9*MAX(MC_Random_N10!$C3:$K3),MC_Random_N10!$B3*(1-EP$1),0) -> 0 | EQ3: =IF(EQ$1*MC_Random_N10!$B3>=0.9*MAX(MC_Random_N10!$C3:$K3),MC_Random_N10!$B3*(1-EQ$1),0) -> 0 | ER3: =IF(ER$1*MC_Random_N10!$B3>=0.9*MAX(MC_Random_N10!$C3:$K3),MC_Random_N10!$B3*(1-ER$1),0) -> 0 | ... ET3: =IF(ET$1*MC_Random_N10!$B3>=0.9*MAX(MC_Random_N10!$C3:$K3),MC_Random_N10!$B3*(1-ET$1),0) -> 0 | EV3: 0.3 | EW3: ES(0.3) | EX3: =AVERAGE(EM2:EM1001) -> 0 | FF3: 2 | FG3: =MAX(FG$1*MC_Random_N10!$B3,0.9*MAX(MC_Random_N10!$C3:$K3)) -> 0.78770555 | FH3: =MAX(FH$1*MC_Random_N10!$B3,0.9*MAX(MC_Random_N10!$C3:$K3)) -> 0.78770555 | FI3: =MAX(FI$1*MC_Random_N10!$B3,0.9*MAX(MC_Random_N10!$C3:$K3)) -> 0.78770555 | FJ3: =MAX(FJ$1*MC_Random_N10!$B3,0.9*MAX(MC_Random_N10!$C3:$K3)) -> 0.78770555 | FK3: =MAX(FK$1*MC_Random_N10!$B3,0.9*MAX(MC_Random_N10!$C3:$K3)) -> 0.78770555 | FL3: =MAX(FL$1*MC_Random_N10!$B3,0.9*MAX(MC_Random_N10!$C3:$K3)) -> 0.78770555 | FM3: =MAX(FM$1*MC_Random_N10!$B3,0.9*MAX(MC_Random_N10!$C3:$K3)) -> 0.78770555 | FN3: =MAX(FN$1*MC_Random_N10!$B3,0.9*MAX(MC_Random_N10!$C3:$K3)) -> 0.78770555 | ... FP3: =MAX(FP$1*MC_Random_N10!$B3,0.9*MAX(MC_Random_N10!$C3:$K3)) -> 0.78770555 | FR3: 0.3 | FS3: ER(0.3) | FT3: =AVERAGE(FI2:FI1001) -> 0.80898303
B4: N_c1 | C4: 5 | S4: 3 | T4: =IF(T$1*MC_Random_N2!$B4>=0.5*MC_Random_N2!$C4,MC_Random_N2!$B4*(1-T$1),0) -> 0 | U4: =IF(U$1*MC_Random_N2!$B4>=0.5*MC_Random_N2!$C4,MC_Random_N2!$B4*(1-U$1),0) -> 0 | V4: =IF(V$1*MC_Random_N2!$B4>=0.5*MC_Random_N2!$C4,MC_Random_N2!$B4*(1-V$1),0) -> 0 | W4: =IF(W$1*MC_Random_N2!$B4>=0.5*MC_Random_N2!$C4,MC_Random_N2!$B4*(1-W$1),0) -> 0 | X4: =IF(X$1*MC_Random_N2!$B4>=0.5*MC_Random_N2!$C4,MC_Random_N2!$B4*(1-X$1),0) -> 0 | Y4: =IF(Y$1*MC_Random_N2!$B4>=0.5*MC_Random_N2!$C4,MC_Random_N2!$B4*(1-Y$1),0) -> 0 | Z4: =IF(Z$1*MC_Random_N2!$B4>=0.5*MC_Random_N2!$C4,MC_Random_N2!$B4*(1-Z$1),0) -> 0.12272349 | AA4: =IF(AA$1*MC_Random_N2!$B4>=0.5*MC_Random_N2!$C4,MC_Random_N2!$B4*(1-AA$1),0) -> 0.081815662 | ... AC4: =IF(AC$1*MC_Random_N2!$B4>=0.5*MC_Random_N2!$C4,MC_Random_N2!$B4*(1-AC$1),0) -> 0 | AE4: 0.4 | AF4: ES(0.4) | AG4: =AVERAGE(W2:W1001) -> 0.15958057 | AP4: 3 | AQ4: =MAX(AQ$1*MC_Random_N2!$B4,0.5*MC_Random_N2!$C4) -> 0.2863389 | AR4: =MAX(AR$1*MC_Random_N2!$B4,0.5*MC_Random_N2!$C4) -> 0.2863389 | AS4: =MAX(AS$1*MC_Random_N2!$B4,0.5*MC_Random_N2!$C4) -> 0.2863389 | AT4: =MAX(AT$1*MC_Random_N2!$B4,0.5*MC_Random_N2!$C4) -> 0.2863389 | AU4: =MAX(AU$1*MC_Random_N2!$B4,0.5*MC_Random_N2!$C4) -> 0.2863389 | AV4: =MAX(AV$1*MC_Random_N2!$B4,0.5*MC_Random_N2!$C4) -> 0.2863389 | AW4: =MAX(AW$1*MC_Random_N2!$B4,0.5*MC_Random_N2!$C4) -> 0.28635482 | AX4: =MAX(AX$1*MC_Random_N2!$B4,0.5*MC_Random_N2!$C4) -> 0.32726265 | ... AZ4: =MAX(AZ$1*MC_Random_N2!$B4,0.5*MC_Random_N2!$C4) -> 0.40907831 | BB4: 0.4 | BC4: ER(0.4) | BD4: =AVERAGE(AT2:AT1001) -> 0.30473106 | BU4: 3 | BV4: =RAND() -> 0.95463891 | BW4: =(1-1/N_c1)*BV4 -> 0.76371113 | BX4: =IF(BW4=MAX($BW$2:$BW$6),1,0) -> 1 | BY4: =BX4*BW4 -> 0.76371113 | BZ4: =BX4*(BV4-BY4) -> 0.19092778 | CG4: 3 | CH4: =IF(CH$1*MC_Random_N5!$B4>=0.8*MAX(MC_Random_N5!$C4:$F4),MC_Random_N5!$B4*(1-CH$1),0) -> 0 | CI4: =IF(CI$1*MC_Random_N5!$B4>=0.8*MAX(MC_Random_N5!$C4:$F4),MC_Random_N5!$B4*(1-CI$1),0) -> 0 | CJ4: =IF(CJ$1*MC_Random_N5!$B4>=0.8*MAX(MC_Random_N5!$C4:$F4),MC_Random_N5!$B4*(1-CJ$1),0) -> 0 | CK4: =IF(CK$1*MC_Random_N5!$B4>=0.8*MAX(MC_Random_N5!$C4:$F4),MC_Random_N5!$B4*(1-CK$1),0) -> 0 | CL4: =IF(CL$1*MC_Random_N5!$B4>=0.8*MAX(MC_Random_N5!$C4:$F4),MC_Random_N5!$B4*(1-CL$1),0) -> 0 | CM4: =IF(CM$1*MC_Random_N5!$B4>=0.8*MAX(MC_Random_N5!$C4:$F4),MC_Random_N5!$B4*(1-CM$1),0) -> 0 | CN4: =IF(CN$1*MC_Random_N5!$B4>=0.8*MAX(MC_Random_N5!$C4:$F4),MC_Random_N5!$B4*(1-CN$1),0) -> 0 | CO4: =IF(CO$1*MC_Random_N5!$B4>=0.8*MAX(MC_Random_N5!$C4:$F4),MC_Random_N5!$B4*(1-CO$1),0) -> 0.16187966 | ... CQ4: =IF(CQ$1*MC_Random_N5!$B4>=0.8*MAX(MC_Random_N5!$C4:$F4),MC_Random_N5!$B4*(1-CQ$1),0) -> 0 | CS4: 0.4 | CT4: ES(0.4) | CU4: =AVERAGE(CK2:CK1001) -> 0.0064399818 | DD4: 3 | DE4: =MAX(DE$1*MC_Random_N5!$B4,0.8*MAX(MC_Random_N5!$C4:$F4)) -> 0.58526341 | DF4: =MAX(DF$1*MC_Random_N5!$B4,0.8*MAX(MC_Random_N5!$C4:$F4)) -> 0.58526341 | DG4: =MAX(DG$1*MC_Random_N5!$B4,0.8*MAX(MC_Random_N5!$C4:$F4)) -> 0.58526341 | DH4: =MAX(DH$1*MC_Random_N5!$B4,0.8*MAX(MC_Random_N5!$C4:$F4)) -> 0.58526341 | DI4: =MAX(DI$1*MC_Random_N5!$B4,0.8*MAX(MC_Random_N5!$C4:$F4)) -> 0.58526341 | DJ4: =MAX(DJ$1*MC_Random_N5!$B4,0.8*MAX(MC_Random_N5!$C4:$F4)) -> 0.58526341 | DK4: =MAX(DK$1*MC_Random_N5!$B4,0.8*MAX(MC_Random_N5!$C4:$F4)) -> 0.58526341 | DL4: =MAX(DL$1*MC_Random_N5!$B4,0.8*MAX(MC_Random_N5!$C4:$F4)) -> 0.64751862 | ... DN4: =MAX(DN$1*MC_Random_N5!$B4,0.8*MAX(MC_Random_N5!$C4:$F4)) -> 0.80939828 | DP4: 0.4 | DQ4: ER(0.4) | DR4: =AVERAGE(DH2:DH1001) -> 0.63652022 | DX4: 3 | DY4: =RAND() -> 0.51235596 | DZ4: =(1-1/N_c2)*DY4 -> 0.46112036 | EA4: =IF(DZ4=MAX($DZ$2:$DZ$11),1,0) -> 0 | EB4: =EA4*DZ4 -> 0 | EC4: =EA4*(DY4-EB4) -> 0 | EJ4: 3 | EK4: =IF(EK$1*MC_Random_N10!$B4>=0.9*MAX(MC_Random_N10!$C4:$K4),MC_Random_N10!$B4*(1-EK$1),0) -> 0 | EL4: =IF(EL$1*MC_Random_N10!$B4>=0.9*MAX(MC_Random_N10!$C4:$K4),MC_Random_N10!$B4*(1-EL$1),0) -> 0 | EM4: =IF(EM$1*MC_Random_N10!$B4>=0.9*MAX(MC_Random_N10!$C4:$K4),MC_Random_N10!$B4*(1-EM$1),0) -> 0 | EN4: =IF(EN$1*MC_Random_N10!$B4>=0.9*MAX(MC_Random_N10!$C4:$K4),MC_Random_N10!$B4*(1-EN$1),0) -> 0 | EO4: =IF(EO$1*MC_Random_N10!$B4>=0.9*MAX(MC_Random_N10!$C4:$K4),MC_Random_N10!$B4*(1-EO$1),0) -> 0 | EP4: =IF(EP$1*MC_Random_N10!$B4>=0.9*MAX(MC_Random_N10!$C4:$K4),MC_Random_N10!$B4*(1-EP$1),0) -> 0 | EQ4: =IF(EQ$1*MC_Random_N10!$B4>=0.9*MAX(MC_Random_N10!$C4:$K4),MC_Random_N10!$B4*(1-EQ$1),0) -> 0 | ER4: =IF(ER$1*MC_Random_N10!$B4>=0.9*MAX(MC_Random_N10!$C4:$K4),MC_Random_N10!$B4*(1-ER$1),0) -> 0 | ... ET4: =IF(ET$1*MC_Random_N10!$B4>=0.9*MAX(MC_Random_N10!$C4:$K4),MC_Random_N10!$B4*(1-ET$1),0) -> 0 | EV4: 0.4 | EW4: ES(0.4) | EX4: =AVERAGE(EN2:EN1001) -> 0 | FF4: 3 | FG4: =MAX(FG$1*MC_Random_N10!$B4,0.9*MAX(MC_Random_N10!$C4:$K4)) -> 0.86348889 | FH4: =MAX(FH$1*MC_Random_N10!$B4,0.9*MAX(MC_Random_N10!$C4:$K4)) -> 0.86348889 | FI4: =MAX(FI$1*MC_Random_N10!$B4,0.9*MAX(MC_Random_N10!$C4:$K4)) -> 0.86348889 | FJ4: =MAX(FJ$1*MC_Random_N10!$B4,0.9*MAX(MC_Random_N10!$C4:$K4)) -> 0.86348889 | FK4: =MAX(FK$1*MC_Random_N10!$B4,0.9*MAX(MC_Random_N10!$C4:$K4)) -> 0.86348889 | FL4: =MAX(FL$1*MC_Random_N10!$B4,0.9*MAX(MC_Random_N10!$C4:$K4)) -> 0.86348889 | FM4: =MAX(FM$1*MC_Random_N10!$B4,0.9*MAX(MC_Random_N10!$C4:$K4)) -> 0.86348889 | FN4: =MAX(FN$1*MC_Random_N10!$B4,0.9*MAX(MC_Random_N10!$C4:$K4)) -> 0.86348889 | ... FP4: =MAX(FP$1*MC_Random_N10!$B4,0.9*MAX(MC_Random_N10!$C4:$K4)) -> 0.86348889 | FR4: 0.4 | FS4: ER(0.4) | FT4: =AVERAGE(FJ2:FJ1001) -> 0.80898303
B5: N_c2 | C5: 10 | S5: 4 | T5: =IF(T$1*MC_Random_N2!$B5>=0.5*MC_Random_N2!$C5,MC_Random_N2!$B5*(1-T$1),0) -> 0 | U5: =IF(U$1*MC_Random_N2!$B5>=0.5*MC_Random_N2!$C5,MC_Random_N2!$B5*(1-U$1),0) -> 0 | V5: =IF(V$1*MC_Random_N2!$B5>=0.5*MC_Random_N2!$C5,MC_Random_N2!$B5*(1-V$1),0) -> 0.50876577 | W5: =IF(W$1*MC_Random_N2!$B5>=0.5*MC_Random_N2!$C5,MC_Random_N2!$B5*(1-W$1),0) -> 0.43608495 | X5: =IF(X$1*MC_Random_N2!$B5>=0.5*MC_Random_N2!$C5,MC_Random_N2!$B5*(1-X$1),0) -> 0.36340412 | Y5: =IF(Y$1*MC_Random_N2!$B5>=0.5*MC_Random_N2!$C5,MC_Random_N2!$B5*(1-Y$1),0) -> 0.2907233 | Z5: =IF(Z$1*MC_Random_N2!$B5>=0.5*MC_Random_N2!$C5,MC_Random_N2!$B5*(1-Z$1),0) -> 0.21804247 | AA5: =IF(AA$1*MC_Random_N2!$B5>=0.5*MC_Random_N2!$C5,MC_Random_N2!$B5*(1-AA$1),0) -> 0.14536165 | ... AC5: =IF(AC$1*MC_Random_N2!$B5>=0.5*MC_Random_N2!$C5,MC_Random_N2!$B5*(1-AC$1),0) -> 0 | AE5: 0.5 | AF5: ES(0.5) | AG5: =AVERAGE(X2:X1001) -> 0.16441459 | AP5: 4 | AQ5: =MAX(AQ$1*MC_Random_N2!$B5,0.5*MC_Random_N2!$C5) -> 0.17755018 | AR5: =MAX(AR$1*MC_Random_N2!$B5,0.5*MC_Random_N2!$C5) -> 0.17755018 | AS5: =MAX(AS$1*MC_Random_N2!$B5,0.5*MC_Random_N2!$C5) -> 0.21804247 | AT5: =MAX(AT$1*MC_Random_N2!$B5,0.5*MC_Random_N2!$C5) -> 0.2907233 | AU5: =MAX(AU$1*MC_Random_N2!$B5,0.5*MC_Random_N2!$C5) -> 0.36340412 | AV5: =MAX(AV$1*MC_Random_N2!$B5,0.5*MC_Random_N2!$C5) -> 0.43608495 | AW5: =MAX(AW$1*MC_Random_N2!$B5,0.5*MC_Random_N2!$C5) -> 0.50876577 | AX5: =MAX(AX$1*MC_Random_N2!$B5,0.5*MC_Random_N2!$C5) -> 0.5814466 | ... AZ5: =MAX(AZ$1*MC_Random_N2!$B5,0.5*MC_Random_N2!$C5) -> 0.72680825 | BB5: 0.5 | BC5: ER(0.5) | BD5: =AVERAGE(AU2:AU1001) -> 0.33432021 | BU5: 4 | BV5: =RAND() -> 0.24079777 | BW5: =(1-1/N_c1)*BV5 -> 0.19263822 | BX5: =IF(BW5=MAX($BW$2:$BW$6),1,0) -> 0 | BY5: =BX5*BW5 -> 0 | BZ5: =BX5*(BV5-BY5) -> 0 | CG5: 4 | CH5: =IF(CH$1*MC_Random_N5!$B5>=0.8*MAX(MC_Random_N5!$C5:$F5),MC_Random_N5!$B5*(1-CH$1),0) -> 0 | CI5: =IF(CI$1*MC_Random_N5!$B5>=0.8*MAX(MC_Random_N5!$C5:$F5),MC_Random_N5!$B5*(1-CI$1),0) -> 0 | CJ5: =IF(CJ$1*MC_Random_N5!$B5>=0.8*MAX(MC_Random_N5!$C5:$F5),MC_Random_N5!$B5*(1-CJ$1),0) -> 0 | CK5: =IF(CK$1*MC_Random_N5!$B5>=0.8*MAX(MC_Random_N5!$C5:$F5),MC_Random_N5!$B5*(1-CK$1),0) -> 0 | CL5: =IF(CL$1*MC_Random_N5!$B5>=0.8*MAX(MC_Random_N5!$C5:$F5),MC_Random_N5!$B5*(1-CL$1),0) -> 0 | CM5: =IF(CM$1*MC_Random_N5!$B5>=0.8*MAX(MC_Random_N5!$C5:$F5),MC_Random_N5!$B5*(1-CM$1),0) -> 0 | CN5: =IF(CN$1*MC_Random_N5!$B5>=0.8*MAX(MC_Random_N5!$C5:$F5),MC_Random_N5!$B5*(1-CN$1),0) -> 0.26721502 | CO5: =IF(CO$1*MC_Random_N5!$B5>=0.8*MAX(MC_Random_N5!$C5:$F5),MC_Random_N5!$B5*(1-CO$1),0) -> 0.17814335 | ... CQ5: =IF(CQ$1*MC_Random_N5!$B5>=0.8*MAX(MC_Random_N5!$C5:$F5),MC_Random_N5!$B5*(1-CQ$1),0) -> 0 | CS5: 0.5 | CT5: ES(0.5) | CU5: =AVERAGE(CL2:CL1001) -> 0.013085082 | DD5: 4 | DE5: =MAX(DE$1*MC_Random_N5!$B5,0.8*MAX(MC_Random_N5!$C5:$F5)) -> 0.59811104 | DF5: =MAX(DF$1*MC_Random_N5!$B5,0.8*MAX(MC_Random_N5!$C5:$F5)) -> 0.59811104 | DG5: =MAX(DG$1*MC_Random_N5!$B5,0.8*MAX(MC_Random_N5!$C5:$F5)) -> 0.59811104 | DH5: =MAX(DH$1*MC_Random_N5!$B5,0.8*MAX(MC_Random_N5!$C5:$F5)) -> 0.59811104 | DI5: =MAX(DI$1*MC_Random_N5!$B5,0.8*MAX(MC_Random_N5!$C5:$F5)) -> 0.59811104 | DJ5: =MAX(DJ$1*MC_Random_N5!$B5,0.8*MAX(MC_Random_N5!$C5:$F5)) -> 0.59811104 | DK5: =MAX(DK$1*MC_Random_N5!$B5,0.8*MAX(MC_Random_N5!$C5:$F5)) -> 0.62350171 | DL5: =MAX(DL$1*MC_Random_N5!$B5,0.8*MAX(MC_Random_N5!$C5:$F5)) -> 0.71257338 | ... DN5: =MAX(DN$1*MC_Random_N5!$B5,0.8*MAX(MC_Random_N5!$C5:$F5)) -> 0.89071673 | DP5: 0.5 | DQ5: ER(0.5) | DR5: =AVERAGE(DI2:DI1001) -> 0.63825017 | DX5: 4 | DY5: =RAND() -> 0.73225255 | DZ5: =(1-1/N_c2)*DY5 -> 0.6590273 | EA5: =IF(DZ5=MAX($DZ$2:$DZ$11),1,0) -> 0 | EB5: =EA5*DZ5 -> 0 | EC5: =EA5*(DY5-EB5) -> 0 | EJ5: 4 | EK5: =IF(EK$1*MC_Random_N10!$B5>=0.9*MAX(MC_Random_N10!$C5:$K5),MC_Random_N10!$B5*(1-EK$1),0) -> 0 | EL5: =IF(EL$1*MC_Random_N10!$B5>=0.9*MAX(MC_Random_N10!$C5:$K5),MC_Random_N10!$B5*(1-EL$1),0) -> 0 | EM5: =IF(EM$1*MC_Random_N10!$B5>=0.9*MAX(MC_Random_N10!$C5:$K5),MC_Random_N10!$B5*(1-EM$1),0) -> 0 | EN5: =IF(EN$1*MC_Random_N10!$B5>=0.9*MAX(MC_Random_N10!$C5:$K5),MC_Random_N10!$B5*(1-EN$1),0) -> 0 | EO5: =IF(EO$1*MC_Random_N10!$B5>=0.9*MAX(MC_Random_N10!$C5:$K5),MC_Random_N10!$B5*(1-EO$1),0) -> 0 | EP5: =IF(EP$1*MC_Random_N10!$B5>=0.9*MAX(MC_Random_N10!$C5:$K5),MC_Random_N10!$B5*(1-EP$1),0) -> 0 | EQ5: =IF(EQ$1*MC_Random_N10!$B5>=0.9*MAX(MC_Random_N10!$C5:$K5),MC_Random_N10!$B5*(1-EQ$1),0) -> 0 | ER5: =IF(ER$1*MC_Random_N10!$B5>=0.9*MAX(MC_Random_N10!$C5:$K5),MC_Random_N10!$B5*(1-ER$1),0) -> 0 | ... ET5: =IF(ET$1*MC_Random_N10!$B5>=0.9*MAX(MC_Random_N10!$C5:$K5),MC_Random_N10!$B5*(1-ET$1),0) -> 0 | EV5: 0.5 | EW5: ES(0.5) | EX5: =AVERAGE(EO2:EO1001) -> 0.00043401312 | FF5: 4 | FG5: =MAX(FG$1*MC_Random_N10!$B5,0.9*MAX(MC_Random_N10!$C5:$K5)) -> 0.80101948 | FH5: =MAX(FH$1*MC_Random_N10!$B5,0.9*MAX(MC_Random_N10!$C5:$K5)) -> 0.80101948 | FI5: =MAX(FI$1*MC_Random_N10!$B5,0.9*MAX(MC_Random_N10!$C5:$K5)) -> 0.80101948 | FJ5: =MAX(FJ$1*MC_Random_N10!$B5,0.9*MAX(MC_Random_N10!$C5:$K5)) -> 0.80101948 | FK5: =MAX(FK$1*MC_Random_N10!$B5,0.9*MAX(MC_Random_N10!$C5:$K5)) -> 0.80101948 | FL5: =MAX(FL$1*MC_Random_N10!$B5,0.9*MAX(MC_Random_N10!$C5:$K5)) -> 0.80101948 | FM5: =MAX(FM$1*MC_Random_N10!$B5,0.9*MAX(MC_Random_N10!$C5:$K5)) -> 0.80101948 | FN5: =MAX(FN$1*MC_Random_N10!$B5,0.9*MAX(MC_Random_N10!$C5:$K5)) -> 0.80101948 | ... FP5: =MAX(FP$1*MC_Random_N10!$B5,0.9*MAX(MC_Random_N10!$C5:$K5)) -> 0.80101948 | FR5: 0.5 | FS5: ER(0.5) | FT5: =AVERAGE(FK2:FK1001) -> 0.80901445
S6: 5 | T6: =IF(T$1*MC_Random_N2!$B6>=0.5*MC_Random_N2!$C6,MC_Random_N2!$B6*(1-T$1),0) -> 0 | U6: =IF(U$1*MC_Random_N2!$B6>=0.5*MC_Random_N2!$C6,MC_Random_N2!$B6*(1-U$1),0) -> 0 | V6: =IF(V$1*MC_Random_N2!$B6>=0.5*MC_Random_N2!$C6,MC_Random_N2!$B6*(1-V$1),0) -> 0 | W6: =IF(W$1*MC_Random_N2!$B6>=0.5*MC_Random_N2!$C6,MC_Random_N2!$B6*(1-W$1),0) -> 0 | X6: =IF(X$1*MC_Random_N2!$B6>=0.5*MC_Random_N2!$C6,MC_Random_N2!$B6*(1-X$1),0) -> 0 | Y6: =IF(Y$1*MC_Random_N2!$B6>=0.5*MC_Random_N2!$C6,MC_Random_N2!$B6*(1-Y$1),0) -> 0.19572457 | Z6: =IF(Z$1*MC_Random_N2!$B6>=0.5*MC_Random_N2!$C6,MC_Random_N2!$B6*(1-Z$1),0) -> 0.14679343 | AA6: =IF(AA$1*MC_Random_N2!$B6>=0.5*MC_Random_N2!$C6,MC_Random_N2!$B6*(1-AA$1),0) -> 0.097862284 | ... AC6: =IF(AC$1*MC_Random_N2!$B6>=0.5*MC_Random_N2!$C6,MC_Random_N2!$B6*(1-AC$1),0) -> 0 | AE6: 0.6 | AF6: ES(0.6) | AG6: =AVERAGE(Y2:Y1001) -> 0.15105112 | AP6: 5 | AQ6: =MAX(AQ$1*MC_Random_N2!$B6,0.5*MC_Random_N2!$C6) -> 0.26560191 | AR6: =MAX(AR$1*MC_Random_N2!$B6,0.5*MC_Random_N2!$C6) -> 0.26560191 | AS6: =MAX(AS$1*MC_Random_N2!$B6,0.5*MC_Random_N2!$C6) -> 0.26560191 | AT6: =MAX(AT$1*MC_Random_N2!$B6,0.5*MC_Random_N2!$C6) -> 0.26560191 | AU6: =MAX(AU$1*MC_Random_N2!$B6,0.5*MC_Random_N2!$C6) -> 0.26560191 | AV6: =MAX(AV$1*MC_Random_N2!$B6,0.5*MC_Random_N2!$C6) -> 0.29358685 | AW6: =MAX(AW$1*MC_Random_N2!$B6,0.5*MC_Random_N2!$C6) -> 0.342518 | AX6: =MAX(AX$1*MC_Random_N2!$B6,0.5*MC_Random_N2!$C6) -> 0.39144914 | ... AZ6: =MAX(AZ$1*MC_Random_N2!$B6,0.5*MC_Random_N2!$C6) -> 0.48931142 | BB6: 0.6 | BC6: ER(0.6) | BD6: =AVERAGE(AV2:AV1001) -> 0.36991817 | BU6: 5 | BV6: =RAND() -> 0.50488258 | BW6: =(1-1/N_c1)*BV6 -> 0.40390606 | BX6: =IF(BW6=MAX($BW$2:$BW$6),1,0) -> 0 | BY6: =BX6*BW6 -> 0 | BZ6: =BX6*(BV6-BY6) -> 0 | CG6: 5 | CH6: =IF(CH$1*MC_Random_N5!$B6>=0.8*MAX(MC_Random_N5!$C6:$F6),MC_Random_N5!$B6*(1-CH$1),0) -> 0 | CI6: =IF(CI$1*MC_Random_N5!$B6>=0.8*MAX(MC_Random_N5!$C6:$F6),MC_Random_N5!$B6*(1-CI$1),0) -> 0 | CJ6: =IF(CJ$1*MC_Random_N5!$B6>=0.8*MAX(MC_Random_N5!$C6:$F6),MC_Random_N5!$B6*(1-CJ$1),0) -> 0 | CK6: =IF(CK$1*MC_Random_N5!$B6>=0.8*MAX(MC_Random_N5!$C6:$F6),MC_Random_N5!$B6*(1-CK$1),0) -> 0 | CL6: =IF(CL$1*MC_Random_N5!$B6>=0.8*MAX(MC_Random_N5!$C6:$F6),MC_Random_N5!$B6*(1-CL$1),0) -> 0 | CM6: =IF(CM$1*MC_Random_N5!$B6>=0.8*MAX(MC_Random_N5!$C6:$F6),MC_Random_N5!$B6*(1-CM$1),0) -> 0.25912016 | CN6: =IF(CN$1*MC_Random_N5!$B6>=0.8*MAX(MC_Random_N5!$C6:$F6),MC_Random_N5!$B6*(1-CN$1),0) -> 0.19434012 | CO6: =IF(CO$1*MC_Random_N5!$B6>=0.8*MAX(MC_Random_N5!$C6:$F6),MC_Random_N5!$B6*(1-CO$1),0) -> 0.12956008 | ... CQ6: =IF(CQ$1*MC_Random_N5!$B6>=0.8*MAX(MC_Random_N5!$C6:$F6),MC_Random_N5!$B6*(1-CQ$1),0) -> 0 | CS6: 0.6 | CT6: ES(0.6) | CU6: =AVERAGE(CM2:CM1001) -> 0.02100506 | DD6: 5 | DE6: =MAX(DE$1*MC_Random_N5!$B6,0.8*MAX(MC_Random_N5!$C6:$F6)) -> 0.32755736 | DF6: =MAX(DF$1*MC_Random_N5!$B6,0.8*MAX(MC_Random_N5!$C6:$F6)) -> 0.32755736 | DG6: =MAX(DG$1*MC_Random_N5!$B6,0.8*MAX(MC_Random_N5!$C6:$F6)) -> 0.32755736 | DH6: =MAX(DH$1*MC_Random_N5!$B6,0.8*MAX(MC_Random_N5!$C6:$F6)) -> 0.32755736 | DI6: =MAX(DI$1*MC_Random_N5!$B6,0.8*MAX(MC_Random_N5!$C6:$F6)) -> 0.32755736 | DJ6: =MAX(DJ$1*MC_Random_N5!$B6,0.8*MAX(MC_Random_N5!$C6:$F6)) -> 0.38868024 | DK6: =MAX(DK$1*MC_Random_N5!$B6,0.8*MAX(MC_Random_N5!$C6:$F6)) -> 0.45346028 | DL6: =MAX(DL$1*MC_Random_N5!$B6,0.8*MAX(MC_Random_N5!$C6:$F6)) -> 0.51824032 | ... DN6: =MAX(DN$1*MC_Random_N5!$B6,0.8*MAX(MC_Random_N5!$C6:$F6)) -> 0.6478004 | DP6: 0.6 | DQ6: ER(0.6) | DR6: =AVERAGE(DJ2:DJ1001) -> 0.64205505 | DX6: 5 | DY6: =RAND() -> 0.73647479 | DZ6: =(1-1/N_c2)*DY6 -> 0.66282732 | EA6: =IF(DZ6=MAX($DZ$2:$DZ$11),1,0) -> 0 | EB6: =EA6*DZ6 -> 0 | EC6: =EA6*(DY6-EB6) -> 0 | EJ6: 5 | EK6: =IF(EK$1*MC_Random_N10!$B6>=0.9*MAX(MC_Random_N10!$C6:$K6),MC_Random_N10!$B6*(1-EK$1),0) -> 0 | EL6: =IF(EL$1*MC_Random_N10!$B6>=0.9*MAX(MC_Random_N10!$C6:$K6),MC_Random_N10!$B6*(1-EL$1),0) -> 0 | EM6: =IF(EM$1*MC_Random_N10!$B6>=0.9*MAX(MC_Random_N10!$C6:$K6),MC_Random_N10!$B6*(1-EM$1),0) -> 0 | EN6: =IF(EN$1*MC_Random_N10!$B6>=0.9*MAX(MC_Random_N10!$C6:$K6),MC_Random_N10!$B6*(1-EN$1),0) -> 0 | EO6: =IF(EO$1*MC_Random_N10!$B6>=0.9*MAX(MC_Random_N10!$C6:$K6),MC_Random_N10!$B6*(1-EO$1),0) -> 0 | EP6: =IF(EP$1*MC_Random_N10!$B6>=0.9*MAX(MC_Random_N10!$C6:$K6),MC_Random_N10!$B6*(1-EP$1),0) -> 0 | EQ6: =IF(EQ$1*MC_Random_N10!$B6>=0.9*MAX(MC_Random_N10!$C6:$K6),MC_Random_N10!$B6*(1-EQ$1),0) -> 0 | ER6: =IF(ER$1*MC_Random_N10!$B6>=0.9*MAX(MC_Random_N10!$C6:$K6),MC_Random_N10!$B6*(1-ER$1),0) -> 0 | ... ET6: =IF(ET$1*MC_Random_N10!$B6>=0.9*MAX(MC_Random_N10!$C6:$K6),MC_Random_N10!$B6*(1-ET$1),0) -> 0 | EV6: 0.6 | EW6: ES(0.6) | EX6: =AVERAGE(EP2:EP1001) -> 0.00074127 | FF6: 5 | FG6: =MAX(FG$1*MC_Random_N10!$B6,0.9*MAX(MC_Random_N10!$C6:$K6)) -> 0.88066064 | FH6: =MAX(FH$1*MC_Random_N10!$B6,0.9*MAX(MC_Random_N10!$C6:$K6)) -> 0.88066064 | FI6: =MAX(FI$1*MC_Random_N10!$B6,0.9*MAX(MC_Random_N10!$C6:$K6)) -> 0.88066064 | FJ6: =MAX(FJ$1*MC_Random_N10!$B6,0.9*MAX(MC_Random_N10!$C6:$K6)) -> 0.88066064 | FK6: =MAX(FK$1*MC_Random_N10!$B6,0.9*MAX(MC_Random_N10!$C6:$K6)) -> 0.88066064 | FL6: =MAX(FL$1*MC_Random_N10!$B6,0.9*MAX(MC_Random_N10!$C6:$K6)) -> 0.88066064 | FM6: =MAX(FM$1*MC_Random_N10!$B6,0.9*MAX(MC_Random_N10!$C6:$K6)) -> 0.88066064 | FN6: =MAX(FN$1*MC_Random_N10!$B6,0.9*MAX(MC_Random_N10!$C6:$K6)) -> 0.88066064 | ... FP6: =MAX(FP$1*MC_Random_N10!$B6,0.9*MAX(MC_Random_N10!$C6:$K6)) -> 0.88066064 | FR6: 0.6 | FS6: ER(0.6) | FT6: =AVERAGE(FL2:FL1001) -> 0.8091578
S7: 6 | T7: =IF(T$1*MC_Random_N2!$B7>=0.5*MC_Random_N2!$C7,MC_Random_N2!$B7*(1-T$1),0) -> 0.88736884 | U7: =IF(U$1*MC_Random_N2!$B7>=0.5*MC_Random_N2!$C7,MC_Random_N2!$B7*(1-U$1),0) -> 0.7887723 | V7: =IF(V$1*MC_Random_N2!$B7>=0.5*MC_Random_N2!$C7,MC_Random_N2!$B7*(1-V$1),0) -> 0.69017576 | W7: =IF(W$1*MC_Random_N2!$B7>=0.5*MC_Random_N2!$C7,MC_Random_N2!$B7*(1-W$1),0) -> 0.59157922 | X7: =IF(X$1*MC_Random_N2!$B7>=0.5*MC_Random_N2!$C7,MC_Random_N2!$B7*(1-X$1),0) -> 0.49298269 | Y7: =IF(Y$1*MC_Random_N2!$B7>=0.5*MC_Random_N2!$C7,MC_Random_N2!$B7*(1-Y$1),0) -> 0.39438615 | Z7: =IF(Z$1*MC_Random_N2!$B7>=0.5*MC_Random_N2!$C7,MC_Random_N2!$B7*(1-Z$1),0) -> 0.29578961 | AA7: =IF(AA$1*MC_Random_N2!$B7>=0.5*MC_Random_N2!$C7,MC_Random_N2!$B7*(1-AA$1),0) -> 0.19719307 | ... AC7: =IF(AC$1*MC_Random_N2!$B7>=0.5*MC_Random_N2!$C7,MC_Random_N2!$B7*(1-AC$1),0) -> 0 | AE7: 0.7 | AF7: ES(0.7) | AG7: =AVERAGE(Z2:Z1001) -> 0.12319928 | AP7: 6 | AQ7: =MAX(AQ$1*MC_Random_N2!$B7,0.5*MC_Random_N2!$C7) -> 0.098596537 | AR7: =MAX(AR$1*MC_Random_N2!$B7,0.5*MC_Random_N2!$C7) -> 0.19719307 | AS7: =MAX(AS$1*MC_Random_N2!$B7,0.5*MC_Random_N2!$C7) -> 0.29578961 | AT7: =MAX(AT$1*MC_Random_N2!$B7,0.5*MC_Random_N2!$C7) -> 0.39438615 | AU7: =MAX(AU$1*MC_Random_N2!$B7,0.5*MC_Random_N2!$C7) -> 0.49298269 | AV7: =MAX(AV$1*MC_Random_N2!$B7,0.5*MC_Random_N2!$C7) -> 0.59157922 | AW7: =MAX(AW$1*MC_Random_N2!$B7,0.5*MC_Random_N2!$C7) -> 0.69017576 | AX7: =MAX(AX$1*MC_Random_N2!$B7,0.5*MC_Random_N2!$C7) -> 0.7887723 | ... AZ7: =MAX(AZ$1*MC_Random_N2!$B7,0.5*MC_Random_N2!$C7) -> 0.98596537 | BB7: 0.7 | BC7: ER(0.7) | BD7: =AVERAGE(AW2:AW1001) -> 0.40943762 | CG7: 6 | CH7: =IF(CH$1*MC_Random_N5!$B7>=0.8*MAX(MC_Random_N5!$C7:$F7),MC_Random_N5!$B7*(1-CH$1),0) -> 0 | CI7: =IF(CI$1*MC_Random_N5!$B7>=0.8*MAX(MC_Random_N5!$C7:$F7),MC_Random_N5!$B7*(1-CI$1),0) -> 0 | CJ7: =IF(CJ$1*MC_Random_N5!$B7>=0.8*MAX(MC_Random_N5!$C7:$F7),MC_Random_N5!$B7*(1-CJ$1),0) -> 0 | CK7: =IF(CK$1*MC_Random_N5!$B7>=0.8*MAX(MC_Random_N5!$C7:$F7),MC_Random_N5!$B7*(1-CK$1),0) -> 0 | CL7: =IF(CL$1*MC_Random_N5!$B7>=0.8*MAX(MC_Random_N5!$C7:$F7),MC_Random_N5!$B7*(1-CL$1),0) -> 0 | CM7: =IF(CM$1*MC_Random_N5!$B7>=0.8*MAX(MC_Random_N5!$C7:$F7),MC_Random_N5!$B7*(1-CM$1),0) -> 0 | CN7: =IF(CN$1*MC_Random_N5!$B7>=0.8*MAX(MC_Random_N5!$C7:$F7),MC_Random_N5!$B7*(1-CN$1),0) -> 0 | CO7: =IF(CO$1*MC_Random_N5!$B7>=0.8*MAX(MC_Random_N5!$C7:$F7),MC_Random_N5!$B7*(1-CO$1),0) -> 0 | ... CQ7: =IF(CQ$1*MC_Random_N5!$B7>=0.8*MAX(MC_Random_N5!$C7:$F7),MC_Random_N5!$B7*(1-CQ$1),0) -> 0 | CS7: 0.7 | CT7: ES(0.7) | CU7: =AVERAGE(CN2:CN1001) -> 0.029544427 | DD7: 6 | DE7: =MAX(DE$1*MC_Random_N5!$B7,0.8*MAX(MC_Random_N5!$C7:$F7)) -> 0.49980532 | DF7: =MAX(DF$1*MC_Random_N5!$B7,0.8*MAX(MC_Random_N5!$C7:$F7)) -> 0.49980532 | DG7: =MAX(DG$1*MC_Random_N5!$B7,0.8*MAX(MC_Random_N5!$C7:$F7)) -> 0.49980532 | DH7: =MAX(DH$1*MC_Random_N5!$B7,0.8*MAX(MC_Random_N5!$C7:$F7)) -> 0.49980532 | DI7: =MAX(DI$1*MC_Random_N5!$B7,0.8*MAX(MC_Random_N5!$C7:$F7)) -> 0.49980532 | DJ7: =MAX(DJ$1*MC_Random_N5!$B7,0.8*MAX(MC_Random_N5!$C7:$F7)) -> 0.49980532 | DK7: =MAX(DK$1*MC_Random_N5!$B7,0.8*MAX(MC_Random_N5!$C7:$F7)) -> 0.49980532 | DL7: =MAX(DL$1*MC_Random_N5!$B7,0.8*MAX(MC_Random_N5!$C7:$F7)) -> 0.49980532 | ... DN7: =MAX(DN$1*MC_Random_N5!$B7,0.8*MAX(MC_Random_N5!$C7:$F7)) -> 0.49980532 | DP7: 0.7 | DQ7: ER(0.7) | DR7: =AVERAGE(DK2:DK1001) -> 0.64947503 | DX7: 6 | DY7: =RAND() -> 0.21911589 | DZ7: =(1-1/N_c2)*DY7 -> 0.1972043 | EA7: =IF(DZ7=MAX($DZ$2:$DZ$11),1,0) -> 0 | EB7: =EA7*DZ7 -> 0 | EC7: =EA7*(DY7-EB7) -> 0 | EJ7: 6 | EK7: =IF(EK$1*MC_Random_N10!$B7>=0.9*MAX(MC_Random_N10!$C7:$K7),MC_Random_N10!$B7*(1-EK$1),0) -> 0 | EL7: =IF(EL$1*MC_Random_N10!$B7>=0.9*MAX(MC_Random_N10!$C7:$K7),MC_Random_N10!$B7*(1-EL$1),0) -> 0 | EM7: =IF(EM$1*MC_Random_N10!$B7>=0.9*MAX(MC_Random_N10!$C7:$K7),MC_Random_N10!$B7*(1-EM$1),0) -> 0 | EN7: =IF(EN$1*MC_Random_N10!$B7>=0.9*MAX(MC_Random_N10!$C7:$K7),MC_Random_N10!$B7*(1-EN$1),0) -> 0 | EO7: =IF(EO$1*MC_Random_N10!$B7>=0.9*MAX(MC_Random_N10!$C7:$K7),MC_Random_N10!$B7*(1-EO$1),0) -> 0 | EP7: =IF(EP$1*MC_Random_N10!$B7>=0.9*MAX(MC_Random_N10!$C7:$K7),MC_Random_N10!$B7*(1-EP$1),0) -> 0 | EQ7: =IF(EQ$1*MC_Random_N10!$B7>=0.9*MAX(MC_Random_N10!$C7:$K7),MC_Random_N10!$B7*(1-EQ$1),0) -> 0 | ER7: =IF(ER$1*MC_Random_N10!$B7>=0.9*MAX(MC_Random_N10!$C7:$K7),MC_Random_N10!$B7*(1-ER$1),0) -> 0 | ... ET7: =IF(ET$1*MC_Random_N10!$B7>=0.9*MAX(MC_Random_N10!$C7:$K7),MC_Random_N10!$B7*(1-ET$1),0) -> 0 | EV7: 0.7 | EW7: ES(0.7) | EX7: =AVERAGE(EQ2:EQ1001) -> 0.0024878134 | FF7: 6 | FG7: =MAX(FG$1*MC_Random_N10!$B7,0.9*MAX(MC_Random_N10!$C7:$K7)) -> 0.76094603 | FH7: =MAX(FH$1*MC_Random_N10!$B7,0.9*MAX(MC_Random_N10!$C7:$K7)) -> 0.76094603 | FI7: =MAX(FI$1*MC_Random_N10!$B7,0.9*MAX(MC_Random_N10!$C7:$K7)) -> 0.76094603 | FJ7: =MAX(FJ$1*MC_Random_N10!$B7,0.9*MAX(MC_Random_N10!$C7:$K7)) -> 0.76094603 | FK7: =MAX(FK$1*MC_Random_N10!$B7,0.9*MAX(MC_Random_N10!$C7:$K7)) -> 0.76094603 | FL7: =MAX(FL$1*MC_Random_N10!$B7,0.9*MAX(MC_Random_N10!$C7:$K7)) -> 0.76094603 | FM7: =MAX(FM$1*MC_Random_N10!$B7,0.9*MAX(MC_Random_N10!$C7:$K7)) -> 0.76094603 | FN7: =MAX(FN$1*MC_Random_N10!$B7,0.9*MAX(MC_Random_N10!$C7:$K7)) -> 0.76094603 | ... FP7: =MAX(FP$1*MC_Random_N10!$B7,0.9*MAX(MC_Random_N10!$C7:$K7)) -> 0.76094603 | FR7: 0.7 | FS7: ER(0.7) | FT7: =AVERAGE(FM2:FM1001) -> 0.80959206
S8: 7 | T8: =IF(T$1*MC_Random_N2!$B8>=0.5*MC_Random_N2!$C8,MC_Random_N2!$B8*(1-T$1),0) -> 0 | U8: =IF(U$1*MC_Random_N2!$B8>=0.5*MC_Random_N2!$C8,MC_Random_N2!$B8*(1-U$1),0) -> 0 | V8: =IF(V$1*MC_Random_N2!$B8>=0.5*MC_Random_N2!$C8,MC_Random_N2!$B8*(1-V$1),0) -> 0.47766553 | W8: =IF(W$1*MC_Random_N2!$B8>=0.5*MC_Random_N2!$C8,MC_Random_N2!$B8*(1-W$1),0) -> 0.4094276 | X8: =IF(X$1*MC_Random_N2!$B8>=0.5*MC_Random_N2!$C8,MC_Random_N2!$B8*(1-X$1),0) -> 0.34118966 | Y8: =IF(Y$1*MC_Random_N2!$B8>=0.5*MC_Random_N2!$C8,MC_Random_N2!$B8*(1-Y$1),0) -> 0.27295173 | Z8: =IF(Z$1*MC_Random_N2!$B8>=0.5*MC_Random_N2!$C8,MC_Random_N2!$B8*(1-Z$1),0) -> 0.2047138 | AA8: =IF(AA$1*MC_Random_N2!$B8>=0.5*MC_Random_N2!$C8,MC_Random_N2!$B8*(1-AA$1),0) -> 0.13647587 | ... AC8: =IF(AC$1*MC_Random_N2!$B8>=0.5*MC_Random_N2!$C8,MC_Random_N2!$B8*(1-AC$1),0) -> 0 | AE8: 0.8 | AF8: ES(0.8) | AG8: =AVERAGE(AA2:AA1001) -> 0.0870401 | AP8: 7 | AQ8: =MAX(AQ$1*MC_Random_N2!$B8,0.5*MC_Random_N2!$C8) -> 0.14516016 | AR8: =MAX(AR$1*MC_Random_N2!$B8,0.5*MC_Random_N2!$C8) -> 0.14516016 | AS8: =MAX(AS$1*MC_Random_N2!$B8,0.5*MC_Random_N2!$C8) -> 0.2047138 | AT8: =MAX(AT$1*MC_Random_N2!$B8,0.5*MC_Random_N2!$C8) -> 0.27295173 | AU8: =MAX(AU$1*MC_Random_N2!$B8,0.5*MC_Random_N2!$C8) -> 0.34118966 | AV8: =MAX(AV$1*MC_Random_N2!$B8,0.5*MC_Random_N2!$C8) -> 0.4094276 | AW8: =MAX(AW$1*MC_Random_N2!$B8,0.5*MC_Random_N2!$C8) -> 0.47766553 | AX8: =MAX(AX$1*MC_Random_N2!$B8,0.5*MC_Random_N2!$C8) -> 0.54590346 | ... AZ8: =MAX(AZ$1*MC_Random_N2!$B8,0.5*MC_Random_N2!$C8) -> 0.68237933 | BB8: 0.8 | BC8: ER(0.8) | BD8: =AVERAGE(AX2:AX1001) -> 0.45189325 | CG8: 7 | CH8: =IF(CH$1*MC_Random_N5!$B8>=0.8*MAX(MC_Random_N5!$C8:$F8),MC_Random_N5!$B8*(1-CH$1),0) -> 0 | CI8: =IF(CI$1*MC_Random_N5!$B8>=0.8*MAX(MC_Random_N5!$C8:$F8),MC_Random_N5!$B8*(1-CI$1),0) -> 0 | CJ8: =IF(CJ$1*MC_Random_N5!$B8>=0.8*MAX(MC_Random_N5!$C8:$F8),MC_Random_N5!$B8*(1-CJ$1),0) -> 0 | CK8: =IF(CK$1*MC_Random_N5!$B8>=0.8*MAX(MC_Random_N5!$C8:$F8),MC_Random_N5!$B8*(1-CK$1),0) -> 0 | CL8: =IF(CL$1*MC_Random_N5!$B8>=0.8*MAX(MC_Random_N5!$C8:$F8),MC_Random_N5!$B8*(1-CL$1),0) -> 0 | CM8: =IF(CM$1*MC_Random_N5!$B8>=0.8*MAX(MC_Random_N5!$C8:$F8),MC_Random_N5!$B8*(1-CM$1),0) -> 0 | CN8: =IF(CN$1*MC_Random_N5!$B8>=0.8*MAX(MC_Random_N5!$C8:$F8),MC_Random_N5!$B8*(1-CN$1),0) -> 0 | CO8: =IF(CO$1*MC_Random_N5!$B8>=0.8*MAX(MC_Random_N5!$C8:$F8),MC_Random_N5!$B8*(1-CO$1),0) -> 0 | ... CQ8: =IF(CQ$1*MC_Random_N5!$B8>=0.8*MAX(MC_Random_N5!$C8:$F8),MC_Random_N5!$B8*(1-CQ$1),0) -> 0 | CS8: 0.8 | CT8: ES(0.8) | CU8: =AVERAGE(CO2:CO1001) -> 0.033928457 | DD8: 7 | DE8: =MAX(DE$1*MC_Random_N5!$B8,0.8*MAX(MC_Random_N5!$C8:$F8)) -> 0.65236069 | DF8: =MAX(DF$1*MC_Random_N5!$B8,0.8*MAX(MC_Random_N5!$C8:$F8)) -> 0.65236069 | DG8: =MAX(DG$1*MC_Random_N5!$B8,0.8*MAX(MC_Random_N5!$C8:$F8)) -> 0.65236069 | DH8: =MAX(DH$1*MC_Random_N5!$B8,0.8*MAX(MC_Random_N5!$C8:$F8)) -> 0.65236069 | DI8: =MAX(DI$1*MC_Random_N5!$B8,0.8*MAX(MC_Random_N5!$C8:$F8)) -> 0.65236069 | DJ8: =MAX(DJ$1*MC_Random_N5!$B8,0.8*MAX(MC_Random_N5!$C8:$F8)) -> 0.65236069 | DK8: =MAX(DK$1*MC_Random_N5!$B8,0.8*MAX(MC_Random_N5!$C8:$F8)) -> 0.65236069 | DL8: =MAX(DL$1*MC_Random_N5!$B8,0.8*MAX(MC_Random_N5!$C8:$F8)) -> 0.65236069 | ... DN8: =MAX(DN$1*MC_Random_N5!$B8,0.8*MAX(MC_Random_N5!$C8:$F8)) -> 0.65236069 | DP8: 0.8 | DQ8: ER(0.8) | DR8: =AVERAGE(DL2:DL1001) -> 0.66273906 | DX8: 7 | DY8: =RAND() -> 0.013467021 | DZ8: =(1-1/N_c2)*DY8 -> 0.012120319 | EA8: =IF(DZ8=MAX($DZ$2:$DZ$11),1,0) -> 0 | EB8: =EA8*DZ8 -> 0 | EC8: =EA8*(DY8-EB8) -> 0 | EJ8: 7 | EK8: =IF(EK$1*MC_Random_N10!$B8>=0.9*MAX(MC_Random_N10!$C8:$K8),MC_Random_N10!$B8*(1-EK$1),0) -> 0 | EL8: =IF(EL$1*MC_Random_N10!$B8>=0.9*MAX(MC_Random_N10!$C8:$K8),MC_Random_N10!$B8*(1-EL$1),0) -> 0 | EM8: =IF(EM$1*MC_Random_N10!$B8>=0.9*MAX(MC_Random_N10!$C8:$K8),MC_Random_N10!$B8*(1-EM$1),0) -> 0 | EN8: =IF(EN$1*MC_Random_N10!$B8>=0.9*MAX(MC_Random_N10!$C8:$K8),MC_Random_N10!$B8*(1-EN$1),0) -> 0 | EO8: =IF(EO$1*MC_Random_N10!$B8>=0.9*MAX(MC_Random_N10!$C8:$K8),MC_Random_N10!$B8*(1-EO$1),0) -> 0 | EP8: =IF(EP$1*MC_Random_N10!$B8>=0.9*MAX(MC_Random_N10!$C8:$K8),MC_Random_N10!$B8*(1-EP$1),0) -> 0 | EQ8: =IF(EQ$1*MC_Random_N10!$B8>=0.9*MAX(MC_Random_N10!$C8:$K8),MC_Random_N10!$B8*(1-EQ$1),0) -> 0 | ER8: =IF(ER$1*MC_Random_N10!$B8>=0.9*MAX(MC_Random_N10!$C8:$K8),MC_Random_N10!$B8*(1-ER$1),0) -> 0 | ... ET8: =IF(ET$1*MC_Random_N10!$B8>=0.9*MAX(MC_Random_N10!$C8:$K8),MC_Random_N10!$B8*(1-ET$1),0) -> 0 | EV8: 0.8 | EW8: ES(0.8) | EX8: =AVERAGE(ER2:ER1001) -> 0.0068866623 | FF8: 7 | FG8: =MAX(FG$1*MC_Random_N10!$B8,0.9*MAX(MC_Random_N10!$C8:$K8)) -> 0.83898814 | FH8: =MAX(FH$1*MC_Random_N10!$B8,0.9*MAX(MC_Random_N10!$C8:$K8)) -> 0.83898814 | FI8: =MAX(FI$1*MC_Random_N10!$B8,0.9*MAX(MC_Random_N10!$C8:$K8)) -> 0.83898814 | FJ8: =MAX(FJ$1*MC_Random_N10!$B8,0.9*MAX(MC_Random_N10!$C8:$K8)) -> 0.83898814 | FK8: =MAX(FK$1*MC_Random_N10!$B8,0.9*MAX(MC_Random_N10!$C8:$K8)) -> 0.83898814 | FL8: =MAX(FL$1*MC_Random_N10!$B8,0.9*MAX(MC_Random_N10!$C8:$K8)) -> 0.83898814 | FM8: =MAX(FM$1*MC_Random_N10!$B8,0.9*MAX(MC_Random_N10!$C8:$K8)) -> 0.83898814 | FN8: =MAX(FN$1*MC_Random_N10!$B8,0.9*MAX(MC_Random_N10!$C8:$K8)) -> 0.83898814 | ... FP8: =MAX(FP$1*MC_Random_N10!$B8,0.9*MAX(MC_Random_N10!$C8:$K8)) -> 0.83898814 | FR8: 0.8 | FS8: ER(0.8) | FT8: =AVERAGE(FN2:FN1001) -> 0.81141921
S9: 8 | T9: =IF(T$1*MC_Random_N2!$B9>=0.5*MC_Random_N2!$C9,MC_Random_N2!$B9*(1-T$1),0) -> 0 | U9: =IF(U$1*MC_Random_N2!$B9>=0.5*MC_Random_N2!$C9,MC_Random_N2!$B9*(1-U$1),0) -> 0 | V9: =IF(V$1*MC_Random_N2!$B9>=0.5*MC_Random_N2!$C9,MC_Random_N2!$B9*(1-V$1),0) -> 0 | W9: =IF(W$1*MC_Random_N2!$B9>=0.5*MC_Random_N2!$C9,MC_Random_N2!$B9*(1-W$1),0) -> 0.57306651 | X9: =IF(X$1*MC_Random_N2!$B9>=0.5*MC_Random_N2!$C9,MC_Random_N2!$B9*(1-X$1),0) -> 0.47755542 | Y9: =IF(Y$1*MC_Random_N2!$B9>=0.5*MC_Random_N2!$C9,MC_Random_N2!$B9*(1-Y$1),0) -> 0.38204434 | Z9: =IF(Z$1*MC_Random_N2!$B9>=0.5*MC_Random_N2!$C9,MC_Random_N2!$B9*(1-Z$1),0) -> 0.28653325 | AA9: =IF(AA$1*MC_Random_N2!$B9>=0.5*MC_Random_N2!$C9,MC_Random_N2!$B9*(1-AA$1),0) -> 0.19102217 | ... AC9: =IF(AC$1*MC_Random_N2!$B9>=0.5*MC_Random_N2!$C9,MC_Random_N2!$B9*(1-AC$1),0) -> 0 | AE9: 0.9 | AF9: ES(0.9) | AG9: =AVERAGE(AB2:AB1001) -> 0.045099016 | AP9: 8 | AQ9: =MAX(AQ$1*MC_Random_N2!$B9,0.5*MC_Random_N2!$C9) -> 0.34595629 | AR9: =MAX(AR$1*MC_Random_N2!$B9,0.5*MC_Random_N2!$C9) -> 0.34595629 | AS9: =MAX(AS$1*MC_Random_N2!$B9,0.5*MC_Random_N2!$C9) -> 0.34595629 | AT9: =MAX(AT$1*MC_Random_N2!$B9,0.5*MC_Random_N2!$C9) -> 0.38204434 | AU9: =MAX(AU$1*MC_Random_N2!$B9,0.5*MC_Random_N2!$C9) -> 0.47755542 | AV9: =MAX(AV$1*MC_Random_N2!$B9,0.5*MC_Random_N2!$C9) -> 0.57306651 | AW9: =MAX(AW$1*MC_Random_N2!$B9,0.5*MC_Random_N2!$C9) -> 0.66857759 | AX9: =MAX(AX$1*MC_Random_N2!$B9,0.5*MC_Random_N2!$C9) -> 0.76408868 | ... AZ9: =MAX(AZ$1*MC_Random_N2!$B9,0.5*MC_Random_N2!$C9) -> 0.95511084 | BB9: 0.9 | BC9: ER(0.9) | BD9: =AVERAGE(AY2:AY1001) -> 0.49636484 | CG9: 8 | CH9: =IF(CH$1*MC_Random_N5!$B9>=0.8*MAX(MC_Random_N5!$C9:$F9),MC_Random_N5!$B9*(1-CH$1),0) -> 0 | CI9: =IF(CI$1*MC_Random_N5!$B9>=0.8*MAX(MC_Random_N5!$C9:$F9),MC_Random_N5!$B9*(1-CI$1),0) -> 0 | CJ9: =IF(CJ$1*MC_Random_N5!$B9>=0.8*MAX(MC_Random_N5!$C9:$F9),MC_Random_N5!$B9*(1-CJ$1),0) -> 0 | CK9: =IF(CK$1*MC_Random_N5!$B9>=0.8*MAX(MC_Random_N5!$C9:$F9),MC_Random_N5!$B9*(1-CK$1),0) -> 0 | CL9: =IF(CL$1*MC_Random_N5!$B9>=0.8*MAX(MC_Random_N5!$C9:$F9),MC_Random_N5!$B9*(1-CL$1),0) -> 0 | CM9: =IF(CM$1*MC_Random_N5!$B9>=0.8*MAX(MC_Random_N5!$C9:$F9),MC_Random_N5!$B9*(1-CM$1),0) -> 0 | CN9: =IF(CN$1*MC_Random_N5!$B9>=0.8*MAX(MC_Random_N5!$C9:$F9),MC_Random_N5!$B9*(1-CN$1),0) -> 0 | CO9: =IF(CO$1*MC_Random_N5!$B9>=0.8*MAX(MC_Random_N5!$C9:$F9),MC_Random_N5!$B9*(1-CO$1),0) -> 0 | ... CQ9: =IF(CQ$1*MC_Random_N5!$B9>=0.8*MAX(MC_Random_N5!$C9:$F9),MC_Random_N5!$B9*(1-CQ$1),0) -> 0 | CS9: 0.9 | CT9: ES(0.9) | CU9: =AVERAGE(CP2:CP1001) -> 0.024814799 | DD9: 8 | DE9: =MAX(DE$1*MC_Random_N5!$B9,0.8*MAX(MC_Random_N5!$C9:$F9)) -> 0.77267871 | DF9: =MAX(DF$1*MC_Random_N5!$B9,0.8*MAX(MC_Random_N5!$C9:$F9)) -> 0.77267871 | DG9: =MAX(DG$1*MC_Random_N5!$B9,0.8*MAX(MC_Random_N5!$C9:$F9)) -> 0.77267871 | DH9: =MAX(DH$1*MC_Random_N5!$B9,0.8*MAX(MC_Random_N5!$C9:$F9)) -> 0.77267871 | DI9: =MAX(DI$1*MC_Random_N5!$B9,0.8*MAX(MC_Random_N5!$C9:$F9)) -> 0.77267871 | DJ9: =MAX(DJ$1*MC_Random_N5!$B9,0.8*MAX(MC_Random_N5!$C9:$F9)) -> 0.77267871 | DK9: =MAX(DK$1*MC_Random_N5!$B9,0.8*MAX(MC_Random_N5!$C9:$F9)) -> 0.77267871 | DL9: =MAX(DL$1*MC_Random_N5!$B9,0.8*MAX(MC_Random_N5!$C9:$F9)) -> 0.77267871 | ... DN9: =MAX(DN$1*MC_Random_N5!$B9,0.8*MAX(MC_Random_N5!$C9:$F9)) -> 0.81113931 | DP9: 0.9 | DQ9: ER(0.9) | DR9: =AVERAGE(DM2:DM1001) -> 0.6837866 | DX9: 8 | DY9: =RAND() -> 0.60106439 | DZ9: =(1-1/N_c2)*DY9 -> 0.54095795 | EA9: =IF(DZ9=MAX($DZ$2:$DZ$11),1,0) -> 0 | EB9: =EA9*DZ9 -> 0 | EC9: =EA9*(DY9-EB9) -> 0 | EJ9: 8 | EK9: =IF(EK$1*MC_Random_N10!$B9>=0.9*MAX(MC_Random_N10!$C9:$K9),MC_Random_N10!$B9*(1-EK$1),0) -> 0 | EL9: =IF(EL$1*MC_Random_N10!$B9>=0.9*MAX(MC_Random_N10!$C9:$K9),MC_Random_N10!$B9*(1-EL$1),0) -> 0 | EM9: =IF(EM$1*MC_Random_N10!$B9>=0.9*MAX(MC_Random_N10!$C9:$K9),MC_Random_N10!$B9*(1-EM$1),0) -> 0 | EN9: =IF(EN$1*MC_Random_N10!$B9>=0.9*MAX(MC_Random_N10!$C9:$K9),MC_Random_N10!$B9*(1-EN$1),0) -> 0 | EO9: =IF(EO$1*MC_Random_N10!$B9>=0.9*MAX(MC_Random_N10!$C9:$K9),MC_Random_N10!$B9*(1-EO$1),0) -> 0 | EP9: =IF(EP$1*MC_Random_N10!$B9>=0.9*MAX(MC_Random_N10!$C9:$K9),MC_Random_N10!$B9*(1-EP$1),0) -> 0 | EQ9: =IF(EQ$1*MC_Random_N10!$B9>=0.9*MAX(MC_Random_N10!$C9:$K9),MC_Random_N10!$B9*(1-EQ$1),0) -> 0 | ER9: =IF(ER$1*MC_Random_N10!$B9>=0.9*MAX(MC_Random_N10!$C9:$K9),MC_Random_N10!$B9*(1-ER$1),0) -> 0 | ... ET9: =IF(ET$1*MC_Random_N10!$B9>=0.9*MAX(MC_Random_N10!$C9:$K9),MC_Random_N10!$B9*(1-ET$1),0) -> 0 | EV9: 0.9 | EW9: ES(0.9) | EX9: =AVERAGE(ES2:ES1001) -> 0.010406304 | FF9: 8 | FG9: =MAX(FG$1*MC_Random_N10!$B9,0.9*MAX(MC_Random_N10!$C9:$K9)) -> 0.80428863 | FH9: =MAX(FH$1*MC_Random_N10!$B9,0.9*MAX(MC_Random_N10!$C9:$K9)) -> 0.80428863 | FI9: =MAX(FI$1*MC_Random_N10!$B9,0.9*MAX(MC_Random_N10!$C9:$K9)) -> 0.80428863 | FJ9: =MAX(FJ$1*MC_Random_N10!$B9,0.9*MAX(MC_Random_N10!$C9:$K9)) -> 0.80428863 | FK9: =MAX(FK$1*MC_Random_N10!$B9,0.9*MAX(MC_Random_N10!$C9:$K9)) -> 0.80428863 | FL9: =MAX(FL$1*MC_Random_N10!$B9,0.9*MAX(MC_Random_N10!$C9:$K9)) -> 0.80428863 | FM9: =MAX(FM$1*MC_Random_N10!$B9,0.9*MAX(MC_Random_N10!$C9:$K9)) -> 0.80428863 | FN9: =MAX(FN$1*MC_Random_N10!$B9,0.9*MAX(MC_Random_N10!$C9:$K9)) -> 0.80428863 | ... FP9: =MAX(FP$1*MC_Random_N10!$B9,0.9*MAX(MC_Random_N10!$C9:$K9)) -> 0.80428863 | FR9: 0.9 | FS9: ER(0.9) | FT9: =AVERAGE(FO2:FO1001) -> 0.8185027
S10: 9 | T10: =IF(T$1*MC_Random_N2!$B10>=0.5*MC_Random_N2!$C10,MC_Random_N2!$B10*(1-T$1),0) -> 0 | U10: =IF(U$1*MC_Random_N2!$B10>=0.5*MC_Random_N2!$C10,MC_Random_N2!$B10*(1-U$1),0) -> 0 | V10: =IF(V$1*MC_Random_N2!$B10>=0.5*MC_Random_N2!$C10,MC_Random_N2!$B10*(1-V$1),0) -> 0 | W10: =IF(W$1*MC_Random_N2!$B10>=0.5*MC_Random_N2!$C10,MC_Random_N2!$B10*(1-W$1),0) -> 0 | X10: =IF(X$1*MC_Random_N2!$B10>=0.5*MC_Random_N2!$C10,MC_Random_N2!$B10*(1-X$1),0) -> 0 | Y10: =IF(Y$1*MC_Random_N2!$B10>=0.5*MC_Random_N2!$C10,MC_Random_N2!$B10*(1-Y$1),0) -> 0 | Z10: =IF(Z$1*MC_Random_N2!$B10>=0.5*MC_Random_N2!$C10,MC_Random_N2!$B10*(1-Z$1),0) -> 0 | AA10: =IF(AA$1*MC_Random_N2!$B10>=0.5*MC_Random_N2!$C10,MC_Random_N2!$B10*(1-AA$1),0) -> 0 | ... AC10: =IF(AC$1*MC_Random_N2!$B10>=0.5*MC_Random_N2!$C10,MC_Random_N2!$B10*(1-AC$1),0) -> 0 | AE10: 1 | AF10: ES(1.0) | AG10: =AVERAGE(AC2:AC1001) -> 0 | AP10: 9 | AQ10: =MAX(AQ$1*MC_Random_N2!$B10,0.5*MC_Random_N2!$C10) -> 0.39306757 | AR10: =MAX(AR$1*MC_Random_N2!$B10,0.5*MC_Random_N2!$C10) -> 0.39306757 | AS10: =MAX(AS$1*MC_Random_N2!$B10,0.5*MC_Random_N2!$C10) -> 0.39306757 | AT10: =MAX(AT$1*MC_Random_N2!$B10,0.5*MC_Random_N2!$C10) -> 0.39306757 | AU10: =MAX(AU$1*MC_Random_N2!$B10,0.5*MC_Random_N2!$C10) -> 0.39306757 | AV10: =MAX(AV$1*MC_Random_N2!$B10,0.5*MC_Random_N2!$C10) -> 0.39306757 | AW10: =MAX(AW$1*MC_Random_N2!$B10,0.5*MC_Random_N2!$C10) -> 0.39306757 | AX10: =MAX(AX$1*MC_Random_N2!$B10,0.5*MC_Random_N2!$C10) -> 0.39306757 | ... AZ10: =MAX(AZ$1*MC_Random_N2!$B10,0.5*MC_Random_N2!$C10) -> 0.39306757 | BB10: 1 | BC10: ER(1.0) | BD10: =AVERAGE(AZ2:AZ1001) -> 0.54186569 | CG10: 9 | CH10: =IF(CH$1*MC_Random_N5!$B10>=0.8*MAX(MC_Random_N5!$C10:$F10),MC_Random_N5!$B10*(1-CH$1),0) -> 0 | CI10: =IF(CI$1*MC_Random_N5!$B10>=0.8*MAX(MC_Random_N5!$C10:$F10),MC_Random_N5!$B10*(1-CI$1),0) -> 0 | CJ10: =IF(CJ$1*MC_Random_N5!$B10>=0.8*MAX(MC_Random_N5!$C10:$F10),MC_Random_N5!$B10*(1-CJ$1),0) -> 0 | CK10: =IF(CK$1*MC_Random_N5!$B10>=0.8*MAX(MC_Random_N5!$C10:$F10),MC_Random_N5!$B10*(1-CK$1),0) -> 0 | CL10: =IF(CL$1*MC_Random_N5!$B10>=0.8*MAX(MC_Random_N5!$C10:$F10),MC_Random_N5!$B10*(1-CL$1),0) -> 0 | CM10: =IF(CM$1*MC_Random_N5!$B10>=0.8*MAX(MC_Random_N5!$C10:$F10),MC_Random_N5!$B10*(1-CM$1),0) -> 0 | CN10: =IF(CN$1*MC_Random_N5!$B10>=0.8*MAX(MC_Random_N5!$C10:$F10),MC_Random_N5!$B10*(1-CN$1),0) -> 0 | CO10: =IF(CO$1*MC_Random_N5!$B10>=0.8*MAX(MC_Random_N5!$C10:$F10),MC_Random_N5!$B10*(1-CO$1),0) -> 0 | ... CQ10: =IF(CQ$1*MC_Random_N5!$B10>=0.8*MAX(MC_Random_N5!$C10:$F10),MC_Random_N5!$B10*(1-CQ$1),0) -> 0 | CS10: 1 | CT10: ES(1.0) | CU10: =AVERAGE(CQ2:CQ1001) -> 0 | DD10: 9 | DE10: =MAX(DE$1*MC_Random_N5!$B10,0.8*MAX(MC_Random_N5!$C10:$F10)) -> 0.43850936 | DF10: =MAX(DF$1*MC_Random_N5!$B10,0.8*MAX(MC_Random_N5!$C10:$F10)) -> 0.43850936 | DG10: =MAX(DG$1*MC_Random_N5!$B10,0.8*MAX(MC_Random_N5!$C10:$F10)) -> 0.43850936 | DH10: =MAX(DH$1*MC_Random_N5!$B10,0.8*MAX(MC_Random_N5!$C10:$F10)) -> 0.43850936 | DI10: =MAX(DI$1*MC_Random_N5!$B10,0.8*MAX(MC_Random_N5!$C10:$F10)) -> 0.43850936 | DJ10: =MAX(DJ$1*MC_Random_N5!$B10,0.8*MAX(MC_Random_N5!$C10:$F10)) -> 0.43850936 | DK10: =MAX(DK$1*MC_Random_N5!$B10,0.8*MAX(MC_Random_N5!$C10:$F10)) -> 0.43850936 | DL10: =MAX(DL$1*MC_Random_N5!$B10,0.8*MAX(MC_Random_N5!$C10:$F10)) -> 0.43850936 | ... DN10: =MAX(DN$1*MC_Random_N5!$B10,0.8*MAX(MC_Random_N5!$C10:$F10)) -> 0.43850936 | DP10: 1 | DQ10: ER(1.0) | DR10: =AVERAGE(DN2:DN1001) -> 0.71135166 | DX10: 9 | DY10: =RAND() -> 0.21076349 | DZ10: =(1-1/N_c2)*DY10 -> 0.18968714 | EA10: =IF(DZ10=MAX($DZ$2:$DZ$11),1,0) -> 0 | EB10: =EA10*DZ10 -> 0 | EC10: =EA10*(DY10-EB10) -> 0 | EJ10: 9 | EK10: =IF(EK$1*MC_Random_N10!$B10>=0.9*MAX(MC_Random_N10!$C10:$K10),MC_Random_N10!$B10*(1-EK$1),0) -> 0 | EL10: =IF(EL$1*MC_Random_N10!$B10>=0.9*MAX(MC_Random_N10!$C10:$K10),MC_Random_N10!$B10*(1-EL$1),0) -> 0 | EM10: =IF(EM$1*MC_Random_N10!$B10>=0.9*MAX(MC_Random_N10!$C10:$K10),MC_Random_N10!$B10*(1-EM$1),0) -> 0 | EN10: =IF(EN$1*MC_Random_N10!$B10>=0.9*MAX(MC_Random_N10!$C10:$K10),MC_Random_N10!$B10*(1-EN$1),0) -> 0 | EO10: =IF(EO$1*MC_Random_N10!$B10>=0.9*MAX(MC_Random_N10!$C10:$K10),MC_Random_N10!$B10*(1-EO$1),0) -> 0 | EP10: =IF(EP$1*MC_Random_N10!$B10>=0.9*MAX(MC_Random_N10!$C10:$K10),MC_Random_N10!$B10*(1-EP$1),0) -> 0 | EQ10: =IF(EQ$1*MC_Random_N10!$B10>=0.9*MAX(MC_Random_N10!$C10:$K10),MC_Random_N10!$B10*(1-EQ$1),0) -> 0 | ER10: =IF(ER$1*MC_Random_N10!$B10>=0.9*MAX(MC_Random_N10!$C10:$K10),MC_Random_N10!$B10*(1-ER$1),0) -> 0 | ... ET10: =IF(ET$1*MC_Random_N10!$B10>=0.9*MAX(MC_Random_N10!$C10:$K10),MC_Random_N10!$B10*(1-ET$1),0) -> 0 | EV10: 1 | EW10: ES(1.0) | EX10: =AVERAGE(ET2:ET1001) -> 0 | FF10: 9 | FG10: =MAX(FG$1*MC_Random_N10!$B10,0.9*MAX(MC_Random_N10!$C10:$K10)) -> 0.85208986 | FH10: =MAX(FH$1*MC_Random_N10!$B10,0.9*MAX(MC_Random_N10!$C10:$K10)) -> 0.85208986 | FI10: =MAX(FI$1*MC_Random_N10!$B10,0.9*MAX(MC_Random_N10!$C10:$K10)) -> 0.85208986 | FJ10: =MAX(FJ$1*MC_Random_N10!$B10,0.9*MAX(MC_Random_N10!$C10:$K10)) -> 0.85208986 | FK10: =MAX(FK$1*MC_Random_N10!$B10,0.9*MAX(MC_Random_N10!$C10:$K10)) -> 0.85208986 | FL10: =MAX(FL$1*MC_Random_N10!$B10,0.9*MAX(MC_Random_N10!$C10:$K10)) -> 0.85208986 | FM10: =MAX(FM$1*MC_Random_N10!$B10,0.9*MAX(MC_Random_N10!$C10:$K10)) -> 0.85208986 | FN10: =MAX(FN$1*MC_Random_N10!$B10,0.9*MAX(MC_Random_N10!$C10:$K10)) -> 0.85208986 | ... FP10: =MAX(FP$1*MC_Random_N10!$B10,0.9*MAX(MC_Random_N10!$C10:$K10)) -> 0.89031891 | FR10: 1 | FS10: ER(1.0) | FT10: =AVERAGE(FP2:FP1001) -> 0.83252644
S11: 10 | T11: =IF(T$1*MC_Random_N2!$B11>=0.5*MC_Random_N2!$C11,MC_Random_N2!$B11*(1-T$1),0) -> 0 | U11: =IF(U$1*MC_Random_N2!$B11>=0.5*MC_Random_N2!$C11,MC_Random_N2!$B11*(1-U$1),0) -> 0 | V11: =IF(V$1*MC_Random_N2!$B11>=0.5*MC_Random_N2!$C11,MC_Random_N2!$B11*(1-V$1),0) -> 0 | W11: =IF(W$1*MC_Random_N2!$B11>=0.5*MC_Random_N2!$C11,MC_Random_N2!$B11*(1-W$1),0) -> 0.45856309 | X11: =IF(X$1*MC_Random_N2!$B11>=0.5*MC_Random_N2!$C11,MC_Random_N2!$B11*(1-X$1),0) -> 0.38213591 | Y11: =IF(Y$1*MC_Random_N2!$B11>=0.5*MC_Random_N2!$C11,MC_Random_N2!$B11*(1-Y$1),0) -> 0.30570873 | Z11: =IF(Z$1*MC_Random_N2!$B11>=0.5*MC_Random_N2!$C11,MC_Random_N2!$B11*(1-Z$1),0) -> 0.22928155 | AA11: =IF(AA$1*MC_Random_N2!$B11>=0.5*MC_Random_N2!$C11,MC_Random_N2!$B11*(1-AA$1),0) -> 0.15285436 | ... AC11: =IF(AC$1*MC_Random_N2!$B11>=0.5*MC_Random_N2!$C11,MC_Random_N2!$B11*(1-AC$1),0) -> 0 | AP11: 10 | AQ11: =MAX(AQ$1*MC_Random_N2!$B11,0.5*MC_Random_N2!$C11) -> 0.26829295 | AR11: =MAX(AR$1*MC_Random_N2!$B11,0.5*MC_Random_N2!$C11) -> 0.26829295 | AS11: =MAX(AS$1*MC_Random_N2!$B11,0.5*MC_Random_N2!$C11) -> 0.26829295 | AT11: =MAX(AT$1*MC_Random_N2!$B11,0.5*MC_Random_N2!$C11) -> 0.30570873 | AU11: =MAX(AU$1*MC_Random_N2!$B11,0.5*MC_Random_N2!$C11) -> 0.38213591 | AV11: =MAX(AV$1*MC_Random_N2!$B11,0.5*MC_Random_N2!$C11) -> 0.45856309 | AW11: =MAX(AW$1*MC_Random_N2!$B11,0.5*MC_Random_N2!$C11) -> 0.53499027 | AX11: =MAX(AX$1*MC_Random_N2!$B11,0.5*MC_Random_N2!$C11) -> 0.61141746 | ... AZ11: =MAX(AZ$1*MC_Random_N2!$B11,0.5*MC_Random_N2!$C11) -> 0.76427182 | CG11: 10 | CH11: =IF(CH$1*MC_Random_N5!$B11>=0.8*MAX(MC_Random_N5!$C11:$F11),MC_Random_N5!$B11*(1-CH$1),0) -> 0 | CI11: =IF(CI$1*MC_Random_N5!$B11>=0.8*MAX(MC_Random_N5!$C11:$F11),MC_Random_N5!$B11*(1-CI$1),0) -> 0 | CJ11: =IF(CJ$1*MC_Random_N5!$B11>=0.8*MAX(MC_Random_N5!$C11:$F11),MC_Random_N5!$B11*(1-CJ$1),0) -> 0 | CK11: =IF(CK$1*MC_Random_N5!$B11>=0.8*MAX(MC_Random_N5!$C11:$F11),MC_Random_N5!$B11*(1-CK$1),0) -> 0 | CL11: =IF(CL$1*MC_Random_N5!$B11>=0.8*MAX(MC_Random_N5!$C11:$F11),MC_Random_N5!$B11*(1-CL$1),0) -> 0 | CM11: =IF(CM$1*MC_Random_N5!$B11>=0.8*MAX(MC_Random_N5!$C11:$F11),MC_Random_N5!$B11*(1-CM$1),0) -> 0 | CN11: =IF(CN$1*MC_Random_N5!$B11>=0.8*MAX(MC_Random_N5!$C11:$F11),MC_Random_N5!$B11*(1-CN$1),0) -> 0 | CO11: =IF(CO$1*MC_Random_N5!$B11>=0.8*MAX(MC_Random_N5!$C11:$F11),MC_Random_N5!$B11*(1-CO$1),0) -> 0 | ... CQ11: =IF(CQ$1*MC_Random_N5!$B11>=0.8*MAX(MC_Random_N5!$C11:$F11),MC_Random_N5!$B11*(1-CQ$1),0) -> 0 | DD11: 10 | DE11: =MAX(DE$1*MC_Random_N5!$B11,0.8*MAX(MC_Random_N5!$C11:$F11)) -> 0.78976558 | DF11: =MAX(DF$1*MC_Random_N5!$B11,0.8*MAX(MC_Random_N5!$C11:$F11)) -> 0.78976558 | DG11: =MAX(DG$1*MC_Random_N5!$B11,0.8*MAX(MC_Random_N5!$C11:$F11)) -> 0.78976558 | DH11: =MAX(DH$1*MC_Random_N5!$B11,0.8*MAX(MC_Random_N5!$C11:$F11)) -> 0.78976558 | DI11: =MAX(DI$1*MC_Random_N5!$B11,0.8*MAX(MC_Random_N5!$C11:$F11)) -> 0.78976558 | DJ11: =MAX(DJ$1*MC_Random_N5!$B11,0.8*MAX(MC_Random_N5!$C11:$F11)) -> 0.78976558 | DK11: =MAX(DK$1*MC_Random_N5!$B11,0.8*MAX(MC_Random_N5!$C11:$F11)) -> 0.78976558 | DL11: =MAX(DL$1*MC_Random_N5!$B11,0.8*MAX(MC_Random_N5!$C11:$F11)) -> 0.78976558 | ... DN11: =MAX(DN$1*MC_Random_N5!$B11,0.8*MAX(MC_Random_N5!$C11:$F11)) -> 0.91541365 | DX11: 10 | DY11: =RAND() -> 0.78859182 | DZ11: =(1-1/N_c2)*DY11 -> 0.70973264 | EA11: =IF(DZ11=MAX($DZ$2:$DZ$11),1,0) -> 0 | EB11: =EA11*DZ11 -> 0 | EC11: =EA11*(DY11-EB11) -> 0 | EJ11: 10 | EK11: =IF(EK$1*MC_Random_N10!$B11>=0.9*MAX(MC_Random_N10!$C11:$K11),MC_Random_N10!$B11*(1-EK$1),0) -> 0 | EL11: =IF(EL$1*MC_Random_N10!$B11>=0.9*MAX(MC_Random_N10!$C11:$K11),MC_Random_N10!$B11*(1-EL$1),0) -> 0 | EM11: =IF(EM$1*MC_Random_N10!$B11>=0.9*MAX(MC_Random_N10!$C11:$K11),MC_Random_N10!$B11*(1-EM$1),0) -> 0 | EN11: =IF(EN$1*MC_Random_N10!$B11>=0.9*MAX(MC_Random_N10!$C11:$K11),MC_Random_N10!$B11*(1-EN$1),0) -> 0 | EO11: =IF(EO$1*MC_Random_N10!$B11>=0.9*MAX(MC_Random_N10!$C11:$K11),MC_Random_N10!$B11*(1-EO$1),0) -> 0 | EP11: =IF(EP$1*MC_Random_N10!$B11>=0.9*MAX(MC_Random_N10!$C11:$K11),MC_Random_N10!$B11*(1-EP$1),0) -> 0 | EQ11: =IF(EQ$1*MC_Random_N10!$B11>=0.9*MAX(MC_Random_N10!$C11:$K11),MC_Random_N10!$B11*(1-EQ$1),0) -> 0 | ER11: =IF(ER$1*MC_Random_N10!$B11>=0.9*MAX(MC_Random_N10!$C11:$K11),MC_Random_N10!$B11*(1-ER$1),0) -> 0 | ... ET11: =IF(ET$1*MC_Random_N10!$B11>=0.9*MAX(MC_Random_N10!$C11:$K11),MC_Random_N10!$B11*(1-ET$1),0) -> 0 | FF11: 10 | FG11: =MAX(FG$1*MC_Random_N10!$B11,0.9*MAX(MC_Random_N10!$C11:$K11)) -> 0.84216379 | FH11: =MAX(FH$1*MC_Random_N10!$B11,0.9*MAX(MC_Random_N10!$C11:$K11)) -> 0.84216379 | FI11: =MAX(FI$1*MC_Random_N10!$B11,0.9*MAX(MC_Random_N10!$C11:$K11)) -> 0.84216379 | FJ11: =MAX(FJ$1*MC_Random_N10!$B11,0.9*MAX(MC_Random_N10!$C11:$K11)) -> 0.84216379 | FK11: =MAX(FK$1*MC_Random_N10!$B11,0.9*MAX(MC_Random_N10!$C11:$K11)) -> 0.84216379 | FL11: =MAX(FL$1*MC_Random_N10!$B11,0.9*MAX(MC_Random_N10!$C11:$K11)) -> 0.84216379 | FM11: =MAX(FM$1*MC_Random_N10!$B11,0.9*MAX(MC_Random_N10!$C11:$K11)) -> 0.84216379 | FN11: =MAX(FN$1*MC_Random_N10!$B11,0.9*MAX(MC_Random_N10!$C11:$K11)) -> 0.84216379 | ... FP11: =MAX(FP$1*MC_Random_N10!$B11,0.9*MAX(MC_Random_N10!$C11:$K11)) -> 0.84216379
S12: 11 | T12: =IF(T$1*MC_Random_N2!$B12>=0.5*MC_Random_N2!$C12,MC_Random_N2!$B12*(1-T$1),0) -> 0 | U12: =IF(U$1*MC_Random_N2!$B12>=0.5*MC_Random_N2!$C12,MC_Random_N2!$B12*(1-U$1),0) -> 0 | V12: =IF(V$1*MC_Random_N2!$B12>=0.5*MC_Random_N2!$C12,MC_Random_N2!$B12*(1-V$1),0) -> 0 | W12: =IF(W$1*MC_Random_N2!$B12>=0.5*MC_Random_N2!$C12,MC_Random_N2!$B12*(1-W$1),0) -> 0 | X12: =IF(X$1*MC_Random_N2!$B12>=0.5*MC_Random_N2!$C12,MC_Random_N2!$B12*(1-X$1),0) -> 0 | Y12: =IF(Y$1*MC_Random_N2!$B12>=0.5*MC_Random_N2!$C12,MC_Random_N2!$B12*(1-Y$1),0) -> 0 | Z12: =IF(Z$1*MC_Random_N2!$B12>=0.5*MC_Random_N2!$C12,MC_Random_N2!$B12*(1-Z$1),0) -> 0 | AA12: =IF(AA$1*MC_Random_N2!$B12>=0.5*MC_Random_N2!$C12,MC_Random_N2!$B12*(1-AA$1),0) -> 0.11559351 | ... AC12: =IF(AC$1*MC_Random_N2!$B12>=0.5*MC_Random_N2!$C12,MC_Random_N2!$B12*(1-AC$1),0) -> 0 | AP12: 11 | AQ12: =MAX(AQ$1*MC_Random_N2!$B12,0.5*MC_Random_N2!$C12) -> 0.44795704 | AR12: =MAX(AR$1*MC_Random_N2!$B12,0.5*MC_Random_N2!$C12) -> 0.44795704 | AS12: =MAX(AS$1*MC_Random_N2!$B12,0.5*MC_Random_N2!$C12) -> 0.44795704 | AT12: =MAX(AT$1*MC_Random_N2!$B12,0.5*MC_Random_N2!$C12) -> 0.44795704 | AU12: =MAX(AU$1*MC_Random_N2!$B12,0.5*MC_Random_N2!$C12) -> 0.44795704 | AV12: =MAX(AV$1*MC_Random_N2!$B12,0.5*MC_Random_N2!$C12) -> 0.44795704 | AW12: =MAX(AW$1*MC_Random_N2!$B12,0.5*MC_Random_N2!$C12) -> 0.44795704 | AX12: =MAX(AX$1*MC_Random_N2!$B12,0.5*MC_Random_N2!$C12) -> 0.46237403 | ... AZ12: =MAX(AZ$1*MC_Random_N2!$B12,0.5*MC_Random_N2!$C12) -> 0.57796753 | BC12: avg_ER(x) | BD12: =AVERAGE(BD1:BD10) -> 0.37114081 | CG12: 11 | CH12: =IF(CH$1*MC_Random_N5!$B12>=0.8*MAX(MC_Random_N5!$C12:$F12),MC_Random_N5!$B12*(1-CH$1),0) -> 0 | CI12: =IF(CI$1*MC_Random_N5!$B12>=0.8*MAX(MC_Random_N5!$C12:$F12),MC_Random_N5!$B12*(1-CI$1),0) -> 0 | CJ12: =IF(CJ$1*MC_Random_N5!$B12>=0.8*MAX(MC_Random_N5!$C12:$F12),MC_Random_N5!$B12*(1-CJ$1),0) -> 0 | CK12: =IF(CK$1*MC_Random_N5!$B12>=0.8*MAX(MC_Random_N5!$C12:$F12),MC_Random_N5!$B12*(1-CK$1),0) -> 0 | CL12: =IF(CL$1*MC_Random_N5!$B12>=0.8*MAX(MC_Random_N5!$C12:$F12),MC_Random_N5!$B12*(1-CL$1),0) -> 0 | CM12: =IF(CM$1*MC_Random_N5!$B12>=0.8*MAX(MC_Random_N5!$C12:$F12),MC_Random_N5!$B12*(1-CM$1),0) -> 0 | CN12: =IF(CN$1*MC_Random_N5!$B12>=0.8*MAX(MC_Random_N5!$C12:$F12),MC_Random_N5!$B12*(1-CN$1),0) -> 0 | CO12: =IF(CO$1*MC_Random_N5!$B12>=0.8*MAX(MC_Random_N5!$C12:$F12),MC_Random_N5!$B12*(1-CO$1),0) -> 0.19727434 | ... CQ12: =IF(CQ$1*MC_Random_N5!$B12>=0.8*MAX(MC_Random_N5!$C12:$F12),MC_Random_N5!$B12*(1-CQ$1),0) -> 0 | DD12: 11 | DE12: =MAX(DE$1*MC_Random_N5!$B12,0.8*MAX(MC_Random_N5!$C12:$F12)) -> 0.78583431 | DF12: =MAX(DF$1*MC_Random_N5!$B12,0.8*MAX(MC_Random_N5!$C12:$F12)) -> 0.78583431 | DG12: =MAX(DG$1*MC_Random_N5!$B12,0.8*MAX(MC_Random_N5!$C12:$F12)) -> 0.78583431 | DH12: =MAX(DH$1*MC_Random_N5!$B12,0.8*MAX(MC_Random_N5!$C12:$F12)) -> 0.78583431 | DI12: =MAX(DI$1*MC_Random_N5!$B12,0.8*MAX(MC_Random_N5!$C12:$F12)) -> 0.78583431 | DJ12: =MAX(DJ$1*MC_Random_N5!$B12,0.8*MAX(MC_Random_N5!$C12:$F12)) -> 0.78583431 | DK12: =MAX(DK$1*MC_Random_N5!$B12,0.8*MAX(MC_Random_N5!$C12:$F12)) -> 0.78583431 | DL12: =MAX(DL$1*MC_Random_N5!$B12,0.8*MAX(MC_Random_N5!$C12:$F12)) -> 0.78909737 | ... DN12: =MAX(DN$1*MC_Random_N5!$B12,0.8*MAX(MC_Random_N5!$C12:$F12)) -> 0.98637172 | DQ12: avg_ER(x) | DR12: =AVERAGE(DR1:DR10) -> 0.65313282 | EJ12: 11 | EK12: =IF(EK$1*MC_Random_N10!$B12>=0.9*MAX(MC_Random_N10!$C12:$K12),MC_Random_N10!$B12*(1-EK$1),0) -> 0 | EL12: =IF(EL$1*MC_Random_N10!$B12>=0.9*MAX(MC_Random_N10!$C12:$K12),MC_Random_N10!$B12*(1-EL$1),0) -> 0 | EM12: =IF(EM$1*MC_Random_N10!$B12>=0.9*MAX(MC_Random_N10!$C12:$K12),MC_Random_N10!$B12*(1-EM$1),0) -> 0 | EN12: =IF(EN$1*MC_Random_N10!$B12>=0.9*MAX(MC_Random_N10!$C12:$K12),MC_Random_N10!$B12*(1-EN$1),0) -> 0 | EO12: =IF(EO$1*MC_Random_N10!$B12>=0.9*MAX(MC_Random_N10!$C12:$K12),MC_Random_N10!$B12*(1-EO$1),0) -> 0 | EP12: =IF(EP$1*MC_Random_N10!$B12>=0.9*MAX(MC_Random_N10!$C12:$K12),MC_Random_N10!$B12*(1-EP$1),0) -> 0 | EQ12: =IF(EQ$1*MC_Random_N10!$B12>=0.9*MAX(MC_Random_N10!$C12:$K12),MC_Random_N10!$B12*(1-EQ$1),0) -> 0 | ER12: =IF(ER$1*MC_Random_N10!$B12>=0.9*MAX(MC_Random_N10!$C12:$K12),MC_Random_N10!$B12*(1-ER$1),0) -> 0 | ... ET12: =IF(ET$1*MC_Random_N10!$B12>=0.9*MAX(MC_Random_N10!$C12:$K12),MC_Random_N10!$B12*(1-ET$1),0) -> 0 | FF12: 11 | FG12: =MAX(FG$1*MC_Random_N10!$B12,0.9*MAX(MC_Random_N10!$C12:$K12)) -> 0.87659419 | FH12: =MAX(FH$1*MC_Random_N10!$B12,0.9*MAX(MC_Random_N10!$C12:$K12)) -> 0.87659419 | FI12: =MAX(FI$1*MC_Random_N10!$B12,0.9*MAX(MC_Random_N10!$C12:$K12)) -> 0.87659419 | FJ12: =MAX(FJ$1*MC_Random_N10!$B12,0.9*MAX(MC_Random_N10!$C12:$K12)) -> 0.87659419 | FK12: =MAX(FK$1*MC_Random_N10!$B12,0.9*MAX(MC_Random_N10!$C12:$K12)) -> 0.87659419 | FL12: =MAX(FL$1*MC_Random_N10!$B12,0.9*MAX(MC_Random_N10!$C12:$K12)) -> 0.87659419 | FM12: =MAX(FM$1*MC_Random_N10!$B12,0.9*MAX(MC_Random_N10!$C12:$K12)) -> 0.87659419 | FN12: =MAX(FN$1*MC_Random_N10!$B12,0.9*MAX(MC_Random_N10!$C12:$K12)) -> 0.87659419 | ... FP12: =MAX(FP$1*MC_Random_N10!$B12,0.9*MAX(MC_Random_N10!$C12:$K12)) -> 0.87659419 | FS12: avg_ER(x) | FT12: =AVERAGE(FT1:FT10) -> 0.81261448
S13: 12 | T13: =IF(T$1*MC_Random_N2!$B13>=0.5*MC_Random_N2!$C13,MC_Random_N2!$B13*(1-T$1),0) -> 0 | U13: =IF(U$1*MC_Random_N2!$B13>=0.5*MC_Random_N2!$C13,MC_Random_N2!$B13*(1-U$1),0) -> 0 | V13: =IF(V$1*MC_Random_N2!$B13>=0.5*MC_Random_N2!$C13,MC_Random_N2!$B13*(1-V$1),0) -> 0 | W13: =IF(W$1*MC_Random_N2!$B13>=0.5*MC_Random_N2!$C13,MC_Random_N2!$B13*(1-W$1),0) -> 0 | X13: =IF(X$1*MC_Random_N2!$B13>=0.5*MC_Random_N2!$C13,MC_Random_N2!$B13*(1-X$1),0) -> 0 | Y13: =IF(Y$1*MC_Random_N2!$B13>=0.5*MC_Random_N2!$C13,MC_Random_N2!$B13*(1-Y$1),0) -> 0 | Z13: =IF(Z$1*MC_Random_N2!$B13>=0.5*MC_Random_N2!$C13,MC_Random_N2!$B13*(1-Z$1),0) -> 0 | AA13: =IF(AA$1*MC_Random_N2!$B13>=0.5*MC_Random_N2!$C13,MC_Random_N2!$B13*(1-AA$1),0) -> 0.13219847 | ... AC13: =IF(AC$1*MC_Random_N2!$B13>=0.5*MC_Random_N2!$C13,MC_Random_N2!$B13*(1-AC$1),0) -> 0 | AP13: 12 | AQ13: =MAX(AQ$1*MC_Random_N2!$B13,0.5*MC_Random_N2!$C13) -> 0.46396525 | AR13: =MAX(AR$1*MC_Random_N2!$B13,0.5*MC_Random_N2!$C13) -> 0.46396525 | AS13: =MAX(AS$1*MC_Random_N2!$B13,0.5*MC_Random_N2!$C13) -> 0.46396525 | AT13: =MAX(AT$1*MC_Random_N2!$B13,0.5*MC_Random_N2!$C13) -> 0.46396525 | AU13: =MAX(AU$1*MC_Random_N2!$B13,0.5*MC_Random_N2!$C13) -> 0.46396525 | AV13: =MAX(AV$1*MC_Random_N2!$B13,0.5*MC_Random_N2!$C13) -> 0.46396525 | AW13: =MAX(AW$1*MC_Random_N2!$B13,0.5*MC_Random_N2!$C13) -> 0.46396525 | AX13: =MAX(AX$1*MC_Random_N2!$B13,0.5*MC_Random_N2!$C13) -> 0.52879389 | ... AZ13: =MAX(AZ$1*MC_Random_N2!$B13,0.5*MC_Random_N2!$C13) -> 0.66099236 | BC13: max_ER(x) | BD13: =MAX(BD1:BD10) -> 0.54186569 | CG13: 12 | CH13: =IF(CH$1*MC_Random_N5!$B13>=0.8*MAX(MC_Random_N5!$C13:$F13),MC_Random_N5!$B13*(1-CH$1),0) -> 0 | CI13: =IF(CI$1*MC_Random_N5!$B13>=0.8*MAX(MC_Random_N5!$C13:$F13),MC_Random_N5!$B13*(1-CI$1),0) -> 0 | CJ13: =IF(CJ$1*MC_Random_N5!$B13>=0.8*MAX(MC_Random_N5!$C13:$F13),MC_Random_N5!$B13*(1-CJ$1),0) -> 0 | CK13: =IF(CK$1*MC_Random_N5!$B13>=0.8*MAX(MC_Random_N5!$C13:$F13),MC_Random_N5!$B13*(1-CK$1),0) -> 0 | CL13: =IF(CL$1*MC_Random_N5!$B13>=0.8*MAX(MC_Random_N5!$C13:$F13),MC_Random_N5!$B13*(1-CL$1),0) -> 0 | CM13: =IF(CM$1*MC_Random_N5!$B13>=0.8*MAX(MC_Random_N5!$C13:$F13),MC_Random_N5!$B13*(1-CM$1),0) -> 0 | CN13: =IF(CN$1*MC_Random_N5!$B13>=0.8*MAX(MC_Random_N5!$C13:$F13),MC_Random_N5!$B13*(1-CN$1),0) -> 0 | CO13: =IF(CO$1*MC_Random_N5!$B13>=0.8*MAX(MC_Random_N5!$C13:$F13),MC_Random_N5!$B13*(1-CO$1),0) -> 0 | ... CQ13: =IF(CQ$1*MC_Random_N5!$B13>=0.8*MAX(MC_Random_N5!$C13:$F13),MC_Random_N5!$B13*(1-CQ$1),0) -> 0 | DD13: 12 | DE13: =MAX(DE$1*MC_Random_N5!$B13,0.8*MAX(MC_Random_N5!$C13:$F13)) -> 0.6224244 | DF13: =MAX(DF$1*MC_Random_N5!$B13,0.8*MAX(MC_Random_N5!$C13:$F13)) -> 0.6224244 | DG13: =MAX(DG$1*MC_Random_N5!$B13,0.8*MAX(MC_Random_N5!$C13:$F13)) -> 0.6224244 | DH13: =MAX(DH$1*MC_Random_N5!$B13,0.8*MAX(MC_Random_N5!$C13:$F13)) -> 0.6224244 | DI13: =MAX(DI$1*MC_Random_N5!$B13,0.8*MAX(MC_Random_N5!$C13:$F13)) -> 0.6224244 | DJ13: =MAX(DJ$1*MC_Random_N5!$B13,0.8*MAX(MC_Random_N5!$C13:$F13)) -> 0.6224244 | DK13: =MAX(DK$1*MC_Random_N5!$B13,0.8*MAX(MC_Random_N5!$C13:$F13)) -> 0.6224244 | DL13: =MAX(DL$1*MC_Random_N5!$B13,0.8*MAX(MC_Random_N5!$C13:$F13)) -> 0.6224244 | ... DN13: =MAX(DN$1*MC_Random_N5!$B13,0.8*MAX(MC_Random_N5!$C13:$F13)) -> 0.6224244 | DQ13: max_ER(x) | DR13: =MAX(DR1:DR10) -> 0.71135166 | EJ13: 12 | EK13: =IF(EK$1*MC_Random_N10!$B13>=0.9*MAX(MC_Random_N10!$C13:$K13),MC_Random_N10!$B13*(1-EK$1),0) -> 0 | EL13: =IF(EL$1*MC_Random_N10!$B13>=0.9*MAX(MC_Random_N10!$C13:$K13),MC_Random_N10!$B13*(1-EL$1),0) -> 0 | EM13: =IF(EM$1*MC_Random_N10!$B13>=0.9*MAX(MC_Random_N10!$C13:$K13),MC_Random_N10!$B13*(1-EM$1),0) -> 0 | EN13: =IF(EN$1*MC_Random_N10!$B13>=0.9*MAX(MC_Random_N10!$C13:$K13),MC_Random_N10!$B13*(1-EN$1),0) -> 0 | EO13: =IF(EO$1*MC_Random_N10!$B13>=0.9*MAX(MC_Random_N10!$C13:$K13),MC_Random_N10!$B13*(1-EO$1),0) -> 0 | EP13: =IF(EP$1*MC_Random_N10!$B13>=0.9*MAX(MC_Random_N10!$C13:$K13),MC_Random_N10!$B13*(1-EP$1),0) -> 0 | EQ13: =IF(EQ$1*MC_Random_N10!$B13>=0.9*MAX(MC_Random_N10!$C13:$K13),MC_Random_N10!$B13*(1-EQ$1),0) -> 0 | ER13: =IF(ER$1*MC_Random_N10!$B13>=0.9*MAX(MC_Random_N10!$C13:$K13),MC_Random_N10!$B13*(1-ER$1),0) -> 0 | ... ET13: =IF(ET$1*MC_Random_N10!$B13>=0.9*MAX(MC_Random_N10!$C13:$K13),MC_Random_N10!$B13*(1-ET$1),0) -> 0 | FF13: 12 | FG13: =MAX(FG$1*MC_Random_N10!$B13,0.9*MAX(MC_Random_N10!$C13:$K13)) -> 0.84700603 | FH13: =MAX(FH$1*MC_Random_N10!$B13,0.9*MAX(MC_Random_N10!$C13:$K13)) -> 0.84700603 | FI13: =MAX(FI$1*MC_Random_N10!$B13,0.9*MAX(MC_Random_N10!$C13:$K13)) -> 0.84700603 | FJ13: =MAX(FJ$1*MC_Random_N10!$B13,0.9*MAX(MC_Random_N10!$C13:$K13)) -> 0.84700603 | FK13: =MAX(FK$1*MC_Random_N10!$B13,0.9*MAX(MC_Random_N10!$C13:$K13)) -> 0.84700603 | FL13: =MAX(FL$1*MC_Random_N10!$B13,0.9*MAX(MC_Random_N10!$C13:$K13)) -> 0.84700603 | FM13: =MAX(FM$1*MC_Random_N10!$B13,0.9*MAX(MC_Random_N10!$C13:$K13)) -> 0.84700603 | FN13: =MAX(FN$1*MC_Random_N10!$B13,0.9*MAX(MC_Random_N10!$C13:$K13)) -> 0.84700603 | ... FP13: =MAX(FP$1*MC_Random_N10!$B13,0.9*MAX(MC_Random_N10!$C13:$K13)) -> 0.84700603 | FS13: max_ER(x) | FT13: =MAX(FT1:FT10) -> 0.83252644
S14: 13 | T14: =IF(T$1*MC_Random_N2!$B14>=0.5*MC_Random_N2!$C14,MC_Random_N2!$B14*(1-T$1),0) -> 0 | U14: =IF(U$1*MC_Random_N2!$B14>=0.5*MC_Random_N2!$C14,MC_Random_N2!$B14*(1-U$1),0) -> 0 | V14: =IF(V$1*MC_Random_N2!$B14>=0.5*MC_Random_N2!$C14,MC_Random_N2!$B14*(1-V$1),0) -> 0 | W14: =IF(W$1*MC_Random_N2!$B14>=0.5*MC_Random_N2!$C14,MC_Random_N2!$B14*(1-W$1),0) -> 0 | X14: =IF(X$1*MC_Random_N2!$B14>=0.5*MC_Random_N2!$C14,MC_Random_N2!$B14*(1-X$1),0) -> 0 | Y14: =IF(Y$1*MC_Random_N2!$B14>=0.5*MC_Random_N2!$C14,MC_Random_N2!$B14*(1-Y$1),0) -> 0 | Z14: =IF(Z$1*MC_Random_N2!$B14>=0.5*MC_Random_N2!$C14,MC_Random_N2!$B14*(1-Z$1),0) -> 0 | AA14: =IF(AA$1*MC_Random_N2!$B14>=0.5*MC_Random_N2!$C14,MC_Random_N2!$B14*(1-AA$1),0) -> 0 | ... AC14: =IF(AC$1*MC_Random_N2!$B14>=0.5*MC_Random_N2!$C14,MC_Random_N2!$B14*(1-AC$1),0) -> 0 | AF14: max(S1(x)) | AG14: =MAX(AG1:AG10) -> 0.16441459 | AP14: 13 | AQ14: =MAX(AQ$1*MC_Random_N2!$B14,0.5*MC_Random_N2!$C14) -> 0.32590134 | AR14: =MAX(AR$1*MC_Random_N2!$B14,0.5*MC_Random_N2!$C14) -> 0.32590134 | AS14: =MAX(AS$1*MC_Random_N2!$B14,0.5*MC_Random_N2!$C14) -> 0.32590134 | AT14: =MAX(AT$1*MC_Random_N2!$B14,0.5*MC_Random_N2!$C14) -> 0.32590134 | AU14: =MAX(AU$1*MC_Random_N2!$B14,0.5*MC_Random_N2!$C14) -> 0.32590134 | AV14: =MAX(AV$1*MC_Random_N2!$B14,0.5*MC_Random_N2!$C14) -> 0.32590134 | AW14: =MAX(AW$1*MC_Random_N2!$B14,0.5*MC_Random_N2!$C14) -> 0.32590134 | AX14: =MAX(AX$1*MC_Random_N2!$B14,0.5*MC_Random_N2!$C14) -> 0.32590134 | ... AZ14: =MAX(AZ$1*MC_Random_N2!$B14,0.5*MC_Random_N2!$C14) -> 0.32590134 | CG14: 13 | CH14: =IF(CH$1*MC_Random_N5!$B14>=0.8*MAX(MC_Random_N5!$C14:$F14),MC_Random_N5!$B14*(1-CH$1),0) -> 0 | CI14: =IF(CI$1*MC_Random_N5!$B14>=0.8*MAX(MC_Random_N5!$C14:$F14),MC_Random_N5!$B14*(1-CI$1),0) -> 0 | CJ14: =IF(CJ$1*MC_Random_N5!$B14>=0.8*MAX(MC_Random_N5!$C14:$F14),MC_Random_N5!$B14*(1-CJ$1),0) -> 0 | CK14: =IF(CK$1*MC_Random_N5!$B14>=0.8*MAX(MC_Random_N5!$C14:$F14),MC_Random_N5!$B14*(1-CK$1),0) -> 0 | CL14: =IF(CL$1*MC_Random_N5!$B14>=0.8*MAX(MC_Random_N5!$C14:$F14),MC_Random_N5!$B14*(1-CL$1),0) -> 0 | CM14: =IF(CM$1*MC_Random_N5!$B14>=0.8*MAX(MC_Random_N5!$C14:$F14),MC_Random_N5!$B14*(1-CM$1),0) -> 0 | CN14: =IF(CN$1*MC_Random_N5!$B14>=0.8*MAX(MC_Random_N5!$C14:$F14),MC_Random_N5!$B14*(1-CN$1),0) -> 0 | CO14: =IF(CO$1*MC_Random_N5!$B14>=0.8*MAX(MC_Random_N5!$C14:$F14),MC_Random_N5!$B14*(1-CO$1),0) -> 0 | ... CQ14: =IF(CQ$1*MC_Random_N5!$B14>=0.8*MAX(MC_Random_N5!$C14:$F14),MC_Random_N5!$B14*(1-CQ$1),0) -> 0 | CT14: max(S1(x)) | CU14: =MAX(CU1:CU10) -> 0.033928457 | DD14: 13 | DE14: =MAX(DE$1*MC_Random_N5!$B14,0.8*MAX(MC_Random_N5!$C14:$F14)) -> 0.75913587 | DF14: =MAX(DF$1*MC_Random_N5!$B14,0.8*MAX(MC_Random_N5!$C14:$F14)) -> 0.75913587 | DG14: =MAX(DG$1*MC_Random_N5!$B14,0.8*MAX(MC_Random_N5!$C14:$F14)) -> 0.75913587 | DH14: =MAX(DH$1*MC_Random_N5!$B14,0.8*MAX(MC_Random_N5!$C14:$F14)) -> 0.75913587 | DI14: =MAX(DI$1*MC_Random_N5!$B14,0.8*MAX(MC_Random_N5!$C14:$F14)) -> 0.75913587 | DJ14: =MAX(DJ$1*MC_Random_N5!$B14,0.8*MAX(MC_Random_N5!$C14:$F14)) -> 0.75913587 | DK14: =MAX(DK$1*MC_Random_N5!$B14,0.8*MAX(MC_Random_N5!$C14:$F14)) -> 0.75913587 | DL14: =MAX(DL$1*MC_Random_N5!$B14,0.8*MAX(MC_Random_N5!$C14:$F14)) -> 0.75913587 | ... DN14: =MAX(DN$1*MC_Random_N5!$B14,0.8*MAX(MC_Random_N5!$C14:$F14)) -> 0.94635773 | EJ14: 13 | EK14: =IF(EK$1*MC_Random_N10!$B14>=0.9*MAX(MC_Random_N10!$C14:$K14),MC_Random_N10!$B14*(1-EK$1),0) -> 0 | EL14: =IF(EL$1*MC_Random_N10!$B14>=0.9*MAX(MC_Random_N10!$C14:$K14),MC_Random_N10!$B14*(1-EL$1),0) -> 0 | EM14: =IF(EM$1*MC_Random_N10!$B14>=0.9*MAX(MC_Random_N10!$C14:$K14),MC_Random_N10!$B14*(1-EM$1),0) -> 0 | EN14: =IF(EN$1*MC_Random_N10!$B14>=0.9*MAX(MC_Random_N10!$C14:$K14),MC_Random_N10!$B14*(1-EN$1),0) -> 0 | EO14: =IF(EO$1*MC_Random_N10!$B14>=0.9*MAX(MC_Random_N10!$C14:$K14),MC_Random_N10!$B14*(1-EO$1),0) -> 0 | EP14: =IF(EP$1*MC_Random_N10!$B14>=0.9*MAX(MC_Random_N10!$C14:$K14),MC_Random_N10!$B14*(1-EP$1),0) -> 0 | EQ14: =IF(EQ$1*MC_Random_N10!$B14>=0.9*MAX(MC_Random_N10!$C14:$K14),MC_Random_N10!$B14*(1-EQ$1),0) -> 0 | ER14: =IF(ER$1*MC_Random_N10!$B14>=0.9*MAX(MC_Random_N10!$C14:$K14),MC_Random_N10!$B14*(1-ER$1),0) -> 0.19513064 | ... ET14: =IF(ET$1*MC_Random_N10!$B14>=0.9*MAX(MC_Random_N10!$C14:$K14),MC_Random_N10!$B14*(1-ET$1),0) -> 0 | EW14: max(S1(x)) | EX14: =MAX(EX1:EX10) -> 0.010406304 | FF14: 13 | FG14: =MAX(FG$1*MC_Random_N10!$B14,0.9*MAX(MC_Random_N10!$C14:$K14)) -> 0.74456865 | FH14: =MAX(FH$1*MC_Random_N10!$B14,0.9*MAX(MC_Random_N10!$C14:$K14)) -> 0.74456865 | FI14: =MAX(FI$1*MC_Random_N10!$B14,0.9*MAX(MC_Random_N10!$C14:$K14)) -> 0.74456865 | FJ14: =MAX(FJ$1*MC_Random_N10!$B14,0.9*MAX(MC_Random_N10!$C14:$K14)) -> 0.74456865 | FK14: =MAX(FK$1*MC_Random_N10!$B14,0.9*MAX(MC_Random_N10!$C14:$K14)) -> 0.74456865 | FL14: =MAX(FL$1*MC_Random_N10!$B14,0.9*MAX(MC_Random_N10!$C14:$K14)) -> 0.74456865 | FM14: =MAX(FM$1*MC_Random_N10!$B14,0.9*MAX(MC_Random_N10!$C14:$K14)) -> 0.74456865 | FN14: =MAX(FN$1*MC_Random_N10!$B14,0.9*MAX(MC_Random_N10!$C14:$K14)) -> 0.78052256 | ... FP14: =MAX(FP$1*MC_Random_N10!$B14,0.9*MAX(MC_Random_N10!$C14:$K14)) -> 0.9756532
S15: 14 | T15: =IF(T$1*MC_Random_N2!$B15>=0.5*MC_Random_N2!$C15,MC_Random_N2!$B15*(1-T$1),0) -> 0 | U15: =IF(U$1*MC_Random_N2!$B15>=0.5*MC_Random_N2!$C15,MC_Random_N2!$B15*(1-U$1),0) -> 0 | V15: =IF(V$1*MC_Random_N2!$B15>=0.5*MC_Random_N2!$C15,MC_Random_N2!$B15*(1-V$1),0) -> 0.070271062 | W15: =IF(W$1*MC_Random_N2!$B15>=0.5*MC_Random_N2!$C15,MC_Random_N2!$B15*(1-W$1),0) -> 0.060232339 | X15: =IF(X$1*MC_Random_N2!$B15>=0.5*MC_Random_N2!$C15,MC_Random_N2!$B15*(1-X$1),0) -> 0.050193616 | Y15: =IF(Y$1*MC_Random_N2!$B15>=0.5*MC_Random_N2!$C15,MC_Random_N2!$B15*(1-Y$1),0) -> 0.040154893 | Z15: =IF(Z$1*MC_Random_N2!$B15>=0.5*MC_Random_N2!$C15,MC_Random_N2!$B15*(1-Z$1),0) -> 0.030116169 | AA15: =IF(AA$1*MC_Random_N2!$B15>=0.5*MC_Random_N2!$C15,MC_Random_N2!$B15*(1-AA$1),0) -> 0.020077446 | ... AC15: =IF(AC$1*MC_Random_N2!$B15>=0.5*MC_Random_N2!$C15,MC_Random_N2!$B15*(1-AC$1),0) -> 0 | AF15: id | AG15: =MATCH(AG14,AG1:AG10,0) -> 5 | AP15: 14 | AQ15: =MAX(AQ$1*MC_Random_N2!$B15,0.5*MC_Random_N2!$C15) -> 0.028048885 | AR15: =MAX(AR$1*MC_Random_N2!$B15,0.5*MC_Random_N2!$C15) -> 0.028048885 | AS15: =MAX(AS$1*MC_Random_N2!$B15,0.5*MC_Random_N2!$C15) -> 0.030116169 | AT15: =MAX(AT$1*MC_Random_N2!$B15,0.5*MC_Random_N2!$C15) -> 0.040154893 | AU15: =MAX(AU$1*MC_Random_N2!$B15,0.5*MC_Random_N2!$C15) -> 0.050193616 | AV15: =MAX(AV$1*MC_Random_N2!$B15,0.5*MC_Random_N2!$C15) -> 0.060232339 | AW15: =MAX(AW$1*MC_Random_N2!$B15,0.5*MC_Random_N2!$C15) -> 0.070271062 | AX15: =MAX(AX$1*MC_Random_N2!$B15,0.5*MC_Random_N2!$C15) -> 0.080309785 | ... AZ15: =MAX(AZ$1*MC_Random_N2!$B15,0.5*MC_Random_N2!$C15) -> 0.10038723 | CG15: 14 | CH15: =IF(CH$1*MC_Random_N5!$B15>=0.8*MAX(MC_Random_N5!$C15:$F15),MC_Random_N5!$B15*(1-CH$1),0) -> 0 | CI15: =IF(CI$1*MC_Random_N5!$B15>=0.8*MAX(MC_Random_N5!$C15:$F15),MC_Random_N5!$B15*(1-CI$1),0) -> 0 | CJ15: =IF(CJ$1*MC_Random_N5!$B15>=0.8*MAX(MC_Random_N5!$C15:$F15),MC_Random_N5!$B15*(1-CJ$1),0) -> 0 | CK15: =IF(CK$1*MC_Random_N5!$B15>=0.8*MAX(MC_Random_N5!$C15:$F15),MC_Random_N5!$B15*(1-CK$1),0) -> 0 | CL15: =IF(CL$1*MC_Random_N5!$B15>=0.8*MAX(MC_Random_N5!$C15:$F15),MC_Random_N5!$B15*(1-CL$1),0) -> 0 | CM15: =IF(CM$1*MC_Random_N5!$B15>=0.8*MAX(MC_Random_N5!$C15:$F15),MC_Random_N5!$B15*(1-CM$1),0) -> 0 | CN15: =IF(CN$1*MC_Random_N5!$B15>=0.8*MAX(MC_Random_N5!$C15:$F15),MC_Random_N5!$B15*(1-CN$1),0) -> 0 | CO15: =IF(CO$1*MC_Random_N5!$B15>=0.8*MAX(MC_Random_N5!$C15:$F15),MC_Random_N5!$B15*(1-CO$1),0) -> 0 | ... CQ15: =IF(CQ$1*MC_Random_N5!$B15>=0.8*MAX(MC_Random_N5!$C15:$F15),MC_Random_N5!$B15*(1-CQ$1),0) -> 0 | CT15: id | CU15: =MATCH(CU14,CU1:CU10,0) -> 8 | DD15: 14 | DE15: =MAX(DE$1*MC_Random_N5!$B15,0.8*MAX(MC_Random_N5!$C15:$F15)) -> 0.79857179 | DF15: =MAX(DF$1*MC_Random_N5!$B15,0.8*MAX(MC_Random_N5!$C15:$F15)) -> 0.79857179 | DG15: =MAX(DG$1*MC_Random_N5!$B15,0.8*MAX(MC_Random_N5!$C15:$F15)) -> 0.79857179 | DH15: =MAX(DH$1*MC_Random_N5!$B15,0.8*MAX(MC_Random_N5!$C15:$F15)) -> 0.79857179 | DI15: =MAX(DI$1*MC_Random_N5!$B15,0.8*MAX(MC_Random_N5!$C15:$F15)) -> 0.79857179 | DJ15: =MAX(DJ$1*MC_Random_N5!$B15,0.8*MAX(MC_Random_N5!$C15:$F15)) -> 0.79857179 | DK15: =MAX(DK$1*MC_Random_N5!$B15,0.8*MAX(MC_Random_N5!$C15:$F15)) -> 0.79857179 | DL15: =MAX(DL$1*MC_Random_N5!$B15,0.8*MAX(MC_Random_N5!$C15:$F15)) -> 0.79857179 | ... DN15: =MAX(DN$1*MC_Random_N5!$B15,0.8*MAX(MC_Random_N5!$C15:$F15)) -> 0.79857179 | EJ15: 14 | EK15: =IF(EK$1*MC_Random_N10!$B15>=0.9*MAX(MC_Random_N10!$C15:$K15),MC_Random_N10!$B15*(1-EK$1),0) -> 0 | EL15: =IF(EL$1*MC_Random_N10!$B15>=0.9*MAX(MC_Random_N10!$C15:$K15),MC_Random_N10!$B15*(1-EL$1),0) -> 0 | EM15: =IF(EM$1*MC_Random_N10!$B15>=0.9*MAX(MC_Random_N10!$C15:$K15),MC_Random_N10!$B15*(1-EM$1),0) -> 0 | EN15: =IF(EN$1*MC_Random_N10!$B15>=0.9*MAX(MC_Random_N10!$C15:$K15),MC_Random_N10!$B15*(1-EN$1),0) -> 0 | EO15: =IF(EO$1*MC_Random_N10!$B15>=0.9*MAX(MC_Random_N10!$C15:$K15),MC_Random_N10!$B15*(1-EO$1),0) -> 0 | EP15: =IF(EP$1*MC_Random_N10!$B15>=0.9*MAX(MC_Random_N10!$C15:$K15),MC_Random_N10!$B15*(1-EP$1),0) -> 0 | EQ15: =IF(EQ$1*MC_Random_N10!$B15>=0.9*MAX(MC_Random_N10!$C15:$K15),MC_Random_N10!$B15*(1-EQ$1),0) -> 0 | ER15: =IF(ER$1*MC_Random_N10!$B15>=0.9*MAX(MC_Random_N10!$C15:$K15),MC_Random_N10!$B15*(1-ER$1),0) -> 0 | ... ET15: =IF(ET$1*MC_Random_N10!$B15>=0.9*MAX(MC_Random_N10!$C15:$K15),MC_Random_N10!$B15*(1-ET$1),0) -> 0 | EW15: id | EX15: =MATCH(EX14,EX1:EX10,0) -> 9 | FF15: 14 | FG15: =MAX(FG$1*MC_Random_N10!$B15,0.9*MAX(MC_Random_N10!$C15:$K15)) -> 0.86727282 | FH15: =MAX(FH$1*MC_Random_N10!$B15,0.9*MAX(MC_Random_N10!$C15:$K15)) -> 0.86727282 | FI15: =MAX(FI$1*MC_Random_N10!$B15,0.9*MAX(MC_Random_N10!$C15:$K15)) -> 0.86727282 | FJ15: =MAX(FJ$1*MC_Random_N10!$B15,0.9*MAX(MC_Random_N10!$C15:$K15)) -> 0.86727282 | FK15: =MAX(FK$1*MC_Random_N10!$B15,0.9*MAX(MC_Random_N10!$C15:$K15)) -> 0.86727282 | FL15: =MAX(FL$1*MC_Random_N10!$B15,0.9*MAX(MC_Random_N10!$C15:$K15)) -> 0.86727282 | FM15: =MAX(FM$1*MC_Random_N10!$B15,0.9*MAX(MC_Random_N10!$C15:$K15)) -> 0.86727282 | FN15: =MAX(FN$1*MC_Random_N10!$B15,0.9*MAX(MC_Random_N10!$C15:$K15)) -> 0.86727282 | ... FP15: =MAX(FP$1*MC_Random_N10!$B15,0.9*MAX(MC_Random_N10!$C15:$K15)) -> 0.86727282
S16: 15 | T16: =IF(T$1*MC_Random_N2!$B16>=0.5*MC_Random_N2!$C16,MC_Random_N2!$B16*(1-T$1),0) -> 0 | U16: =IF(U$1*MC_Random_N2!$B16>=0.5*MC_Random_N2!$C16,MC_Random_N2!$B16*(1-U$1),0) -> 0 | V16: =IF(V$1*MC_Random_N2!$B16>=0.5*MC_Random_N2!$C16,MC_Random_N2!$B16*(1-V$1),0) -> 0 | W16: =IF(W$1*MC_Random_N2!$B16>=0.5*MC_Random_N2!$C16,MC_Random_N2!$B16*(1-W$1),0) -> 0 | X16: =IF(X$1*MC_Random_N2!$B16>=0.5*MC_Random_N2!$C16,MC_Random_N2!$B16*(1-X$1),0) -> 0 | Y16: =IF(Y$1*MC_Random_N2!$B16>=0.5*MC_Random_N2!$C16,MC_Random_N2!$B16*(1-Y$1),0) -> 0 | Z16: =IF(Z$1*MC_Random_N2!$B16>=0.5*MC_Random_N2!$C16,MC_Random_N2!$B16*(1-Z$1),0) -> 0 | AA16: =IF(AA$1*MC_Random_N2!$B16>=0.5*MC_Random_N2!$C16,MC_Random_N2!$B16*(1-AA$1),0) -> 0 | ... AC16: =IF(AC$1*MC_Random_N2!$B16>=0.5*MC_Random_N2!$C16,MC_Random_N2!$B16*(1-AC$1),0) -> 0 | AF16: x* | AG16: {=INDEX(AE1:AE10,AG15)} -> 0.5 | AP16: 15 | AQ16: =MAX(AQ$1*MC_Random_N2!$B16,0.5*MC_Random_N2!$C16) -> 0.48743578 | AR16: =MAX(AR$1*MC_Random_N2!$B16,0.5*MC_Random_N2!$C16) -> 0.48743578 | AS16: =MAX(AS$1*MC_Random_N2!$B16,0.5*MC_Random_N2!$C16) -> 0.48743578 | AT16: =MAX(AT$1*MC_Random_N2!$B16,0.5*MC_Random_N2!$C16) -> 0.48743578 | AU16: =MAX(AU$1*MC_Random_N2!$B16,0.5*MC_Random_N2!$C16) -> 0.48743578 | AV16: =MAX(AV$1*MC_Random_N2!$B16,0.5*MC_Random_N2!$C16) -> 0.48743578 | AW16: =MAX(AW$1*MC_Random_N2!$B16,0.5*MC_Random_N2!$C16) -> 0.48743578 | AX16: =MAX(AX$1*MC_Random_N2!$B16,0.5*MC_Random_N2!$C16) -> 0.48743578 | ... AZ16: =MAX(AZ$1*MC_Random_N2!$B16,0.5*MC_Random_N2!$C16) -> 0.53001136 | CG16: 15 | CH16: =IF(CH$1*MC_Random_N5!$B16>=0.8*MAX(MC_Random_N5!$C16:$F16),MC_Random_N5!$B16*(1-CH$1),0) -> 0 | CI16: =IF(CI$1*MC_Random_N5!$B16>=0.8*MAX(MC_Random_N5!$C16:$F16),MC_Random_N5!$B16*(1-CI$1),0) -> 0 | CJ16: =IF(CJ$1*MC_Random_N5!$B16>=0.8*MAX(MC_Random_N5!$C16:$F16),MC_Random_N5!$B16*(1-CJ$1),0) -> 0 | CK16: =IF(CK$1*MC_Random_N5!$B16>=0.8*MAX(MC_Random_N5!$C16:$F16),MC_Random_N5!$B16*(1-CK$1),0) -> 0 | CL16: =IF(CL$1*MC_Random_N5!$B16>=0.8*MAX(MC_Random_N5!$C16:$F16),MC_Random_N5!$B16*(1-CL$1),0) -> 0 | CM16: =IF(CM$1*MC_Random_N5!$B16>=0.8*MAX(MC_Random_N5!$C16:$F16),MC_Random_N5!$B16*(1-CM$1),0) -> 0 | CN16: =IF(CN$1*MC_Random_N5!$B16>=0.8*MAX(MC_Random_N5!$C16:$F16),MC_Random_N5!$B16*(1-CN$1),0) -> 0 | CO16: =IF(CO$1*MC_Random_N5!$B16>=0.8*MAX(MC_Random_N5!$C16:$F16),MC_Random_N5!$B16*(1-CO$1),0) -> 0 | ... CQ16: =IF(CQ$1*MC_Random_N5!$B16>=0.8*MAX(MC_Random_N5!$C16:$F16),MC_Random_N5!$B16*(1-CQ$1),0) -> 0 | CT16: x* | CU16: {=INDEX(CS1:CS10,CU15)} -> 0.8 | DD16: 15 | DE16: =MAX(DE$1*MC_Random_N5!$B16,0.8*MAX(MC_Random_N5!$C16:$F16)) -> 0.56161567 | DF16: =MAX(DF$1*MC_Random_N5!$B16,0.8*MAX(MC_Random_N5!$C16:$F16)) -> 0.56161567 | DG16: =MAX(DG$1*MC_Random_N5!$B16,0.8*MAX(MC_Random_N5!$C16:$F16)) -> 0.56161567 | DH16: =MAX(DH$1*MC_Random_N5!$B16,0.8*MAX(MC_Random_N5!$C16:$F16)) -> 0.56161567 | DI16: =MAX(DI$1*MC_Random_N5!$B16,0.8*MAX(MC_Random_N5!$C16:$F16)) -> 0.56161567 | DJ16: =MAX(DJ$1*MC_Random_N5!$B16,0.8*MAX(MC_Random_N5!$C16:$F16)) -> 0.56161567 | DK16: =MAX(DK$1*MC_Random_N5!$B16,0.8*MAX(MC_Random_N5!$C16:$F16)) -> 0.56161567 | DL16: =MAX(DL$1*MC_Random_N5!$B16,0.8*MAX(MC_Random_N5!$C16:$F16)) -> 0.56161567 | ... DN16: =MAX(DN$1*MC_Random_N5!$B16,0.8*MAX(MC_Random_N5!$C16:$F16)) -> 0.56161567 | EJ16: 15 | EK16: =IF(EK$1*MC_Random_N10!$B16>=0.9*MAX(MC_Random_N10!$C16:$K16),MC_Random_N10!$B16*(1-EK$1),0) -> 0 | EL16: =IF(EL$1*MC_Random_N10!$B16>=0.9*MAX(MC_Random_N10!$C16:$K16),MC_Random_N10!$B16*(1-EL$1),0) -> 0 | EM16: =IF(EM$1*MC_Random_N10!$B16>=0.9*MAX(MC_Random_N10!$C16:$K16),MC_Random_N10!$B16*(1-EM$1),0) -> 0 | EN16: =IF(EN$1*MC_Random_N10!$B16>=0.9*MAX(MC_Random_N10!$C16:$K16),MC_Random_N10!$B16*(1-EN$1),0) -> 0 | EO16: =IF(EO$1*MC_Random_N10!$B16>=0.9*MAX(MC_Random_N10!$C16:$K16),MC_Random_N10!$B16*(1-EO$1),0) -> 0 | EP16: =IF(EP$1*MC_Random_N10!$B16>=0.9*MAX(MC_Random_N10!$C16:$K16),MC_Random_N10!$B16*(1-EP$1),0) -> 0 | EQ16: =IF(EQ$1*MC_Random_N10!$B16>=0.9*MAX(MC_Random_N10!$C16:$K16),MC_Random_N10!$B16*(1-EQ$1),0) -> 0 | ER16: =IF(ER$1*MC_Random_N10!$B16>=0.9*MAX(MC_Random_N10!$C16:$K16),MC_Random_N10!$B16*(1-ER$1),0) -> 0 | ... ET16: =IF(ET$1*MC_Random_N10!$B16>=0.9*MAX(MC_Random_N10!$C16:$K16),MC_Random_N10!$B16*(1-ET$1),0) -> 0 | EW16: x* | EX16: {=INDEX(EV1:EV10,EX15)} -> 0.9 | FF16: 15 | FG16: =MAX(FG$1*MC_Random_N10!$B16,0.9*MAX(MC_Random_N10!$C16:$K16)) -> 0.75816681 | FH16: =MAX(FH$1*MC_Random_N10!$B16,0.9*MAX(MC_Random_N10!$C16:$K16)) -> 0.75816681 | FI16: =MAX(FI$1*MC_Random_N10!$B16,0.9*MAX(MC_Random_N10!$C16:$K16)) -> 0.75816681 | FJ16: =MAX(FJ$1*MC_Random_N10!$B16,0.9*MAX(MC_Random_N10!$C16:$K16)) -> 0.75816681 | FK16: =MAX(FK$1*MC_Random_N10!$B16,0.9*MAX(MC_Random_N10!$C16:$K16)) -> 0.75816681 | FL16: =MAX(FL$1*MC_Random_N10!$B16,0.9*MAX(MC_Random_N10!$C16:$K16)) -> 0.75816681 | FM16: =MAX(FM$1*MC_Random_N10!$B16,0.9*MAX(MC_Random_N10!$C16:$K16)) -> 0.75816681 | FN16: =MAX(FN$1*MC_Random_N10!$B16,0.9*MAX(MC_Random_N10!$C16:$K16)) -> 0.75816681 | ... FP16: =MAX(FP$1*MC_Random_N10!$B16,0.9*MAX(MC_Random_N10!$C16:$K16)) -> 0.77068689
S17: 16 | T17: =IF(T$1*MC_Random_N2!$B17>=0.5*MC_Random_N2!$C17,MC_Random_N2!$B17*(1-T$1),0) -> 0 | U17: =IF(U$1*MC_Random_N2!$B17>=0.5*MC_Random_N2!$C17,MC_Random_N2!$B17*(1-U$1),0) -> 0 | V17: =IF(V$1*MC_Random_N2!$B17>=0.5*MC_Random_N2!$C17,MC_Random_N2!$B17*(1-V$1),0) -> 0 | W17: =IF(W$1*MC_Random_N2!$B17>=0.5*MC_Random_N2!$C17,MC_Random_N2!$B17*(1-W$1),0) -> 0 | X17: =IF(X$1*MC_Random_N2!$B17>=0.5*MC_Random_N2!$C17,MC_Random_N2!$B17*(1-X$1),0) -> 0 | Y17: =IF(Y$1*MC_Random_N2!$B17>=0.5*MC_Random_N2!$C17,MC_Random_N2!$B17*(1-Y$1),0) -> 0 | Z17: =IF(Z$1*MC_Random_N2!$B17>=0.5*MC_Random_N2!$C17,MC_Random_N2!$B17*(1-Z$1),0) -> 0 | AA17: =IF(AA$1*MC_Random_N2!$B17>=0.5*MC_Random_N2!$C17,MC_Random_N2!$B17*(1-AA$1),0) -> 0 | ... AC17: =IF(AC$1*MC_Random_N2!$B17>=0.5*MC_Random_N2!$C17,MC_Random_N2!$B17*(1-AC$1),0) -> 0 | AP17: 16 | AQ17: =MAX(AQ$1*MC_Random_N2!$B17,0.5*MC_Random_N2!$C17) -> 0.27480449 | AR17: =MAX(AR$1*MC_Random_N2!$B17,0.5*MC_Random_N2!$C17) -> 0.27480449 | AS17: =MAX(AS$1*MC_Random_N2!$B17,0.5*MC_Random_N2!$C17) -> 0.27480449 | AT17: =MAX(AT$1*MC_Random_N2!$B17,0.5*MC_Random_N2!$C17) -> 0.27480449 | AU17: =MAX(AU$1*MC_Random_N2!$B17,0.5*MC_Random_N2!$C17) -> 0.27480449 | AV17: =MAX(AV$1*MC_Random_N2!$B17,0.5*MC_Random_N2!$C17) -> 0.27480449 | AW17: =MAX(AW$1*MC_Random_N2!$B17,0.5*MC_Random_N2!$C17) -> 0.27480449 | AX17: =MAX(AX$1*MC_Random_N2!$B17,0.5*MC_Random_N2!$C17) -> 0.27480449 | ... AZ17: =MAX(AZ$1*MC_Random_N2!$B17,0.5*MC_Random_N2!$C17) -> 0.27480449 | CG17: 16 | CH17: =IF(CH$1*MC_Random_N5!$B17>=0.8*MAX(MC_Random_N5!$C17:$F17),MC_Random_N5!$B17*(1-CH$1),0) -> 0 | CI17: =IF(CI$1*MC_Random_N5!$B17>=0.8*MAX(MC_Random_N5!$C17:$F17),MC_Random_N5!$B17*(1-CI$1),0) -> 0 | CJ17: =IF(CJ$1*MC_Random_N5!$B17>=0.8*MAX(MC_Random_N5!$C17:$F17),MC_Random_N5!$B17*(1-CJ$1),0) -> 0 | CK17: =IF(CK$1*MC_Random_N5!$B17>=0.8*MAX(MC_Random_N5!$C17:$F17),MC_Random_N5!$B17*(1-CK$1),0) -> 0 | CL17: =IF(CL$1*MC_Random_N5!$B17>=0.8*MAX(MC_Random_N5!$C17:$F17),MC_Random_N5!$B17*(1-CL$1),0) -> 0 | CM17: =IF(CM$1*MC_Random_N5!$B17>=0.8*MAX(MC_Random_N5!$C17:$F17),MC_Random_N5!$B17*(1-CM$1),0) -> 0 | CN17: =IF(CN$1*MC_Random_N5!$B17>=0.8*MAX(MC_Random_N5!$C17:$F17),MC_Random_N5!$B17*(1-CN$1),0) -> 0.29562507 | CO17: =IF(CO$1*MC_Random_N5!$B17>=0.8*MAX(MC_Random_N5!$C17:$F17),MC_Random_N5!$B17*(1-CO$1),0) -> 0.19708338 | ... CQ17: =IF(CQ$1*MC_Random_N5!$B17>=0.8*MAX(MC_Random_N5!$C17:$F17),MC_Random_N5!$B17*(1-CQ$1),0) -> 0 | DD17: 16 | DE17: =MAX(DE$1*MC_Random_N5!$B17,0.8*MAX(MC_Random_N5!$C17:$F17)) -> 0.6813691 | DF17: =MAX(DF$1*MC_Random_N5!$B17,0.8*MAX(MC_Random_N5!$C17:$F17)) -> 0.6813691 | DG17: =MAX(DG$1*MC_Random_N5!$B17,0.8*MAX(MC_Random_N5!$C17:$F17)) -> 0.6813691 | DH17: =MAX(DH$1*MC_Random_N5!$B17,0.8*MAX(MC_Random_N5!$C17:$F17)) -> 0.6813691 | DI17: =MAX(DI$1*MC_Random_N5!$B17,0.8*MAX(MC_Random_N5!$C17:$F17)) -> 0.6813691 | DJ17: =MAX(DJ$1*MC_Random_N5!$B17,0.8*MAX(MC_Random_N5!$C17:$F17)) -> 0.6813691 | DK17: =MAX(DK$1*MC_Random_N5!$B17,0.8*MAX(MC_Random_N5!$C17:$F17)) -> 0.68979183 | DL17: =MAX(DL$1*MC_Random_N5!$B17,0.8*MAX(MC_Random_N5!$C17:$F17)) -> 0.78833352 | ... DN17: =MAX(DN$1*MC_Random_N5!$B17,0.8*MAX(MC_Random_N5!$C17:$F17)) -> 0.9854169 | EJ17: 16 | EK17: =IF(EK$1*MC_Random_N10!$B17>=0.9*MAX(MC_Random_N10!$C17:$K17),MC_Random_N10!$B17*(1-EK$1),0) -> 0 | EL17: =IF(EL$1*MC_Random_N10!$B17>=0.9*MAX(MC_Random_N10!$C17:$K17),MC_Random_N10!$B17*(1-EL$1),0) -> 0 | EM17: =IF(EM$1*MC_Random_N10!$B17>=0.9*MAX(MC_Random_N10!$C17:$K17),MC_Random_N10!$B17*(1-EM$1),0) -> 0 | EN17: =IF(EN$1*MC_Random_N10!$B17>=0.9*MAX(MC_Random_N10!$C17:$K17),MC_Random_N10!$B17*(1-EN$1),0) -> 0 | EO17: =IF(EO$1*MC_Random_N10!$B17>=0.9*MAX(MC_Random_N10!$C17:$K17),MC_Random_N10!$B17*(1-EO$1),0) -> 0 | EP17: =IF(EP$1*MC_Random_N10!$B17>=0.9*MAX(MC_Random_N10!$C17:$K17),MC_Random_N10!$B17*(1-EP$1),0) -> 0 | EQ17: =IF(EQ$1*MC_Random_N10!$B17>=0.9*MAX(MC_Random_N10!$C17:$K17),MC_Random_N10!$B17*(1-EQ$1),0) -> 0 | ER17: =IF(ER$1*MC_Random_N10!$B17>=0.9*MAX(MC_Random_N10!$C17:$K17),MC_Random_N10!$B17*(1-ER$1),0) -> 0 | ... ET17: =IF(ET$1*MC_Random_N10!$B17>=0.9*MAX(MC_Random_N10!$C17:$K17),MC_Random_N10!$B17*(1-ET$1),0) -> 0 | FF17: 16 | FG17: =MAX(FG$1*MC_Random_N10!$B17,0.9*MAX(MC_Random_N10!$C17:$K17)) -> 0.87804242 | FH17: =MAX(FH$1*MC_Random_N10!$B17,0.9*MAX(MC_Random_N10!$C17:$K17)) -> 0.87804242 | FI17: =MAX(FI$1*MC_Random_N10!$B17,0.9*MAX(MC_Random_N10!$C17:$K17)) -> 0.87804242 | FJ17: =MAX(FJ$1*MC_Random_N10!$B17,0.9*MAX(MC_Random_N10!$C17:$K17)) -> 0.87804242 | FK17: =MAX(FK$1*MC_Random_N10!$B17,0.9*MAX(MC_Random_N10!$C17:$K17)) -> 0.87804242 | FL17: =MAX(FL$1*MC_Random_N10!$B17,0.9*MAX(MC_Random_N10!$C17:$K17)) -> 0.87804242 | FM17: =MAX(FM$1*MC_Random_N10!$B17,0.9*MAX(MC_Random_N10!$C17:$K17)) -> 0.87804242 | FN17: =MAX(FN$1*MC_Random_N10!$B17,0.9*MAX(MC_Random_N10!$C17:$K17)) -> 0.87804242 | ... FP17: =MAX(FP$1*MC_Random_N10!$B17,0.9*MAX(MC_Random_N10!$C17:$K17)) -> 0.87804242
S18: 17 | T18: =IF(T$1*MC_Random_N2!$B18>=0.5*MC_Random_N2!$C18,MC_Random_N2!$B18*(1-T$1),0) -> 0 | U18: =IF(U$1*MC_Random_N2!$B18>=0.5*MC_Random_N2!$C18,MC_Random_N2!$B18*(1-U$1),0) -> 0 | V18: =IF(V$1*MC_Random_N2!$B18>=0.5*MC_Random_N2!$C18,MC_Random_N2!$B18*(1-V$1),0) -> 0 | W18: =IF(W$1*MC_Random_N2!$B18>=0.5*MC_Random_N2!$C18,MC_Random_N2!$B18*(1-W$1),0) -> 0.59375946 | X18: =IF(X$1*MC_Random_N2!$B18>=0.5*MC_Random_N2!$C18,MC_Random_N2!$B18*(1-X$1),0) -> 0.49479955 | Y18: =IF(Y$1*MC_Random_N2!$B18>=0.5*MC_Random_N2!$C18,MC_Random_N2!$B18*(1-Y$1),0) -> 0.39583964 | Z18: =IF(Z$1*MC_Random_N2!$B18>=0.5*MC_Random_N2!$C18,MC_Random_N2!$B18*(1-Z$1),0) -> 0.29687973 | AA18: =IF(AA$1*MC_Random_N2!$B18>=0.5*MC_Random_N2!$C18,MC_Random_N2!$B18*(1-AA$1),0) -> 0.19791982 | ... AC18: =IF(AC$1*MC_Random_N2!$B18>=0.5*MC_Random_N2!$C18,MC_Random_N2!$B18*(1-AC$1),0) -> 0 | AP18: 17 | AQ18: =MAX(AQ$1*MC_Random_N2!$B18,0.5*MC_Random_N2!$C18) -> 0.34107731 | AR18: =MAX(AR$1*MC_Random_N2!$B18,0.5*MC_Random_N2!$C18) -> 0.34107731 | AS18: =MAX(AS$1*MC_Random_N2!$B18,0.5*MC_Random_N2!$C18) -> 0.34107731 | AT18: =MAX(AT$1*MC_Random_N2!$B18,0.5*MC_Random_N2!$C18) -> 0.39583964 | AU18: =MAX(AU$1*MC_Random_N2!$B18,0.5*MC_Random_N2!$C18) -> 0.49479955 | AV18: =MAX(AV$1*MC_Random_N2!$B18,0.5*MC_Random_N2!$C18) -> 0.59375946 | AW18: =MAX(AW$1*MC_Random_N2!$B18,0.5*MC_Random_N2!$C18) -> 0.69271937 | AX18: =MAX(AX$1*MC_Random_N2!$B18,0.5*MC_Random_N2!$C18) -> 0.79167928 | ... AZ18: =MAX(AZ$1*MC_Random_N2!$B18,0.5*MC_Random_N2!$C18) -> 0.9895991 | CG18: 17 | CH18: =IF(CH$1*MC_Random_N5!$B18>=0.8*MAX(MC_Random_N5!$C18:$F18),MC_Random_N5!$B18*(1-CH$1),0) -> 0 | CI18: =IF(CI$1*MC_Random_N5!$B18>=0.8*MAX(MC_Random_N5!$C18:$F18),MC_Random_N5!$B18*(1-CI$1),0) -> 0 | CJ18: =IF(CJ$1*MC_Random_N5!$B18>=0.8*MAX(MC_Random_N5!$C18:$F18),MC_Random_N5!$B18*(1-CJ$1),0) -> 0 | CK18: =IF(CK$1*MC_Random_N5!$B18>=0.8*MAX(MC_Random_N5!$C18:$F18),MC_Random_N5!$B18*(1-CK$1),0) -> 0 | CL18: =IF(CL$1*MC_Random_N5!$B18>=0.8*MAX(MC_Random_N5!$C18:$F18),MC_Random_N5!$B18*(1-CL$1),0) -> 0 | CM18: =IF(CM$1*MC_Random_N5!$B18>=0.8*MAX(MC_Random_N5!$C18:$F18),MC_Random_N5!$B18*(1-CM$1),0) -> 0 | CN18: =IF(CN$1*MC_Random_N5!$B18>=0.8*MAX(MC_Random_N5!$C18:$F18),MC_Random_N5!$B18*(1-CN$1),0) -> 0 | CO18: =IF(CO$1*MC_Random_N5!$B18>=0.8*MAX(MC_Random_N5!$C18:$F18),MC_Random_N5!$B18*(1-CO$1),0) -> 0 | ... CQ18: =IF(CQ$1*MC_Random_N5!$B18>=0.8*MAX(MC_Random_N5!$C18:$F18),MC_Random_N5!$B18*(1-CQ$1),0) -> 0 | DD18: 17 | DE18: =MAX(DE$1*MC_Random_N5!$B18,0.8*MAX(MC_Random_N5!$C18:$F18)) -> 0.77233891 | DF18: =MAX(DF$1*MC_Random_N5!$B18,0.8*MAX(MC_Random_N5!$C18:$F18)) -> 0.77233891 | DG18: =MAX(DG$1*MC_Random_N5!$B18,0.8*MAX(MC_Random_N5!$C18:$F18)) -> 0.77233891 | DH18: =MAX(DH$1*MC_Random_N5!$B18,0.8*MAX(MC_Random_N5!$C18:$F18)) -> 0.77233891 | DI18: =MAX(DI$1*MC_Random_N5!$B18,0.8*MAX(MC_Random_N5!$C18:$F18)) -> 0.77233891 | DJ18: =MAX(DJ$1*MC_Random_N5!$B18,0.8*MAX(MC_Random_N5!$C18:$F18)) -> 0.77233891 | DK18: =MAX(DK$1*MC_Random_N5!$B18,0.8*MAX(MC_Random_N5!$C18:$F18)) -> 0.77233891 | DL18: =MAX(DL$1*MC_Random_N5!$B18,0.8*MAX(MC_Random_N5!$C18:$F18)) -> 0.77233891 | ... DN18: =MAX(DN$1*MC_Random_N5!$B18,0.8*MAX(MC_Random_N5!$C18:$F18)) -> 0.77233891 | EJ18: 17 | EK18: =IF(EK$1*MC_Random_N10!$B18>=0.9*MAX(MC_Random_N10!$C18:$K18),MC_Random_N10!$B18*(1-EK$1),0) -> 0 | EL18: =IF(EL$1*MC_Random_N10!$B18>=0.9*MAX(MC_Random_N10!$C18:$K18),MC_Random_N10!$B18*(1-EL$1),0) -> 0 | EM18: =IF(EM$1*MC_Random_N10!$B18>=0.9*MAX(MC_Random_N10!$C18:$K18),MC_Random_N10!$B18*(1-EM$1),0) -> 0 | EN18: =IF(EN$1*MC_Random_N10!$B18>=0.9*MAX(MC_Random_N10!$C18:$K18),MC_Random_N10!$B18*(1-EN$1),0) -> 0 | EO18: =IF(EO$1*MC_Random_N10!$B18>=0.9*MAX(MC_Random_N10!$C18:$K18),MC_Random_N10!$B18*(1-EO$1),0) -> 0 | EP18: =IF(EP$1*MC_Random_N10!$B18>=0.9*MAX(MC_Random_N10!$C18:$K18),MC_Random_N10!$B18*(1-EP$1),0) -> 0 | EQ18: =IF(EQ$1*MC_Random_N10!$B18>=0.9*MAX(MC_Random_N10!$C18:$K18),MC_Random_N10!$B18*(1-EQ$1),0) -> 0 | ER18: =IF(ER$1*MC_Random_N10!$B18>=0.9*MAX(MC_Random_N10!$C18:$K18),MC_Random_N10!$B18*(1-ER$1),0) -> 0 | ... ET18: =IF(ET$1*MC_Random_N10!$B18>=0.9*MAX(MC_Random_N10!$C18:$K18),MC_Random_N10!$B18*(1-ET$1),0) -> 0 | FF18: 17 | FG18: =MAX(FG$1*MC_Random_N10!$B18,0.9*MAX(MC_Random_N10!$C18:$K18)) -> 0.72900131 | FH18: =MAX(FH$1*MC_Random_N10!$B18,0.9*MAX(MC_Random_N10!$C18:$K18)) -> 0.72900131 | FI18: =MAX(FI$1*MC_Random_N10!$B18,0.9*MAX(MC_Random_N10!$C18:$K18)) -> 0.72900131 | FJ18: =MAX(FJ$1*MC_Random_N10!$B18,0.9*MAX(MC_Random_N10!$C18:$K18)) -> 0.72900131 | FK18: =MAX(FK$1*MC_Random_N10!$B18,0.9*MAX(MC_Random_N10!$C18:$K18)) -> 0.72900131 | FL18: =MAX(FL$1*MC_Random_N10!$B18,0.9*MAX(MC_Random_N10!$C18:$K18)) -> 0.72900131 | FM18: =MAX(FM$1*MC_Random_N10!$B18,0.9*MAX(MC_Random_N10!$C18:$K18)) -> 0.72900131 | FN18: =MAX(FN$1*MC_Random_N10!$B18,0.9*MAX(MC_Random_N10!$C18:$K18)) -> 0.72900131 | ... FP18: =MAX(FP$1*MC_Random_N10!$B18,0.9*MAX(MC_Random_N10!$C18:$K18)) -> 0.90056485
S19: 18 | T19: =IF(T$1*MC_Random_N2!$B19>=0.5*MC_Random_N2!$C19,MC_Random_N2!$B19*(1-T$1),0) -> 0.84902002 | U19: =IF(U$1*MC_Random_N2!$B19>=0.5*MC_Random_N2!$C19,MC_Random_N2!$B19*(1-U$1),0) -> 0.75468446 | V19: =IF(V$1*MC_Random_N2!$B19>=0.5*MC_Random_N2!$C19,MC_Random_N2!$B19*(1-V$1),0) -> 0.6603489 | W19: =IF(W$1*MC_Random_N2!$B19>=0.5*MC_Random_N2!$C19,MC_Random_N2!$B19*(1-W$1),0) -> 0.56601335 | X19: =IF(X$1*MC_Random_N2!$B19>=0.5*MC_Random_N2!$C19,MC_Random_N2!$B19*(1-X$1),0) -> 0.47167779 | Y19: =IF(Y$1*MC_Random_N2!$B19>=0.5*MC_Random_N2!$C19,MC_Random_N2!$B19*(1-Y$1),0) -> 0.37734223 | Z19: =IF(Z$1*MC_Random_N2!$B19>=0.5*MC_Random_N2!$C19,MC_Random_N2!$B19*(1-Z$1),0) -> 0.28300667 | AA19: =IF(AA$1*MC_Random_N2!$B19>=0.5*MC_Random_N2!$C19,MC_Random_N2!$B19*(1-AA$1),0) -> 0.18867112 | ... AC19: =IF(AC$1*MC_Random_N2!$B19>=0.5*MC_Random_N2!$C19,MC_Random_N2!$B19*(1-AC$1),0) -> 0 | AP19: 18 | AQ19: =MAX(AQ$1*MC_Random_N2!$B19,0.5*MC_Random_N2!$C19) -> 0.094335558 | AR19: =MAX(AR$1*MC_Random_N2!$B19,0.5*MC_Random_N2!$C19) -> 0.18867112 | AS19: =MAX(AS$1*MC_Random_N2!$B19,0.5*MC_Random_N2!$C19) -> 0.28300667 | AT19: =MAX(AT$1*MC_Random_N2!$B19,0.5*MC_Random_N2!$C19) -> 0.37734223 | AU19: =MAX(AU$1*MC_Random_N2!$B19,0.5*MC_Random_N2!$C19) -> 0.47167779 | AV19: =MAX(AV$1*MC_Random_N2!$B19,0.5*MC_Random_N2!$C19) -> 0.56601335 | AW19: =MAX(AW$1*MC_Random_N2!$B19,0.5*MC_Random_N2!$C19) -> 0.6603489 | AX19: =MAX(AX$1*MC_Random_N2!$B19,0.5*MC_Random_N2!$C19) -> 0.75468446 | ... AZ19: =MAX(AZ$1*MC_Random_N2!$B19,0.5*MC_Random_N2!$C19) -> 0.94335558 | CG19: 18 | CH19: =IF(CH$1*MC_Random_N5!$B19>=0.8*MAX(MC_Random_N5!$C19:$F19),MC_Random_N5!$B19*(1-CH$1),0) -> 0 | CI19: =IF(CI$1*MC_Random_N5!$B19>=0.8*MAX(MC_Random_N5!$C19:$F19),MC_Random_N5!$B19*(1-CI$1),0) -> 0 | CJ19: =IF(CJ$1*MC_Random_N5!$B19>=0.8*MAX(MC_Random_N5!$C19:$F19),MC_Random_N5!$B19*(1-CJ$1),0) -> 0 | CK19: =IF(CK$1*MC_Random_N5!$B19>=0.8*MAX(MC_Random_N5!$C19:$F19),MC_Random_N5!$B19*(1-CK$1),0) -> 0 | CL19: =IF(CL$1*MC_Random_N5!$B19>=0.8*MAX(MC_Random_N5!$C19:$F19),MC_Random_N5!$B19*(1-CL$1),0) -> 0 | CM19: =IF(CM$1*MC_Random_N5!$B19>=0.8*MAX(MC_Random_N5!$C19:$F19),MC_Random_N5!$B19*(1-CM$1),0) -> 0 | CN19: =IF(CN$1*MC_Random_N5!$B19>=0.8*MAX(MC_Random_N5!$C19:$F19),MC_Random_N5!$B19*(1-CN$1),0) -> 0.22180649 | CO19: =IF(CO$1*MC_Random_N5!$B19>=0.8*MAX(MC_Random_N5!$C19:$F19),MC_Random_N5!$B19*(1-CO$1),0) -> 0.14787099 | ... CQ19: =IF(CQ$1*MC_Random_N5!$B19>=0.8*MAX(MC_Random_N5!$C19:$F19),MC_Random_N5!$B19*(1-CQ$1),0) -> 0 | DD19: 18 | DE19: =MAX(DE$1*MC_Random_N5!$B19,0.8*MAX(MC_Random_N5!$C19:$F19)) -> 0.4645924 | DF19: =MAX(DF$1*MC_Random_N5!$B19,0.8*MAX(MC_Random_N5!$C19:$F19)) -> 0.4645924 | DG19: =MAX(DG$1*MC_Random_N5!$B19,0.8*MAX(MC_Random_N5!$C19:$F19)) -> 0.4645924 | DH19: =MAX(DH$1*MC_Random_N5!$B19,0.8*MAX(MC_Random_N5!$C19:$F19)) -> 0.4645924 | DI19: =MAX(DI$1*MC_Random_N5!$B19,0.8*MAX(MC_Random_N5!$C19:$F19)) -> 0.4645924 | DJ19: =MAX(DJ$1*MC_Random_N5!$B19,0.8*MAX(MC_Random_N5!$C19:$F19)) -> 0.4645924 | DK19: =MAX(DK$1*MC_Random_N5!$B19,0.8*MAX(MC_Random_N5!$C19:$F19)) -> 0.51754847 | DL19: =MAX(DL$1*MC_Random_N5!$B19,0.8*MAX(MC_Random_N5!$C19:$F19)) -> 0.59148397 | ... DN19: =MAX(DN$1*MC_Random_N5!$B19,0.8*MAX(MC_Random_N5!$C19:$F19)) -> 0.73935496 | EJ19: 18 | EK19: =IF(EK$1*MC_Random_N10!$B19>=0.9*MAX(MC_Random_N10!$C19:$K19),MC_Random_N10!$B19*(1-EK$1),0) -> 0 | EL19: =IF(EL$1*MC_Random_N10!$B19>=0.9*MAX(MC_Random_N10!$C19:$K19),MC_Random_N10!$B19*(1-EL$1),0) -> 0 | EM19: =IF(EM$1*MC_Random_N10!$B19>=0.9*MAX(MC_Random_N10!$C19:$K19),MC_Random_N10!$B19*(1-EM$1),0) -> 0 | EN19: =IF(EN$1*MC_Random_N10!$B19>=0.9*MAX(MC_Random_N10!$C19:$K19),MC_Random_N10!$B19*(1-EN$1),0) -> 0 | EO19: =IF(EO$1*MC_Random_N10!$B19>=0.9*MAX(MC_Random_N10!$C19:$K19),MC_Random_N10!$B19*(1-EO$1),0) -> 0 | EP19: =IF(EP$1*MC_Random_N10!$B19>=0.9*MAX(MC_Random_N10!$C19:$K19),MC_Random_N10!$B19*(1-EP$1),0) -> 0 | EQ19: =IF(EQ$1*MC_Random_N10!$B19>=0.9*MAX(MC_Random_N10!$C19:$K19),MC_Random_N10!$B19*(1-EQ$1),0) -> 0 | ER19: =IF(ER$1*MC_Random_N10!$B19>=0.9*MAX(MC_Random_N10!$C19:$K19),MC_Random_N10!$B19*(1-ER$1),0) -> 0 | ... ET19: =IF(ET$1*MC_Random_N10!$B19>=0.9*MAX(MC_Random_N10!$C19:$K19),MC_Random_N10!$B19*(1-ET$1),0) -> 0 | FF19: 18 | FG19: =MAX(FG$1*MC_Random_N10!$B19,0.9*MAX(MC_Random_N10!$C19:$K19)) -> 0.87530033 | FH19: =MAX(FH$1*MC_Random_N10!$B19,0.9*MAX(MC_Random_N10!$C19:$K19)) -> 0.87530033 | FI19: =MAX(FI$1*MC_Random_N10!$B19,0.9*MAX(MC_Random_N10!$C19:$K19)) -> 0.87530033 | FJ19: =MAX(FJ$1*MC_Random_N10!$B19,0.9*MAX(MC_Random_N10!$C19:$K19)) -> 0.87530033 | FK19: =MAX(FK$1*MC_Random_N10!$B19,0.9*MAX(MC_Random_N10!$C19:$K19)) -> 0.87530033 | FL19: =MAX(FL$1*MC_Random_N10!$B19,0.9*MAX(MC_Random_N10!$C19:$K19)) -> 0.87530033 | FM19: =MAX(FM$1*MC_Random_N10!$B19,0.9*MAX(MC_Random_N10!$C19:$K19)) -> 0.87530033 | FN19: =MAX(FN$1*MC_Random_N10!$B19,0.9*MAX(MC_Random_N10!$C19:$K19)) -> 0.87530033 | ... FP19: =MAX(FP$1*MC_Random_N10!$B19,0.9*MAX(MC_Random_N10!$C19:$K19)) -> 0.87530033
S20: 19 | T20: =IF(T$1*MC_Random_N2!$B20>=0.5*MC_Random_N2!$C20,MC_Random_N2!$B20*(1-T$1),0) -> 0 | U20: =IF(U$1*MC_Random_N2!$B20>=0.5*MC_Random_N2!$C20,MC_Random_N2!$B20*(1-U$1),0) -> 0 | V20: =IF(V$1*MC_Random_N2!$B20>=0.5*MC_Random_N2!$C20,MC_Random_N2!$B20*(1-V$1),0) -> 0 | W20: =IF(W$1*MC_Random_N2!$B20>=0.5*MC_Random_N2!$C20,MC_Random_N2!$B20*(1-W$1),0) -> 0 | X20: =IF(X$1*MC_Random_N2!$B20>=0.5*MC_Random_N2!$C20,MC_Random_N2!$B20*(1-X$1),0) -> 0.4573505 | Y20: =IF(Y$1*MC_Random_N2!$B20>=0.5*MC_Random_N2!$C20,MC_Random_N2!$B20*(1-Y$1),0) -> 0.3658804 | Z20: =IF(Z$1*MC_Random_N2!$B20>=0.5*MC_Random_N2!$C20,MC_Random_N2!$B20*(1-Z$1),0) -> 0.2744103 | AA20: =IF(AA$1*MC_Random_N2!$B20>=0.5*MC_Random_N2!$C20,MC_Random_N2!$B20*(1-AA$1),0) -> 0.1829402 | ... AC20: =IF(AC$1*MC_Random_N2!$B20>=0.5*MC_Random_N2!$C20,MC_Random_N2!$B20*(1-AC$1),0) -> 0 | AP20: 19 | AQ20: =MAX(AQ$1*MC_Random_N2!$B20,0.5*MC_Random_N2!$C20) -> 0.37859437 | AR20: =MAX(AR$1*MC_Random_N2!$B20,0.5*MC_Random_N2!$C20) -> 0.37859437 | AS20: =MAX(AS$1*MC_Random_N2!$B20,0.5*MC_Random_N2!$C20) -> 0.37859437 | AT20: =MAX(AT$1*MC_Random_N2!$B20,0.5*MC_Random_N2!$C20) -> 0.37859437 | AU20: =MAX(AU$1*MC_Random_N2!$B20,0.5*MC_Random_N2!$C20) -> 0.4573505 | AV20: =MAX(AV$1*MC_Random_N2!$B20,0.5*MC_Random_N2!$C20) -> 0.5488206 | AW20: =MAX(AW$1*MC_Random_N2!$B20,0.5*MC_Random_N2!$C20) -> 0.6402907 | AX20: =MAX(AX$1*MC_Random_N2!$B20,0.5*MC_Random_N2!$C20) -> 0.7317608 | ... AZ20: =MAX(AZ$1*MC_Random_N2!$B20,0.5*MC_Random_N2!$C20) -> 0.914701 | CG20: 19 | CH20: =IF(CH$1*MC_Random_N5!$B20>=0.8*MAX(MC_Random_N5!$C20:$F20),MC_Random_N5!$B20*(1-CH$1),0) -> 0 | CI20: =IF(CI$1*MC_Random_N5!$B20>=0.8*MAX(MC_Random_N5!$C20:$F20),MC_Random_N5!$B20*(1-CI$1),0) -> 0 | CJ20: =IF(CJ$1*MC_Random_N5!$B20>=0.8*MAX(MC_Random_N5!$C20:$F20),MC_Random_N5!$B20*(1-CJ$1),0) -> 0 | CK20: =IF(CK$1*MC_Random_N5!$B20>=0.8*MAX(MC_Random_N5!$C20:$F20),MC_Random_N5!$B20*(1-CK$1),0) -> 0 | CL20: =IF(CL$1*MC_Random_N5!$B20>=0.8*MAX(MC_Random_N5!$C20:$F20),MC_Random_N5!$B20*(1-CL$1),0) -> 0 | CM20: =IF(CM$1*MC_Random_N5!$B20>=0.8*MAX(MC_Random_N5!$C20:$F20),MC_Random_N5!$B20*(1-CM$1),0) -> 0 | CN20: =IF(CN$1*MC_Random_N5!$B20>=0.8*MAX(MC_Random_N5!$C20:$F20),MC_Random_N5!$B20*(1-CN$1),0) -> 0 | CO20: =IF(CO$1*MC_Random_N5!$B20>=0.8*MAX(MC_Random_N5!$C20:$F20),MC_Random_N5!$B20*(1-CO$1),0) -> 0 | ... CQ20: =IF(CQ$1*MC_Random_N5!$B20>=0.8*MAX(MC_Random_N5!$C20:$F20),MC_Random_N5!$B20*(1-CQ$1),0) -> 0 | DD20: 19 | DE20: =MAX(DE$1*MC_Random_N5!$B20,0.8*MAX(MC_Random_N5!$C20:$F20)) -> 0.74605459 | DF20: =MAX(DF$1*MC_Random_N5!$B20,0.8*MAX(MC_Random_N5!$C20:$F20)) -> 0.74605459 | DG20: =MAX(DG$1*MC_Random_N5!$B20,0.8*MAX(MC_Random_N5!$C20:$F20)) -> 0.74605459 | DH20: =MAX(DH$1*MC_Random_N5!$B20,0.8*MAX(MC_Random_N5!$C20:$F20)) -> 0.74605459 | DI20: =MAX(DI$1*MC_Random_N5!$B20,0.8*MAX(MC_Random_N5!$C20:$F20)) -> 0.74605459 | DJ20: =MAX(DJ$1*MC_Random_N5!$B20,0.8*MAX(MC_Random_N5!$C20:$F20)) -> 0.74605459 | DK20: =MAX(DK$1*MC_Random_N5!$B20,0.8*MAX(MC_Random_N5!$C20:$F20)) -> 0.74605459 | DL20: =MAX(DL$1*MC_Random_N5!$B20,0.8*MAX(MC_Random_N5!$C20:$F20)) -> 0.74605459 | ... DN20: =MAX(DN$1*MC_Random_N5!$B20,0.8*MAX(MC_Random_N5!$C20:$F20)) -> 0.88192996 | EJ20: 19 | EK20: =IF(EK$1*MC_Random_N10!$B20>=0.9*MAX(MC_Random_N10!$C20:$K20),MC_Random_N10!$B20*(1-EK$1),0) -> 0 | EL20: =IF(EL$1*MC_Random_N10!$B20>=0.9*MAX(MC_Random_N10!$C20:$K20),MC_Random_N10!$B20*(1-EL$1),0) -> 0 | EM20: =IF(EM$1*MC_Random_N10!$B20>=0.9*MAX(MC_Random_N10!$C20:$K20),MC_Random_N10!$B20*(1-EM$1),0) -> 0 | EN20: =IF(EN$1*MC_Random_N10!$B20>=0.9*MAX(MC_Random_N10!$C20:$K20),MC_Random_N10!$B20*(1-EN$1),0) -> 0 | EO20: =IF(EO$1*MC_Random_N10!$B20>=0.9*MAX(MC_Random_N10!$C20:$K20),MC_Random_N10!$B20*(1-EO$1),0) -> 0 | EP20: =IF(EP$1*MC_Random_N10!$B20>=0.9*MAX(MC_Random_N10!$C20:$K20),MC_Random_N10!$B20*(1-EP$1),0) -> 0 | EQ20: =IF(EQ$1*MC_Random_N10!$B20>=0.9*MAX(MC_Random_N10!$C20:$K20),MC_Random_N10!$B20*(1-EQ$1),0) -> 0 | ER20: =IF(ER$1*MC_Random_N10!$B20>=0.9*MAX(MC_Random_N10!$C20:$K20),MC_Random_N10!$B20*(1-ER$1),0) -> 0 | ... ET20: =IF(ET$1*MC_Random_N10!$B20>=0.9*MAX(MC_Random_N10!$C20:$K20),MC_Random_N10!$B20*(1-ET$1),0) -> 0 | FF20: 19 | FG20: =MAX(FG$1*MC_Random_N10!$B20,0.9*MAX(MC_Random_N10!$C20:$K20)) -> 0.84326128 | FH20: =MAX(FH$1*MC_Random_N10!$B20,0.9*MAX(MC_Random_N10!$C20:$K20)) -> 0.84326128 | FI20: =MAX(FI$1*MC_Random_N10!$B20,0.9*MAX(MC_Random_N10!$C20:$K20)) -> 0.84326128 | FJ20: =MAX(FJ$1*MC_Random_N10!$B20,0.9*MAX(MC_Random_N10!$C20:$K20)) -> 0.84326128 | FK20: =MAX(FK$1*MC_Random_N10!$B20,0.9*MAX(MC_Random_N10!$C20:$K20)) -> 0.84326128 | FL20: =MAX(FL$1*MC_Random_N10!$B20,0.9*MAX(MC_Random_N10!$C20:$K20)) -> 0.84326128 | FM20: =MAX(FM$1*MC_Random_N10!$B20,0.9*MAX(MC_Random_N10!$C20:$K20)) -> 0.84326128 | FN20: =MAX(FN$1*MC_Random_N10!$B20,0.9*MAX(MC_Random_N10!$C20:$K20)) -> 0.84326128 | ... FP20: =MAX(FP$1*MC_Random_N10!$B20,0.9*MAX(MC_Random_N10!$C20:$K20)) -> 0.84326128
S21: 20 | T21: =IF(T$1*MC_Random_N2!$B21>=0.5*MC_Random_N2!$C21,MC_Random_N2!$B21*(1-T$1),0) -> 0 | U21: =IF(U$1*MC_Random_N2!$B21>=0.5*MC_Random_N2!$C21,MC_Random_N2!$B21*(1-U$1),0) -> 0 | V21: =IF(V$1*MC_Random_N2!$B21>=0.5*MC_Random_N2!$C21,MC_Random_N2!$B21*(1-V$1),0) -> 0 | W21: =IF(W$1*MC_Random_N2!$B21>=0.5*MC_Random_N2!$C21,MC_Random_N2!$B21*(1-W$1),0) -> 0 | X21: =IF(X$1*MC_Random_N2!$B21>=0.5*MC_Random_N2!$C21,MC_Random_N2!$B21*(1-X$1),0) -> 0 | Y21: =IF(Y$1*MC_Random_N2!$B21>=0.5*MC_Random_N2!$C21,MC_Random_N2!$B21*(1-Y$1),0) -> 0 | Z21: =IF(Z$1*MC_Random_N2!$B21>=0.5*MC_Random_N2!$C21,MC_Random_N2!$B21*(1-Z$1),0) -> 0 | AA21: =IF(AA$1*MC_Random_N2!$B21>=0.5*MC_Random_N2!$C21,MC_Random_N2!$B21*(1-AA$1),0) -> 0 | ... AC21: =IF(AC$1*MC_Random_N2!$B21>=0.5*MC_Random_N2!$C21,MC_Random_N2!$B21*(1-AC$1),0) -> 0 | AP21: 20 | AQ21: =MAX(AQ$1*MC_Random_N2!$B21,0.5*MC_Random_N2!$C21) -> 0.1914011 | AR21: =MAX(AR$1*MC_Random_N2!$B21,0.5*MC_Random_N2!$C21) -> 0.1914011 | AS21: =MAX(AS$1*MC_Random_N2!$B21,0.5*MC_Random_N2!$C21) -> 0.1914011 | AT21: =MAX(AT$1*MC_Random_N2!$B21,0.5*MC_Random_N2!$C21) -> 0.1914011 | AU21: =MAX(AU$1*MC_Random_N2!$B21,0.5*MC_Random_N2!$C21) -> 0.1914011 | AV21: =MAX(AV$1*MC_Random_N2!$B21,0.5*MC_Random_N2!$C21) -> 0.1914011 | AW21: =MAX(AW$1*MC_Random_N2!$B21,0.5*MC_Random_N2!$C21) -> 0.1914011 | AX21: =MAX(AX$1*MC_Random_N2!$B21,0.5*MC_Random_N2!$C21) -> 0.1914011 | ... AZ21: =MAX(AZ$1*MC_Random_N2!$B21,0.5*MC_Random_N2!$C21) -> 0.1914011 | CG21: 20 | CH21: =IF(CH$1*MC_Random_N5!$B21>=0.8*MAX(MC_Random_N5!$C21:$F21),MC_Random_N5!$B21*(1-CH$1),0) -> 0 | CI21: =IF(CI$1*MC_Random_N5!$B21>=0.8*MAX(MC_Random_N5!$C21:$F21),MC_Random_N5!$B21*(1-CI$1),0) -> 0 | CJ21: =IF(CJ$1*MC_Random_N5!$B21>=0.8*MAX(MC_Random_N5!$C21:$F21),MC_Random_N5!$B21*(1-CJ$1),0) -> 0 | CK21: =IF(CK$1*MC_Random_N5!$B21>=0.8*MAX(MC_Random_N5!$C21:$F21),MC_Random_N5!$B21*(1-CK$1),0) -> 0.50490421 | CL21: =IF(CL$1*MC_Random_N5!$B21>=0.8*MAX(MC_Random_N5!$C21:$F21),MC_Random_N5!$B21*(1-CL$1),0) -> 0.42075351 | CM21: =IF(CM$1*MC_Random_N5!$B21>=0.8*MAX(MC_Random_N5!$C21:$F21),MC_Random_N5!$B21*(1-CM$1),0) -> 0.33660281 | CN21: =IF(CN$1*MC_Random_N5!$B21>=0.8*MAX(MC_Random_N5!$C21:$F21),MC_Random_N5!$B21*(1-CN$1),0) -> 0.25245211 | CO21: =IF(CO$1*MC_Random_N5!$B21>=0.8*MAX(MC_Random_N5!$C21:$F21),MC_Random_N5!$B21*(1-CO$1),0) -> 0.1683014 | ... CQ21: =IF(CQ$1*MC_Random_N5!$B21>=0.8*MAX(MC_Random_N5!$C21:$F21),MC_Random_N5!$B21*(1-CQ$1),0) -> 0 | DD21: 20 | DE21: =MAX(DE$1*MC_Random_N5!$B21,0.8*MAX(MC_Random_N5!$C21:$F21)) -> 0.26961179 | DF21: =MAX(DF$1*MC_Random_N5!$B21,0.8*MAX(MC_Random_N5!$C21:$F21)) -> 0.26961179 | DG21: =MAX(DG$1*MC_Random_N5!$B21,0.8*MAX(MC_Random_N5!$C21:$F21)) -> 0.26961179 | DH21: =MAX(DH$1*MC_Random_N5!$B21,0.8*MAX(MC_Random_N5!$C21:$F21)) -> 0.33660281 | DI21: =MAX(DI$1*MC_Random_N5!$B21,0.8*MAX(MC_Random_N5!$C21:$F21)) -> 0.42075351 | DJ21: =MAX(DJ$1*MC_Random_N5!$B21,0.8*MAX(MC_Random_N5!$C21:$F21)) -> 0.50490421 | DK21: =MAX(DK$1*MC_Random_N5!$B21,0.8*MAX(MC_Random_N5!$C21:$F21)) -> 0.58905491 | DL21: =MAX(DL$1*MC_Random_N5!$B21,0.8*MAX(MC_Random_N5!$C21:$F21)) -> 0.67320562 | ... DN21: =MAX(DN$1*MC_Random_N5!$B21,0.8*MAX(MC_Random_N5!$C21:$F21)) -> 0.84150702 | EJ21: 20 | EK21: =IF(EK$1*MC_Random_N10!$B21>=0.9*MAX(MC_Random_N10!$C21:$K21),MC_Random_N10!$B21*(1-EK$1),0) -> 0 | EL21: =IF(EL$1*MC_Random_N10!$B21>=0.9*MAX(MC_Random_N10!$C21:$K21),MC_Random_N10!$B21*(1-EL$1),0) -> 0 | EM21: =IF(EM$1*MC_Random_N10!$B21>=0.9*MAX(MC_Random_N10!$C21:$K21),MC_Random_N10!$B21*(1-EM$1),0) -> 0 | EN21: =IF(EN$1*MC_Random_N10!$B21>=0.9*MAX(MC_Random_N10!$C21:$K21),MC_Random_N10!$B21*(1-EN$1),0) -> 0 | EO21: =IF(EO$1*MC_Random_N10!$B21>=0.9*MAX(MC_Random_N10!$C21:$K21),MC_Random_N10!$B21*(1-EO$1),0) -> 0 | EP21: =IF(EP$1*MC_Random_N10!$B21>=0.9*MAX(MC_Random_N10!$C21:$K21),MC_Random_N10!$B21*(1-EP$1),0) -> 0 | EQ21: =IF(EQ$1*MC_Random_N10!$B21>=0.9*MAX(MC_Random_N10!$C21:$K21),MC_Random_N10!$B21*(1-EQ$1),0) -> 0 | ER21: =IF(ER$1*MC_Random_N10!$B21>=0.9*MAX(MC_Random_N10!$C21:$K21),MC_Random_N10!$B21*(1-ER$1),0) -> 0 | ... ET21: =IF(ET$1*MC_Random_N10!$B21>=0.9*MAX(MC_Random_N10!$C21:$K21),MC_Random_N10!$B21*(1-ET$1),0) -> 0 | FF21: 20 | FG21: =MAX(FG$1*MC_Random_N10!$B21,0.9*MAX(MC_Random_N10!$C21:$K21)) -> 0.78678993 | FH21: =MAX(FH$1*MC_Random_N10!$B21,0.9*MAX(MC_Random_N10!$C21:$K21)) -> 0.78678993 | FI21: =MAX(FI$1*MC_Random_N10!$B21,0.9*MAX(MC_Random_N10!$C21:$K21)) -> 0.78678993 | FJ21: =MAX(FJ$1*MC_Random_N10!$B21,0.9*MAX(MC_Random_N10!$C21:$K21)) -> 0.78678993 | FK21: =MAX(FK$1*MC_Random_N10!$B21,0.9*MAX(MC_Random_N10!$C21:$K21)) -> 0.78678993 | FL21: =MAX(FL$1*MC_Random_N10!$B21,0.9*MAX(MC_Random_N10!$C21:$K21)) -> 0.78678993 | FM21: =MAX(FM$1*MC_Random_N10!$B21,0.9*MAX(MC_Random_N10!$C21:$K21)) -> 0.78678993 | FN21: =MAX(FN$1*MC_Random_N10!$B21,0.9*MAX(MC_Random_N10!$C21:$K21)) -> 0.78678993 | ... FP21: =MAX(FP$1*MC_Random_N10!$B21,0.9*MAX(MC_Random_N10!$C21:$K21)) -> 0.78678993
S22: 21 | T22: =IF(T$1*MC_Random_N2!$B22>=0.5*MC_Random_N2!$C22,MC_Random_N2!$B22*(1-T$1),0) -> 0 | U22: =IF(U$1*MC_Random_N2!$B22>=0.5*MC_Random_N2!$C22,MC_Random_N2!$B22*(1-U$1),0) -> 0 | V22: =IF(V$1*MC_Random_N2!$B22>=0.5*MC_Random_N2!$C22,MC_Random_N2!$B22*(1-V$1),0) -> 0 | W22: =IF(W$1*MC_Random_N2!$B22>=0.5*MC_Random_N2!$C22,MC_Random_N2!$B22*(1-W$1),0) -> 0 | X22: =IF(X$1*MC_Random_N2!$B22>=0.5*MC_Random_N2!$C22,MC_Random_N2!$B22*(1-X$1),0) -> 0 | Y22: =IF(Y$1*MC_Random_N2!$B22>=0.5*MC_Random_N2!$C22,MC_Random_N2!$B22*(1-Y$1),0) -> 0 | Z22: =IF(Z$1*MC_Random_N2!$B22>=0.5*MC_Random_N2!$C22,MC_Random_N2!$B22*(1-Z$1),0) -> 0 | AA22: =IF(AA$1*MC_Random_N2!$B22>=0.5*MC_Random_N2!$C22,MC_Random_N2!$B22*(1-AA$1),0) -> 0 | ... AC22: =IF(AC$1*MC_Random_N2!$B22>=0.5*MC_Random_N2!$C22,MC_Random_N2!$B22*(1-AC$1),0) -> 0 | AP22: 21 | AQ22: =MAX(AQ$1*MC_Random_N2!$B22,0.5*MC_Random_N2!$C22) -> 0.48154033 | AR22: =MAX(AR$1*MC_Random_N2!$B22,0.5*MC_Random_N2!$C22) -> 0.48154033 | AS22: =MAX(AS$1*MC_Random_N2!$B22,0.5*MC_Random_N2!$C22) -> 0.48154033 | AT22: =MAX(AT$1*MC_Random_N2!$B22,0.5*MC_Random_N2!$C22) -> 0.48154033 | AU22: =MAX(AU$1*MC_Random_N2!$B22,0.5*MC_Random_N2!$C22) -> 0.48154033 | AV22: =MAX(AV$1*MC_Random_N2!$B22,0.5*MC_Random_N2!$C22) -> 0.48154033 | AW22: =MAX(AW$1*MC_Random_N2!$B22,0.5*MC_Random_N2!$C22) -> 0.48154033 | AX22: =MAX(AX$1*MC_Random_N2!$B22,0.5*MC_Random_N2!$C22) -> 0.48154033 | ... AZ22: =MAX(AZ$1*MC_Random_N2!$B22,0.5*MC_Random_N2!$C22) -> 0.48154033 | CG22: 21 | CH22: =IF(CH$1*MC_Random_N5!$B22>=0.8*MAX(MC_Random_N5!$C22:$F22),MC_Random_N5!$B22*(1-CH$1),0) -> 0 | CI22: =IF(CI$1*MC_Random_N5!$B22>=0.8*MAX(MC_Random_N5!$C22:$F22),MC_Random_N5!$B22*(1-CI$1),0) -> 0 | CJ22: =IF(CJ$1*MC_Random_N5!$B22>=0.8*MAX(MC_Random_N5!$C22:$F22),MC_Random_N5!$B22*(1-CJ$1),0) -> 0 | CK22: =IF(CK$1*MC_Random_N5!$B22>=0.8*MAX(MC_Random_N5!$C22:$F22),MC_Random_N5!$B22*(1-CK$1),0) -> 0 | CL22: =IF(CL$1*MC_Random_N5!$B22>=0.8*MAX(MC_Random_N5!$C22:$F22),MC_Random_N5!$B22*(1-CL$1),0) -> 0 | CM22: =IF(CM$1*MC_Random_N5!$B22>=0.8*MAX(MC_Random_N5!$C22:$F22),MC_Random_N5!$B22*(1-CM$1),0) -> 0 | CN22: =IF(CN$1*MC_Random_N5!$B22>=0.8*MAX(MC_Random_N5!$C22:$F22),MC_Random_N5!$B22*(1-CN$1),0) -> 0 | CO22: =IF(CO$1*MC_Random_N5!$B22>=0.8*MAX(MC_Random_N5!$C22:$F22),MC_Random_N5!$B22*(1-CO$1),0) -> 0 | ... CQ22: =IF(CQ$1*MC_Random_N5!$B22>=0.8*MAX(MC_Random_N5!$C22:$F22),MC_Random_N5!$B22*(1-CQ$1),0) -> 0 | DD22: 21 | DE22: =MAX(DE$1*MC_Random_N5!$B22,0.8*MAX(MC_Random_N5!$C22:$F22)) -> 0.65108088 | DF22: =MAX(DF$1*MC_Random_N5!$B22,0.8*MAX(MC_Random_N5!$C22:$F22)) -> 0.65108088 | DG22: =MAX(DG$1*MC_Random_N5!$B22,0.8*MAX(MC_Random_N5!$C22:$F22)) -> 0.65108088 | DH22: =MAX(DH$1*MC_Random_N5!$B22,0.8*MAX(MC_Random_N5!$C22:$F22)) -> 0.65108088 | DI22: =MAX(DI$1*MC_Random_N5!$B22,0.8*MAX(MC_Random_N5!$C22:$F22)) -> 0.65108088 | DJ22: =MAX(DJ$1*MC_Random_N5!$B22,0.8*MAX(MC_Random_N5!$C22:$F22)) -> 0.65108088 | DK22: =MAX(DK$1*MC_Random_N5!$B22,0.8*MAX(MC_Random_N5!$C22:$F22)) -> 0.65108088 | DL22: =MAX(DL$1*MC_Random_N5!$B22,0.8*MAX(MC_Random_N5!$C22:$F22)) -> 0.65108088 | ... DN22: =MAX(DN$1*MC_Random_N5!$B22,0.8*MAX(MC_Random_N5!$C22:$F22)) -> 0.68330267 | EJ22: 21 | EK22: =IF(EK$1*MC_Random_N10!$B22>=0.9*MAX(MC_Random_N10!$C22:$K22),MC_Random_N10!$B22*(1-EK$1),0) -> 0 | EL22: =IF(EL$1*MC_Random_N10!$B22>=0.9*MAX(MC_Random_N10!$C22:$K22),MC_Random_N10!$B22*(1-EL$1),0) -> 0 | EM22: =IF(EM$1*MC_Random_N10!$B22>=0.9*MAX(MC_Random_N10!$C22:$K22),MC_Random_N10!$B22*(1-EM$1),0) -> 0 | EN22: =IF(EN$1*MC_Random_N10!$B22>=0.9*MAX(MC_Random_N10!$C22:$K22),MC_Random_N10!$B22*(1-EN$1),0) -> 0 | EO22: =IF(EO$1*MC_Random_N10!$B22>=0.9*MAX(MC_Random_N10!$C22:$K22),MC_Random_N10!$B22*(1-EO$1),0) -> 0 | EP22: =IF(EP$1*MC_Random_N10!$B22>=0.9*MAX(MC_Random_N10!$C22:$K22),MC_Random_N10!$B22*(1-EP$1),0) -> 0 | EQ22: =IF(EQ$1*MC_Random_N10!$B22>=0.9*MAX(MC_Random_N10!$C22:$K22),MC_Random_N10!$B22*(1-EQ$1),0) -> 0 | ER22: =IF(ER$1*MC_Random_N10!$B22>=0.9*MAX(MC_Random_N10!$C22:$K22),MC_Random_N10!$B22*(1-ER$1),0) -> 0 | ... ET22: =IF(ET$1*MC_Random_N10!$B22>=0.9*MAX(MC_Random_N10!$C22:$K22),MC_Random_N10!$B22*(1-ET$1),0) -> 0 | FF22: 21 | FG22: =MAX(FG$1*MC_Random_N10!$B22,0.9*MAX(MC_Random_N10!$C22:$K22)) -> 0.82449317 | FH22: =MAX(FH$1*MC_Random_N10!$B22,0.9*MAX(MC_Random_N10!$C22:$K22)) -> 0.82449317 | FI22: =MAX(FI$1*MC_Random_N10!$B22,0.9*MAX(MC_Random_N10!$C22:$K22)) -> 0.82449317 | FJ22: =MAX(FJ$1*MC_Random_N10!$B22,0.9*MAX(MC_Random_N10!$C22:$K22)) -> 0.82449317 | FK22: =MAX(FK$1*MC_Random_N10!$B22,0.9*MAX(MC_Random_N10!$C22:$K22)) -> 0.82449317 | FL22: =MAX(FL$1*MC_Random_N10!$B22,0.9*MAX(MC_Random_N10!$C22:$K22)) -> 0.82449317 | FM22: =MAX(FM$1*MC_Random_N10!$B22,0.9*MAX(MC_Random_N10!$C22:$K22)) -> 0.82449317 | FN22: =MAX(FN$1*MC_Random_N10!$B22,0.9*MAX(MC_Random_N10!$C22:$K22)) -> 0.82449317 | ... FP22: =MAX(FP$1*MC_Random_N10!$B22,0.9*MAX(MC_Random_N10!$C22:$K22)) -> 0.82449317
S23: 22 | T23: =IF(T$1*MC_Random_N2!$B23>=0.5*MC_Random_N2!$C23,MC_Random_N2!$B23*(1-T$1),0) -> 0 | U23: =IF(U$1*MC_Random_N2!$B23>=0.5*MC_Random_N2!$C23,MC_Random_N2!$B23*(1-U$1),0) -> 0 | V23: =IF(V$1*MC_Random_N2!$B23>=0.5*MC_Random_N2!$C23,MC_Random_N2!$B23*(1-V$1),0) -> 0 | W23: =IF(W$1*MC_Random_N2!$B23>=0.5*MC_Random_N2!$C23,MC_Random_N2!$B23*(1-W$1),0) -> 0 | X23: =IF(X$1*MC_Random_N2!$B23>=0.5*MC_Random_N2!$C23,MC_Random_N2!$B23*(1-X$1),0) -> 0 | Y23: =IF(Y$1*MC_Random_N2!$B23>=0.5*MC_Random_N2!$C23,MC_Random_N2!$B23*(1-Y$1),0) -> 0 | Z23: =IF(Z$1*MC_Random_N2!$B23>=0.5*MC_Random_N2!$C23,MC_Random_N2!$B23*(1-Z$1),0) -> 0 | AA23: =IF(AA$1*MC_Random_N2!$B23>=0.5*MC_Random_N2!$C23,MC_Random_N2!$B23*(1-AA$1),0) -> 0 | ... AC23: =IF(AC$1*MC_Random_N2!$B23>=0.5*MC_Random_N2!$C23,MC_Random_N2!$B23*(1-AC$1),0) -> 0 | AP23: 22 | AQ23: =MAX(AQ$1*MC_Random_N2!$B23,0.5*MC_Random_N2!$C23) -> 0.22968725 | AR23: =MAX(AR$1*MC_Random_N2!$B23,0.5*MC_Random_N2!$C23) -> 0.22968725 | AS23: =MAX(AS$1*MC_Random_N2!$B23,0.5*MC_Random_N2!$C23) -> 0.22968725 | AT23: =MAX(AT$1*MC_Random_N2!$B23,0.5*MC_Random_N2!$C23) -> 0.22968725 | AU23: =MAX(AU$1*MC_Random_N2!$B23,0.5*MC_Random_N2!$C23) -> 0.22968725 | AV23: =MAX(AV$1*MC_Random_N2!$B23,0.5*MC_Random_N2!$C23) -> 0.22968725 | AW23: =MAX(AW$1*MC_Random_N2!$B23,0.5*MC_Random_N2!$C23) -> 0.22968725 | AX23: =MAX(AX$1*MC_Random_N2!$B23,0.5*MC_Random_N2!$C23) -> 0.22968725 | ... AZ23: =MAX(AZ$1*MC_Random_N2!$B23,0.5*MC_Random_N2!$C23) -> 0.27615833 | CG23: 22 | CH23: =IF(CH$1*MC_Random_N5!$B23>=0.8*MAX(MC_Random_N5!$C23:$F23),MC_Random_N5!$B23*(1-CH$1),0) -> 0 | CI23: =IF(CI$1*MC_Random_N5!$B23>=0.8*MAX(MC_Random_N5!$C23:$F23),MC_Random_N5!$B23*(1-CI$1),0) -> 0 | CJ23: =IF(CJ$1*MC_Random_N5!$B23>=0.8*MAX(MC_Random_N5!$C23:$F23),MC_Random_N5!$B23*(1-CJ$1),0) -> 0 | CK23: =IF(CK$1*MC_Random_N5!$B23>=0.8*MAX(MC_Random_N5!$C23:$F23),MC_Random_N5!$B23*(1-CK$1),0) -> 0 | CL23: =IF(CL$1*MC_Random_N5!$B23>=0.8*MAX(MC_Random_N5!$C23:$F23),MC_Random_N5!$B23*(1-CL$1),0) -> 0 | CM23: =IF(CM$1*MC_Random_N5!$B23>=0.8*MAX(MC_Random_N5!$C23:$F23),MC_Random_N5!$B23*(1-CM$1),0) -> 0 | CN23: =IF(CN$1*MC_Random_N5!$B23>=0.8*MAX(MC_Random_N5!$C23:$F23),MC_Random_N5!$B23*(1-CN$1),0) -> 0 | CO23: =IF(CO$1*MC_Random_N5!$B23>=0.8*MAX(MC_Random_N5!$C23:$F23),MC_Random_N5!$B23*(1-CO$1),0) -> 0.19337529 | ... CQ23: =IF(CQ$1*MC_Random_N5!$B23>=0.8*MAX(MC_Random_N5!$C23:$F23),MC_Random_N5!$B23*(1-CQ$1),0) -> 0 | DD23: 22 | DE23: =MAX(DE$1*MC_Random_N5!$B23,0.8*MAX(MC_Random_N5!$C23:$F23)) -> 0.71277398 | DF23: =MAX(DF$1*MC_Random_N5!$B23,0.8*MAX(MC_Random_N5!$C23:$F23)) -> 0.71277398 | DG23: =MAX(DG$1*MC_Random_N5!$B23,0.8*MAX(MC_Random_N5!$C23:$F23)) -> 0.71277398 | DH23: =MAX(DH$1*MC_Random_N5!$B23,0.8*MAX(MC_Random_N5!$C23:$F23)) -> 0.71277398 | DI23: =MAX(DI$1*MC_Random_N5!$B23,0.8*MAX(MC_Random_N5!$C23:$F23)) -> 0.71277398 | DJ23: =MAX(DJ$1*MC_Random_N5!$B23,0.8*MAX(MC_Random_N5!$C23:$F23)) -> 0.71277398 | DK23: =MAX(DK$1*MC_Random_N5!$B23,0.8*MAX(MC_Random_N5!$C23:$F23)) -> 0.71277398 | DL23: =MAX(DL$1*MC_Random_N5!$B23,0.8*MAX(MC_Random_N5!$C23:$F23)) -> 0.77350115 | ... DN23: =MAX(DN$1*MC_Random_N5!$B23,0.8*MAX(MC_Random_N5!$C23:$F23)) -> 0.96687643 | EJ23: 22 | EK23: =IF(EK$1*MC_Random_N10!$B23>=0.9*MAX(MC_Random_N10!$C23:$K23),MC_Random_N10!$B23*(1-EK$1),0) -> 0 | EL23: =IF(EL$1*MC_Random_N10!$B23>=0.9*MAX(MC_Random_N10!$C23:$K23),MC_Random_N10!$B23*(1-EL$1),0) -> 0 | EM23: =IF(EM$1*MC_Random_N10!$B23>=0.9*MAX(MC_Random_N10!$C23:$K23),MC_Random_N10!$B23*(1-EM$1),0) -> 0 | EN23: =IF(EN$1*MC_Random_N10!$B23>=0.9*MAX(MC_Random_N10!$C23:$K23),MC_Random_N10!$B23*(1-EN$1),0) -> 0 | EO23: =IF(EO$1*MC_Random_N10!$B23>=0.9*MAX(MC_Random_N10!$C23:$K23),MC_Random_N10!$B23*(1-EO$1),0) -> 0 | EP23: =IF(EP$1*MC_Random_N10!$B23>=0.9*MAX(MC_Random_N10!$C23:$K23),MC_Random_N10!$B23*(1-EP$1),0) -> 0 | EQ23: =IF(EQ$1*MC_Random_N10!$B23>=0.9*MAX(MC_Random_N10!$C23:$K23),MC_Random_N10!$B23*(1-EQ$1),0) -> 0 | ER23: =IF(ER$1*MC_Random_N10!$B23>=0.9*MAX(MC_Random_N10!$C23:$K23),MC_Random_N10!$B23*(1-ER$1),0) -> 0 | ... ET23: =IF(ET$1*MC_Random_N10!$B23>=0.9*MAX(MC_Random_N10!$C23:$K23),MC_Random_N10!$B23*(1-ET$1),0) -> 0 | FF23: 22 | FG23: =MAX(FG$1*MC_Random_N10!$B23,0.9*MAX(MC_Random_N10!$C23:$K23)) -> 0.78093671 | FH23: =MAX(FH$1*MC_Random_N10!$B23,0.9*MAX(MC_Random_N10!$C23:$K23)) -> 0.78093671 | FI23: =MAX(FI$1*MC_Random_N10!$B23,0.9*MAX(MC_Random_N10!$C23:$K23)) -> 0.78093671 | FJ23: =MAX(FJ$1*MC_Random_N10!$B23,0.9*MAX(MC_Random_N10!$C23:$K23)) -> 0.78093671 | FK23: =MAX(FK$1*MC_Random_N10!$B23,0.9*MAX(MC_Random_N10!$C23:$K23)) -> 0.78093671 | FL23: =MAX(FL$1*MC_Random_N10!$B23,0.9*MAX(MC_Random_N10!$C23:$K23)) -> 0.78093671 | FM23: =MAX(FM$1*MC_Random_N10!$B23,0.9*MAX(MC_Random_N10!$C23:$K23)) -> 0.78093671 | FN23: =MAX(FN$1*MC_Random_N10!$B23,0.9*MAX(MC_Random_N10!$C23:$K23)) -> 0.78093671 | ... FP23: =MAX(FP$1*MC_Random_N10!$B23,0.9*MAX(MC_Random_N10!$C23:$K23)) -> 0.78093671
S24: 23 | T24: =IF(T$1*MC_Random_N2!$B24>=0.5*MC_Random_N2!$C24,MC_Random_N2!$B24*(1-T$1),0) -> 0 | U24: =IF(U$1*MC_Random_N2!$B24>=0.5*MC_Random_N2!$C24,MC_Random_N2!$B24*(1-U$1),0) -> 0 | V24: =IF(V$1*MC_Random_N2!$B24>=0.5*MC_Random_N2!$C24,MC_Random_N2!$B24*(1-V$1),0) -> 0 | W24: =IF(W$1*MC_Random_N2!$B24>=0.5*MC_Random_N2!$C24,MC_Random_N2!$B24*(1-W$1),0) -> 0 | X24: =IF(X$1*MC_Random_N2!$B24>=0.5*MC_Random_N2!$C24,MC_Random_N2!$B24*(1-X$1),0) -> 0 | Y24: =IF(Y$1*MC_Random_N2!$B24>=0.5*MC_Random_N2!$C24,MC_Random_N2!$B24*(1-Y$1),0) -> 0 | Z24: =IF(Z$1*MC_Random_N2!$B24>=0.5*MC_Random_N2!$C24,MC_Random_N2!$B24*(1-Z$1),0) -> 0 | AA24: =IF(AA$1*MC_Random_N2!$B24>=0.5*MC_Random_N2!$C24,MC_Random_N2!$B24*(1-AA$1),0) -> 0 | ... AC24: =IF(AC$1*MC_Random_N2!$B24>=0.5*MC_Random_N2!$C24,MC_Random_N2!$B24*(1-AC$1),0) -> 0 | AP24: 23 | AQ24: =MAX(AQ$1*MC_Random_N2!$B24,0.5*MC_Random_N2!$C24) -> 0.45094474 | AR24: =MAX(AR$1*MC_Random_N2!$B24,0.5*MC_Random_N2!$C24) -> 0.45094474 | AS24: =MAX(AS$1*MC_Random_N2!$B24,0.5*MC_Random_N2!$C24) -> 0.45094474 | AT24: =MAX(AT$1*MC_Random_N2!$B24,0.5*MC_Random_N2!$C24) -> 0.45094474 | AU24: =MAX(AU$1*MC_Random_N2!$B24,0.5*MC_Random_N2!$C24) -> 0.45094474 | AV24: =MAX(AV$1*MC_Random_N2!$B24,0.5*MC_Random_N2!$C24) -> 0.45094474 | AW24: =MAX(AW$1*MC_Random_N2!$B24,0.5*MC_Random_N2!$C24) -> 0.45094474 | AX24: =MAX(AX$1*MC_Random_N2!$B24,0.5*MC_Random_N2!$C24) -> 0.45094474 | ... AZ24: =MAX(AZ$1*MC_Random_N2!$B24,0.5*MC_Random_N2!$C24) -> 0.45094474 | CG24: 23 | CH24: =IF(CH$1*MC_Random_N5!$B24>=0.8*MAX(MC_Random_N5!$C24:$F24),MC_Random_N5!$B24*(1-CH$1),0) -> 0 | CI24: =IF(CI$1*MC_Random_N5!$B24>=0.8*MAX(MC_Random_N5!$C24:$F24),MC_Random_N5!$B24*(1-CI$1),0) -> 0 | CJ24: =IF(CJ$1*MC_Random_N5!$B24>=0.8*MAX(MC_Random_N5!$C24:$F24),MC_Random_N5!$B24*(1-CJ$1),0) -> 0 | CK24: =IF(CK$1*MC_Random_N5!$B24>=0.8*MAX(MC_Random_N5!$C24:$F24),MC_Random_N5!$B24*(1-CK$1),0) -> 0 | CL24: =IF(CL$1*MC_Random_N5!$B24>=0.8*MAX(MC_Random_N5!$C24:$F24),MC_Random_N5!$B24*(1-CL$1),0) -> 0 | CM24: =IF(CM$1*MC_Random_N5!$B24>=0.8*MAX(MC_Random_N5!$C24:$F24),MC_Random_N5!$B24*(1-CM$1),0) -> 0 | CN24: =IF(CN$1*MC_Random_N5!$B24>=0.8*MAX(MC_Random_N5!$C24:$F24),MC_Random_N5!$B24*(1-CN$1),0) -> 0 | CO24: =IF(CO$1*MC_Random_N5!$B24>=0.8*MAX(MC_Random_N5!$C24:$F24),MC_Random_N5!$B24*(1-CO$1),0) -> 0 | ... CQ24: =IF(CQ$1*MC_Random_N5!$B24>=0.8*MAX(MC_Random_N5!$C24:$F24),MC_Random_N5!$B24*(1-CQ$1),0) -> 0 | DD24: 23 | DE24: =MAX(DE$1*MC_Random_N5!$B24,0.8*MAX(MC_Random_N5!$C24:$F24)) -> 0.63115025 | DF24: =MAX(DF$1*MC_Random_N5!$B24,0.8*MAX(MC_Random_N5!$C24:$F24)) -> 0.63115025 | DG24: =MAX(DG$1*MC_Random_N5!$B24,0.8*MAX(MC_Random_N5!$C24:$F24)) -> 0.63115025 | DH24: =MAX(DH$1*MC_Random_N5!$B24,0.8*MAX(MC_Random_N5!$C24:$F24)) -> 0.63115025 | DI24: =MAX(DI$1*MC_Random_N5!$B24,0.8*MAX(MC_Random_N5!$C24:$F24)) -> 0.63115025 | DJ24: =MAX(DJ$1*MC_Random_N5!$B24,0.8*MAX(MC_Random_N5!$C24:$F24)) -> 0.63115025 | DK24: =MAX(DK$1*MC_Random_N5!$B24,0.8*MAX(MC_Random_N5!$C24:$F24)) -> 0.63115025 | DL24: =MAX(DL$1*MC_Random_N5!$B24,0.8*MAX(MC_Random_N5!$C24:$F24)) -> 0.63115025 | ... DN24: =MAX(DN$1*MC_Random_N5!$B24,0.8*MAX(MC_Random_N5!$C24:$F24)) -> 0.69758479 | EJ24: 23 | EK24: =IF(EK$1*MC_Random_N10!$B24>=0.9*MAX(MC_Random_N10!$C24:$K24),MC_Random_N10!$B24*(1-EK$1),0) -> 0 | EL24: =IF(EL$1*MC_Random_N10!$B24>=0.9*MAX(MC_Random_N10!$C24:$K24),MC_Random_N10!$B24*(1-EL$1),0) -> 0 | EM24: =IF(EM$1*MC_Random_N10!$B24>=0.9*MAX(MC_Random_N10!$C24:$K24),MC_Random_N10!$B24*(1-EM$1),0) -> 0 | EN24: =IF(EN$1*MC_Random_N10!$B24>=0.9*MAX(MC_Random_N10!$C24:$K24),MC_Random_N10!$B24*(1-EN$1),0) -> 0 | EO24: =IF(EO$1*MC_Random_N10!$B24>=0.9*MAX(MC_Random_N10!$C24:$K24),MC_Random_N10!$B24*(1-EO$1),0) -> 0 | EP24: =IF(EP$1*MC_Random_N10!$B24>=0.9*MAX(MC_Random_N10!$C24:$K24),MC_Random_N10!$B24*(1-EP$1),0) -> 0 | EQ24: =IF(EQ$1*MC_Random_N10!$B24>=0.9*MAX(MC_Random_N10!$C24:$K24),MC_Random_N10!$B24*(1-EQ$1),0) -> 0 | ER24: =IF(ER$1*MC_Random_N10!$B24>=0.9*MAX(MC_Random_N10!$C24:$K24),MC_Random_N10!$B24*(1-ER$1),0) -> 0 | ... ET24: =IF(ET$1*MC_Random_N10!$B24>=0.9*MAX(MC_Random_N10!$C24:$K24),MC_Random_N10!$B24*(1-ET$1),0) -> 0 | FF24: 23 | FG24: =MAX(FG$1*MC_Random_N10!$B24,0.9*MAX(MC_Random_N10!$C24:$K24)) -> 0.74034381 | FH24: =MAX(FH$1*MC_Random_N10!$B24,0.9*MAX(MC_Random_N10!$C24:$K24)) -> 0.74034381 | FI24: =MAX(FI$1*MC_Random_N10!$B24,0.9*MAX(MC_Random_N10!$C24:$K24)) -> 0.74034381 | FJ24: =MAX(FJ$1*MC_Random_N10!$B24,0.9*MAX(MC_Random_N10!$C24:$K24)) -> 0.74034381 | FK24: =MAX(FK$1*MC_Random_N10!$B24,0.9*MAX(MC_Random_N10!$C24:$K24)) -> 0.74034381 | FL24: =MAX(FL$1*MC_Random_N10!$B24,0.9*MAX(MC_Random_N10!$C24:$K24)) -> 0.74034381 | FM24: =MAX(FM$1*MC_Random_N10!$B24,0.9*MAX(MC_Random_N10!$C24:$K24)) -> 0.74034381 | FN24: =MAX(FN$1*MC_Random_N10!$B24,0.9*MAX(MC_Random_N10!$C24:$K24)) -> 0.74034381 | ... FP24: =MAX(FP$1*MC_Random_N10!$B24,0.9*MAX(MC_Random_N10!$C24:$K24)) -> 0.74034381
S25: 24 | T25: =IF(T$1*MC_Random_N2!$B25>=0.5*MC_Random_N2!$C25,MC_Random_N2!$B25*(1-T$1),0) -> 0 | U25: =IF(U$1*MC_Random_N2!$B25>=0.5*MC_Random_N2!$C25,MC_Random_N2!$B25*(1-U$1),0) -> 0 | V25: =IF(V$1*MC_Random_N2!$B25>=0.5*MC_Random_N2!$C25,MC_Random_N2!$B25*(1-V$1),0) -> 0 | W25: =IF(W$1*MC_Random_N2!$B25>=0.5*MC_Random_N2!$C25,MC_Random_N2!$B25*(1-W$1),0) -> 0 | X25: =IF(X$1*MC_Random_N2!$B25>=0.5*MC_Random_N2!$C25,MC_Random_N2!$B25*(1-X$1),0) -> 0 | Y25: =IF(Y$1*MC_Random_N2!$B25>=0.5*MC_Random_N2!$C25,MC_Random_N2!$B25*(1-Y$1),0) -> 0 | Z25: =IF(Z$1*MC_Random_N2!$B25>=0.5*MC_Random_N2!$C25,MC_Random_N2!$B25*(1-Z$1),0) -> 0.16566452 | AA25: =IF(AA$1*MC_Random_N2!$B25>=0.5*MC_Random_N2!$C25,MC_Random_N2!$B25*(1-AA$1),0) -> 0.11044301 | ... AC25: =IF(AC$1*MC_Random_N2!$B25>=0.5*MC_Random_N2!$C25,MC_Random_N2!$B25*(1-AC$1),0) -> 0 | AP25: 24 | AQ25: =MAX(AQ$1*MC_Random_N2!$B25,0.5*MC_Random_N2!$C25) -> 0.38222519 | AR25: =MAX(AR$1*MC_Random_N2!$B25,0.5*MC_Random_N2!$C25) -> 0.38222519 | AS25: =MAX(AS$1*MC_Random_N2!$B25,0.5*MC_Random_N2!$C25) -> 0.38222519 | AT25: =MAX(AT$1*MC_Random_N2!$B25,0.5*MC_Random_N2!$C25) -> 0.38222519 | AU25: =MAX(AU$1*MC_Random_N2!$B25,0.5*MC_Random_N2!$C25) -> 0.38222519 | AV25: =MAX(AV$1*MC_Random_N2!$B25,0.5*MC_Random_N2!$C25) -> 0.38222519 | AW25: =MAX(AW$1*MC_Random_N2!$B25,0.5*MC_Random_N2!$C25) -> 0.38655054 | AX25: =MAX(AX$1*MC_Random_N2!$B25,0.5*MC_Random_N2!$C25) -> 0.44177204 | ... AZ25: =MAX(AZ$1*MC_Random_N2!$B25,0.5*MC_Random_N2!$C25) -> 0.55221505 | CG25: 24 | CH25: =IF(CH$1*MC_Random_N5!$B25>=0.8*MAX(MC_Random_N5!$C25:$F25),MC_Random_N5!$B25*(1-CH$1),0) -> 0 | CI25: =IF(CI$1*MC_Random_N5!$B25>=0.8*MAX(MC_Random_N5!$C25:$F25),MC_Random_N5!$B25*(1-CI$1),0) -> 0 | CJ25: =IF(CJ$1*MC_Random_N5!$B25>=0.8*MAX(MC_Random_N5!$C25:$F25),MC_Random_N5!$B25*(1-CJ$1),0) -> 0 | CK25: =IF(CK$1*MC_Random_N5!$B25>=0.8*MAX(MC_Random_N5!$C25:$F25),MC_Random_N5!$B25*(1-CK$1),0) -> 0 | CL25: =IF(CL$1*MC_Random_N5!$B25>=0.8*MAX(MC_Random_N5!$C25:$F25),MC_Random_N5!$B25*(1-CL$1),0) -> 0 | CM25: =IF(CM$1*MC_Random_N5!$B25>=0.8*MAX(MC_Random_N5!$C25:$F25),MC_Random_N5!$B25*(1-CM$1),0) -> 0 | CN25: =IF(CN$1*MC_Random_N5!$B25>=0.8*MAX(MC_Random_N5!$C25:$F25),MC_Random_N5!$B25*(1-CN$1),0) -> 0 | CO25: =IF(CO$1*MC_Random_N5!$B25>=0.8*MAX(MC_Random_N5!$C25:$F25),MC_Random_N5!$B25*(1-CO$1),0) -> 0 | ... CQ25: =IF(CQ$1*MC_Random_N5!$B25>=0.8*MAX(MC_Random_N5!$C25:$F25),MC_Random_N5!$B25*(1-CQ$1),0) -> 0 | DD25: 24 | DE25: =MAX(DE$1*MC_Random_N5!$B25,0.8*MAX(MC_Random_N5!$C25:$F25)) -> 0.46675684 | DF25: =MAX(DF$1*MC_Random_N5!$B25,0.8*MAX(MC_Random_N5!$C25:$F25)) -> 0.46675684 | DG25: =MAX(DG$1*MC_Random_N5!$B25,0.8*MAX(MC_Random_N5!$C25:$F25)) -> 0.46675684 | DH25: =MAX(DH$1*MC_Random_N5!$B25,0.8*MAX(MC_Random_N5!$C25:$F25)) -> 0.46675684 | DI25: =MAX(DI$1*MC_Random_N5!$B25,0.8*MAX(MC_Random_N5!$C25:$F25)) -> 0.46675684 | DJ25: =MAX(DJ$1*MC_Random_N5!$B25,0.8*MAX(MC_Random_N5!$C25:$F25)) -> 0.46675684 | DK25: =MAX(DK$1*MC_Random_N5!$B25,0.8*MAX(MC_Random_N5!$C25:$F25)) -> 0.46675684 | DL25: =MAX(DL$1*MC_Random_N5!$B25,0.8*MAX(MC_Random_N5!$C25:$F25)) -> 0.46675684 | ... DN25: =MAX(DN$1*MC_Random_N5!$B25,0.8*MAX(MC_Random_N5!$C25:$F25)) -> 0.5610419 | EJ25: 24 | EK25: =IF(EK$1*MC_Random_N10!$B25>=0.9*MAX(MC_Random_N10!$C25:$K25),MC_Random_N10!$B25*(1-EK$1),0) -> 0 | EL25: =IF(EL$1*MC_Random_N10!$B25>=0.9*MAX(MC_Random_N10!$C25:$K25),MC_Random_N10!$B25*(1-EL$1),0) -> 0 | EM25: =IF(EM$1*MC_Random_N10!$B25>=0.9*MAX(MC_Random_N10!$C25:$K25),MC_Random_N10!$B25*(1-EM$1),0) -> 0 | EN25: =IF(EN$1*MC_Random_N10!$B25>=0.9*MAX(MC_Random_N10!$C25:$K25),MC_Random_N10!$B25*(1-EN$1),0) -> 0 | EO25: =IF(EO$1*MC_Random_N10!$B25>=0.9*MAX(MC_Random_N10!$C25:$K25),MC_Random_N10!$B25*(1-EO$1),0) -> 0 | EP25: =IF(EP$1*MC_Random_N10!$B25>=0.9*MAX(MC_Random_N10!$C25:$K25),MC_Random_N10!$B25*(1-EP$1),0) -> 0 | EQ25: =IF(EQ$1*MC_Random_N10!$B25>=0.9*MAX(MC_Random_N10!$C25:$K25),MC_Random_N10!$B25*(1-EQ$1),0) -> 0 | ER25: =IF(ER$1*MC_Random_N10!$B25>=0.9*MAX(MC_Random_N10!$C25:$K25),MC_Random_N10!$B25*(1-ER$1),0) -> 0 | ... ET25: =IF(ET$1*MC_Random_N10!$B25>=0.9*MAX(MC_Random_N10!$C25:$K25),MC_Random_N10!$B25*(1-ET$1),0) -> 0 | FF25: 24 | FG25: =MAX(FG$1*MC_Random_N10!$B25,0.9*MAX(MC_Random_N10!$C25:$K25)) -> 0.88761557 | FH25: =MAX(FH$1*MC_Random_N10!$B25,0.9*MAX(MC_Random_N10!$C25:$K25)) -> 0.88761557 | FI25: =MAX(FI$1*MC_Random_N10!$B25,0.9*MAX(MC_Random_N10!$C25:$K25)) -> 0.88761557 | FJ25: =MAX(FJ$1*MC_Random_N10!$B25,0.9*MAX(MC_Random_N10!$C25:$K25)) -> 0.88761557 | FK25: =MAX(FK$1*MC_Random_N10!$B25,0.9*MAX(MC_Random_N10!$C25:$K25)) -> 0.88761557 | FL25: =MAX(FL$1*MC_Random_N10!$B25,0.9*MAX(MC_Random_N10!$C25:$K25)) -> 0.88761557 | FM25: =MAX(FM$1*MC_Random_N10!$B25,0.9*MAX(MC_Random_N10!$C25:$K25)) -> 0.88761557 | FN25: =MAX(FN$1*MC_Random_N10!$B25,0.9*MAX(MC_Random_N10!$C25:$K25)) -> 0.88761557 | ... FP25: =MAX(FP$1*MC_Random_N10!$B25,0.9*MAX(MC_Random_N10!$C25:$K25)) -> 0.88761557
S26: 25 | T26: =IF(T$1*MC_Random_N2!$B26>=0.5*MC_Random_N2!$C26,MC_Random_N2!$B26*(1-T$1),0) -> 0 | U26: =IF(U$1*MC_Random_N2!$B26>=0.5*MC_Random_N2!$C26,MC_Random_N2!$B26*(1-U$1),0) -> 0 | V26: =IF(V$1*MC_Random_N2!$B26>=0.5*MC_Random_N2!$C26,MC_Random_N2!$B26*(1-V$1),0) -> 0 | W26: =IF(W$1*MC_Random_N2!$B26>=0.5*MC_Random_N2!$C26,MC_Random_N2!$B26*(1-W$1),0) -> 0 | X26: =IF(X$1*MC_Random_N2!$B26>=0.5*MC_Random_N2!$C26,MC_Random_N2!$B26*(1-X$1),0) -> 0 | Y26: =IF(Y$1*MC_Random_N2!$B26>=0.5*MC_Random_N2!$C26,MC_Random_N2!$B26*(1-Y$1),0) -> 0 | Z26: =IF(Z$1*MC_Random_N2!$B26>=0.5*MC_Random_N2!$C26,MC_Random_N2!$B26*(1-Z$1),0) -> 0 | AA26: =IF(AA$1*MC_Random_N2!$B26>=0.5*MC_Random_N2!$C26,MC_Random_N2!$B26*(1-AA$1),0) -> 0 | ... AC26: =IF(AC$1*MC_Random_N2!$B26>=0.5*MC_Random_N2!$C26,MC_Random_N2!$B26*(1-AC$1),0) -> 0 | AP26: 25 | AQ26: =MAX(AQ$1*MC_Random_N2!$B26,0.5*MC_Random_N2!$C26) -> 0.32877703 | AR26: =MAX(AR$1*MC_Random_N2!$B26,0.5*MC_Random_N2!$C26) -> 0.32877703 | AS26: =MAX(AS$1*MC_Random_N2!$B26,0.5*MC_Random_N2!$C26) -> 0.32877703 | AT26: =MAX(AT$1*MC_Random_N2!$B26,0.5*MC_Random_N2!$C26) -> 0.32877703 | AU26: =MAX(AU$1*MC_Random_N2!$B26,0.5*MC_Random_N2!$C26) -> 0.32877703 | AV26: =MAX(AV$1*MC_Random_N2!$B26,0.5*MC_Random_N2!$C26) -> 0.32877703 | AW26: =MAX(AW$1*MC_Random_N2!$B26,0.5*MC_Random_N2!$C26) -> 0.32877703 | AX26: =MAX(AX$1*MC_Random_N2!$B26,0.5*MC_Random_N2!$C26) -> 0.32877703 | ... AZ26: =MAX(AZ$1*MC_Random_N2!$B26,0.5*MC_Random_N2!$C26) -> 0.32877703 | CG26: 25 | CH26: =IF(CH$1*MC_Random_N5!$B26>=0.8*MAX(MC_Random_N5!$C26:$F26),MC_Random_N5!$B26*(1-CH$1),0) -> 0 | CI26: =IF(CI$1*MC_Random_N5!$B26>=0.8*MAX(MC_Random_N5!$C26:$F26),MC_Random_N5!$B26*(1-CI$1),0) -> 0 | CJ26: =IF(CJ$1*MC_Random_N5!$B26>=0.8*MAX(MC_Random_N5!$C26:$F26),MC_Random_N5!$B26*(1-CJ$1),0) -> 0 | CK26: =IF(CK$1*MC_Random_N5!$B26>=0.8*MAX(MC_Random_N5!$C26:$F26),MC_Random_N5!$B26*(1-CK$1),0) -> 0 | CL26: =IF(CL$1*MC_Random_N5!$B26>=0.8*MAX(MC_Random_N5!$C26:$F26),MC_Random_N5!$B26*(1-CL$1),0) -> 0 | CM26: =IF(CM$1*MC_Random_N5!$B26>=0.8*MAX(MC_Random_N5!$C26:$F26),MC_Random_N5!$B26*(1-CM$1),0) -> 0 | CN26: =IF(CN$1*MC_Random_N5!$B26>=0.8*MAX(MC_Random_N5!$C26:$F26),MC_Random_N5!$B26*(1-CN$1),0) -> 0 | CO26: =IF(CO$1*MC_Random_N5!$B26>=0.8*MAX(MC_Random_N5!$C26:$F26),MC_Random_N5!$B26*(1-CO$1),0) -> 0 | ... CQ26: =IF(CQ$1*MC_Random_N5!$B26>=0.8*MAX(MC_Random_N5!$C26:$F26),MC_Random_N5!$B26*(1-CQ$1),0) -> 0 | DD26: 25 | DE26: =MAX(DE$1*MC_Random_N5!$B26,0.8*MAX(MC_Random_N5!$C26:$F26)) -> 0.70797271 | DF26: =MAX(DF$1*MC_Random_N5!$B26,0.8*MAX(MC_Random_N5!$C26:$F26)) -> 0.70797271 | DG26: =MAX(DG$1*MC_Random_N5!$B26,0.8*MAX(MC_Random_N5!$C26:$F26)) -> 0.70797271 | DH26: =MAX(DH$1*MC_Random_N5!$B26,0.8*MAX(MC_Random_N5!$C26:$F26)) -> 0.70797271 | DI26: =MAX(DI$1*MC_Random_N5!$B26,0.8*MAX(MC_Random_N5!$C26:$F26)) -> 0.70797271 | DJ26: =MAX(DJ$1*MC_Random_N5!$B26,0.8*MAX(MC_Random_N5!$C26:$F26)) -> 0.70797271 | DK26: =MAX(DK$1*MC_Random_N5!$B26,0.8*MAX(MC_Random_N5!$C26:$F26)) -> 0.70797271 | DL26: =MAX(DL$1*MC_Random_N5!$B26,0.8*MAX(MC_Random_N5!$C26:$F26)) -> 0.70797271 | ... DN26: =MAX(DN$1*MC_Random_N5!$B26,0.8*MAX(MC_Random_N5!$C26:$F26)) -> 0.70797271 | EJ26: 25 | EK26: =IF(EK$1*MC_Random_N10!$B26>=0.9*MAX(MC_Random_N10!$C26:$K26),MC_Random_N10!$B26*(1-EK$1),0) -> 0 | EL26: =IF(EL$1*MC_Random_N10!$B26>=0.9*MAX(MC_Random_N10!$C26:$K26),MC_Random_N10!$B26*(1-EL$1),0) -> 0 | EM26: =IF(EM$1*MC_Random_N10!$B26>=0.9*MAX(MC_Random_N10!$C26:$K26),MC_Random_N10!$B26*(1-EM$1),0) -> 0 | EN26: =IF(EN$1*MC_Random_N10!$B26>=0.9*MAX(MC_Random_N10!$C26:$K26),MC_Random_N10!$B26*(1-EN$1),0) -> 0 | EO26: =IF(EO$1*MC_Random_N10!$B26>=0.9*MAX(MC_Random_N10!$C26:$K26),MC_Random_N10!$B26*(1-EO$1),0) -> 0 | EP26: =IF(EP$1*MC_Random_N10!$B26>=0.9*MAX(MC_Random_N10!$C26:$K26),MC_Random_N10!$B26*(1-EP$1),0) -> 0 | EQ26: =IF(EQ$1*MC_Random_N10!$B26>=0.9*MAX(MC_Random_N10!$C26:$K26),MC_Random_N10!$B26*(1-EQ$1),0) -> 0 | ER26: =IF(ER$1*MC_Random_N10!$B26>=0.9*MAX(MC_Random_N10!$C26:$K26),MC_Random_N10!$B26*(1-ER$1),0) -> 0 | ... ET26: =IF(ET$1*MC_Random_N10!$B26>=0.9*MAX(MC_Random_N10!$C26:$K26),MC_Random_N10!$B26*(1-ET$1),0) -> 0 | FF26: 25 | FG26: =MAX(FG$1*MC_Random_N10!$B26,0.9*MAX(MC_Random_N10!$C26:$K26)) -> 0.89576911 | FH26: =MAX(FH$1*MC_Random_N10!$B26,0.9*MAX(MC_Random_N10!$C26:$K26)) -> 0.89576911 | FI26: =MAX(FI$1*MC_Random_N10!$B26,0.9*MAX(MC_Random_N10!$C26:$K26)) -> 0.89576911 | FJ26: =MAX(FJ$1*MC_Random_N10!$B26,0.9*MAX(MC_Random_N10!$C26:$K26)) -> 0.89576911 | FK26: =MAX(FK$1*MC_Random_N10!$B26,0.9*MAX(MC_Random_N10!$C26:$K26)) -> 0.89576911 | FL26: =MAX(FL$1*MC_Random_N10!$B26,0.9*MAX(MC_Random_N10!$C26:$K26)) -> 0.89576911 | FM26: =MAX(FM$1*MC_Random_N10!$B26,0.9*MAX(MC_Random_N10!$C26:$K26)) -> 0.89576911 | FN26: =MAX(FN$1*MC_Random_N10!$B26,0.9*MAX(MC_Random_N10!$C26:$K26)) -> 0.89576911 | ... FP26: =MAX(FP$1*MC_Random_N10!$B26,0.9*MAX(MC_Random_N10!$C26:$K26)) -> 0.89576911
S27: 26 | T27: =IF(T$1*MC_Random_N2!$B27>=0.5*MC_Random_N2!$C27,MC_Random_N2!$B27*(1-T$1),0) -> 0 | U27: =IF(U$1*MC_Random_N2!$B27>=0.5*MC_Random_N2!$C27,MC_Random_N2!$B27*(1-U$1),0) -> 0 | V27: =IF(V$1*MC_Random_N2!$B27>=0.5*MC_Random_N2!$C27,MC_Random_N2!$B27*(1-V$1),0) -> 0 | W27: =IF(W$1*MC_Random_N2!$B27>=0.5*MC_Random_N2!$C27,MC_Random_N2!$B27*(1-W$1),0) -> 0 | X27: =IF(X$1*MC_Random_N2!$B27>=0.5*MC_Random_N2!$C27,MC_Random_N2!$B27*(1-X$1),0) -> 0 | Y27: =IF(Y$1*MC_Random_N2!$B27>=0.5*MC_Random_N2!$C27,MC_Random_N2!$B27*(1-Y$1),0) -> 0.29886703 | Z27: =IF(Z$1*MC_Random_N2!$B27>=0.5*MC_Random_N2!$C27,MC_Random_N2!$B27*(1-Z$1),0) -> 0.22415027 | AA27: =IF(AA$1*MC_Random_N2!$B27>=0.5*MC_Random_N2!$C27,MC_Random_N2!$B27*(1-AA$1),0) -> 0.14943351 | ... AC27: =IF(AC$1*MC_Random_N2!$B27>=0.5*MC_Random_N2!$C27,MC_Random_N2!$B27*(1-AC$1),0) -> 0 | AP27: 26 | AQ27: =MAX(AQ$1*MC_Random_N2!$B27,0.5*MC_Random_N2!$C27) -> 0.43194637 | AR27: =MAX(AR$1*MC_Random_N2!$B27,0.5*MC_Random_N2!$C27) -> 0.43194637 | AS27: =MAX(AS$1*MC_Random_N2!$B27,0.5*MC_Random_N2!$C27) -> 0.43194637 | AT27: =MAX(AT$1*MC_Random_N2!$B27,0.5*MC_Random_N2!$C27) -> 0.43194637 | AU27: =MAX(AU$1*MC_Random_N2!$B27,0.5*MC_Random_N2!$C27) -> 0.43194637 | AV27: =MAX(AV$1*MC_Random_N2!$B27,0.5*MC_Random_N2!$C27) -> 0.44830054 | AW27: =MAX(AW$1*MC_Random_N2!$B27,0.5*MC_Random_N2!$C27) -> 0.5230173 | AX27: =MAX(AX$1*MC_Random_N2!$B27,0.5*MC_Random_N2!$C27) -> 0.59773406 | ... AZ27: =MAX(AZ$1*MC_Random_N2!$B27,0.5*MC_Random_N2!$C27) -> 0.74716757 | CG27: 26 | CH27: =IF(CH$1*MC_Random_N5!$B27>=0.8*MAX(MC_Random_N5!$C27:$F27),MC_Random_N5!$B27*(1-CH$1),0) -> 0 | CI27: =IF(CI$1*MC_Random_N5!$B27>=0.8*MAX(MC_Random_N5!$C27:$F27),MC_Random_N5!$B27*(1-CI$1),0) -> 0 | CJ27: =IF(CJ$1*MC_Random_N5!$B27>=0.8*MAX(MC_Random_N5!$C27:$F27),MC_Random_N5!$B27*(1-CJ$1),0) -> 0 | CK27: =IF(CK$1*MC_Random_N5!$B27>=0.8*MAX(MC_Random_N5!$C27:$F27),MC_Random_N5!$B27*(1-CK$1),0) -> 0 | CL27: =IF(CL$1*MC_Random_N5!$B27>=0.8*MAX(MC_Random_N5!$C27:$F27),MC_Random_N5!$B27*(1-CL$1),0) -> 0 | CM27: =IF(CM$1*MC_Random_N5!$B27>=0.8*MAX(MC_Random_N5!$C27:$F27),MC_Random_N5!$B27*(1-CM$1),0) -> 0 | CN27: =IF(CN$1*MC_Random_N5!$B27>=0.8*MAX(MC_Random_N5!$C27:$F27),MC_Random_N5!$B27*(1-CN$1),0) -> 0 | CO27: =IF(CO$1*MC_Random_N5!$B27>=0.8*MAX(MC_Random_N5!$C27:$F27),MC_Random_N5!$B27*(1-CO$1),0) -> 0 | ... CQ27: =IF(CQ$1*MC_Random_N5!$B27>=0.8*MAX(MC_Random_N5!$C27:$F27),MC_Random_N5!$B27*(1-CQ$1),0) -> 0 | DD27: 26 | DE27: =MAX(DE$1*MC_Random_N5!$B27,0.8*MAX(MC_Random_N5!$C27:$F27)) -> 0.73650903 | DF27: =MAX(DF$1*MC_Random_N5!$B27,0.8*MAX(MC_Random_N5!$C27:$F27)) -> 0.73650903 | DG27: =MAX(DG$1*MC_Random_N5!$B27,0.8*MAX(MC_Random_N5!$C27:$F27)) -> 0.73650903 | DH27: =MAX(DH$1*MC_Random_N5!$B27,0.8*MAX(MC_Random_N5!$C27:$F27)) -> 0.73650903 | DI27: =MAX(DI$1*MC_Random_N5!$B27,0.8*MAX(MC_Random_N5!$C27:$F27)) -> 0.73650903 | DJ27: =MAX(DJ$1*MC_Random_N5!$B27,0.8*MAX(MC_Random_N5!$C27:$F27)) -> 0.73650903 | DK27: =MAX(DK$1*MC_Random_N5!$B27,0.8*MAX(MC_Random_N5!$C27:$F27)) -> 0.73650903 | DL27: =MAX(DL$1*MC_Random_N5!$B27,0.8*MAX(MC_Random_N5!$C27:$F27)) -> 0.73650903 | ... DN27: =MAX(DN$1*MC_Random_N5!$B27,0.8*MAX(MC_Random_N5!$C27:$F27)) -> 0.76516029 | EJ27: 26 | EK27: =IF(EK$1*MC_Random_N10!$B27>=0.9*MAX(MC_Random_N10!$C27:$K27),MC_Random_N10!$B27*(1-EK$1),0) -> 0 | EL27: =IF(EL$1*MC_Random_N10!$B27>=0.9*MAX(MC_Random_N10!$C27:$K27),MC_Random_N10!$B27*(1-EL$1),0) -> 0 | EM27: =IF(EM$1*MC_Random_N10!$B27>=0.9*MAX(MC_Random_N10!$C27:$K27),MC_Random_N10!$B27*(1-EM$1),0) -> 0 | EN27: =IF(EN$1*MC_Random_N10!$B27>=0.9*MAX(MC_Random_N10!$C27:$K27),MC_Random_N10!$B27*(1-EN$1),0) -> 0 | EO27: =IF(EO$1*MC_Random_N10!$B27>=0.9*MAX(MC_Random_N10!$C27:$K27),MC_Random_N10!$B27*(1-EO$1),0) -> 0 | EP27: =IF(EP$1*MC_Random_N10!$B27>=0.9*MAX(MC_Random_N10!$C27:$K27),MC_Random_N10!$B27*(1-EP$1),0) -> 0 | EQ27: =IF(EQ$1*MC_Random_N10!$B27>=0.9*MAX(MC_Random_N10!$C27:$K27),MC_Random_N10!$B27*(1-EQ$1),0) -> 0 | ER27: =IF(ER$1*MC_Random_N10!$B27>=0.9*MAX(MC_Random_N10!$C27:$K27),MC_Random_N10!$B27*(1-ER$1),0) -> 0 | ... ET27: =IF(ET$1*MC_Random_N10!$B27>=0.9*MAX(MC_Random_N10!$C27:$K27),MC_Random_N10!$B27*(1-ET$1),0) -> 0 | FF27: 26 | FG27: =MAX(FG$1*MC_Random_N10!$B27,0.9*MAX(MC_Random_N10!$C27:$K27)) -> 0.78226963 | FH27: =MAX(FH$1*MC_Random_N10!$B27,0.9*MAX(MC_Random_N10!$C27:$K27)) -> 0.78226963 | FI27: =MAX(FI$1*MC_Random_N10!$B27,0.9*MAX(MC_Random_N10!$C27:$K27)) -> 0.78226963 | FJ27: =MAX(FJ$1*MC_Random_N10!$B27,0.9*MAX(MC_Random_N10!$C27:$K27)) -> 0.78226963 | FK27: =MAX(FK$1*MC_Random_N10!$B27,0.9*MAX(MC_Random_N10!$C27:$K27)) -> 0.78226963 | FL27: =MAX(FL$1*MC_Random_N10!$B27,0.9*MAX(MC_Random_N10!$C27:$K27)) -> 0.78226963 | FM27: =MAX(FM$1*MC_Random_N10!$B27,0.9*MAX(MC_Random_N10!$C27:$K27)) -> 0.78226963 | FN27: =MAX(FN$1*MC_Random_N10!$B27,0.9*MAX(MC_Random_N10!$C27:$K27)) -> 0.78226963 | ... FP27: =MAX(FP$1*MC_Random_N10!$B27,0.9*MAX(MC_Random_N10!$C27:$K27)) -> 0.78226963
S28: 27 | T28: =IF(T$1*MC_Random_N2!$B28>=0.5*MC_Random_N2!$C28,MC_Random_N2!$B28*(1-T$1),0) -> 0 | U28: =IF(U$1*MC_Random_N2!$B28>=0.5*MC_Random_N2!$C28,MC_Random_N2!$B28*(1-U$1),0) -> 0 | V28: =IF(V$1*MC_Random_N2!$B28>=0.5*MC_Random_N2!$C28,MC_Random_N2!$B28*(1-V$1),0) -> 0 | W28: =IF(W$1*MC_Random_N2!$B28>=0.5*MC_Random_N2!$C28,MC_Random_N2!$B28*(1-W$1),0) -> 0 | X28: =IF(X$1*MC_Random_N2!$B28>=0.5*MC_Random_N2!$C28,MC_Random_N2!$B28*(1-X$1),0) -> 0 | Y28: =IF(Y$1*MC_Random_N2!$B28>=0.5*MC_Random_N2!$C28,MC_Random_N2!$B28*(1-Y$1),0) -> 0.3494518 | Z28: =IF(Z$1*MC_Random_N2!$B28>=0.5*MC_Random_N2!$C28,MC_Random_N2!$B28*(1-Z$1),0) -> 0.26208885 | AA28: =IF(AA$1*MC_Random_N2!$B28>=0.5*MC_Random_N2!$C28,MC_Random_N2!$B28*(1-AA$1),0) -> 0.1747259 | ... AC28: =IF(AC$1*MC_Random_N2!$B28>=0.5*MC_Random_N2!$C28,MC_Random_N2!$B28*(1-AC$1),0) -> 0 | AP28: 27 | AQ28: =MAX(AQ$1*MC_Random_N2!$B28,0.5*MC_Random_N2!$C28) -> 0.46671958 | AR28: =MAX(AR$1*MC_Random_N2!$B28,0.5*MC_Random_N2!$C28) -> 0.46671958 | AS28: =MAX(AS$1*MC_Random_N2!$B28,0.5*MC_Random_N2!$C28) -> 0.46671958 | AT28: =MAX(AT$1*MC_Random_N2!$B28,0.5*MC_Random_N2!$C28) -> 0.46671958 | AU28: =MAX(AU$1*MC_Random_N2!$B28,0.5*MC_Random_N2!$C28) -> 0.46671958 | AV28: =MAX(AV$1*MC_Random_N2!$B28,0.5*MC_Random_N2!$C28) -> 0.52417769 | AW28: =MAX(AW$1*MC_Random_N2!$B28,0.5*MC_Random_N2!$C28) -> 0.61154064 | AX28: =MAX(AX$1*MC_Random_N2!$B28,0.5*MC_Random_N2!$C28) -> 0.69890359 | ... AZ28: =MAX(AZ$1*MC_Random_N2!$B28,0.5*MC_Random_N2!$C28) -> 0.87362949 | CG28: 27 | CH28: =IF(CH$1*MC_Random_N5!$B28>=0.8*MAX(MC_Random_N5!$C28:$F28),MC_Random_N5!$B28*(1-CH$1),0) -> 0 | CI28: =IF(CI$1*MC_Random_N5!$B28>=0.8*MAX(MC_Random_N5!$C28:$F28),MC_Random_N5!$B28*(1-CI$1),0) -> 0 | CJ28: =IF(CJ$1*MC_Random_N5!$B28>=0.8*MAX(MC_Random_N5!$C28:$F28),MC_Random_N5!$B28*(1-CJ$1),0) -> 0 | CK28: =IF(CK$1*MC_Random_N5!$B28>=0.8*MAX(MC_Random_N5!$C28:$F28),MC_Random_N5!$B28*(1-CK$1),0) -> 0 | CL28: =IF(CL$1*MC_Random_N5!$B28>=0.8*MAX(MC_Random_N5!$C28:$F28),MC_Random_N5!$B28*(1-CL$1),0) -> 0 | CM28: =IF(CM$1*MC_Random_N5!$B28>=0.8*MAX(MC_Random_N5!$C28:$F28),MC_Random_N5!$B28*(1-CM$1),0) -> 0 | CN28: =IF(CN$1*MC_Random_N5!$B28>=0.8*MAX(MC_Random_N5!$C28:$F28),MC_Random_N5!$B28*(1-CN$1),0) -> 0 | CO28: =IF(CO$1*MC_Random_N5!$B28>=0.8*MAX(MC_Random_N5!$C28:$F28),MC_Random_N5!$B28*(1-CO$1),0) -> 0 | ... CQ28: =IF(CQ$1*MC_Random_N5!$B28>=0.8*MAX(MC_Random_N5!$C28:$F28),MC_Random_N5!$B28*(1-CQ$1),0) -> 0 | DD28: 27 | DE28: =MAX(DE$1*MC_Random_N5!$B28,0.8*MAX(MC_Random_N5!$C28:$F28)) -> 0.54782997 | DF28: =MAX(DF$1*MC_Random_N5!$B28,0.8*MAX(MC_Random_N5!$C28:$F28)) -> 0.54782997 | DG28: =MAX(DG$1*MC_Random_N5!$B28,0.8*MAX(MC_Random_N5!$C28:$F28)) -> 0.54782997 | DH28: =MAX(DH$1*MC_Random_N5!$B28,0.8*MAX(MC_Random_N5!$C28:$F28)) -> 0.54782997 | DI28: =MAX(DI$1*MC_Random_N5!$B28,0.8*MAX(MC_Random_N5!$C28:$F28)) -> 0.54782997 | DJ28: =MAX(DJ$1*MC_Random_N5!$B28,0.8*MAX(MC_Random_N5!$C28:$F28)) -> 0.54782997 | DK28: =MAX(DK$1*MC_Random_N5!$B28,0.8*MAX(MC_Random_N5!$C28:$F28)) -> 0.54782997 | DL28: =MAX(DL$1*MC_Random_N5!$B28,0.8*MAX(MC_Random_N5!$C28:$F28)) -> 0.54782997 | ... DN28: =MAX(DN$1*MC_Random_N5!$B28,0.8*MAX(MC_Random_N5!$C28:$F28)) -> 0.65787533 | EJ28: 27 | EK28: =IF(EK$1*MC_Random_N10!$B28>=0.9*MAX(MC_Random_N10!$C28:$K28),MC_Random_N10!$B28*(1-EK$1),0) -> 0 | EL28: =IF(EL$1*MC_Random_N10!$B28>=0.9*MAX(MC_Random_N10!$C28:$K28),MC_Random_N10!$B28*(1-EL$1),0) -> 0 | EM28: =IF(EM$1*MC_Random_N10!$B28>=0.9*MAX(MC_Random_N10!$C28:$K28),MC_Random_N10!$B28*(1-EM$1),0) -> 0 | EN28: =IF(EN$1*MC_Random_N10!$B28>=0.9*MAX(MC_Random_N10!$C28:$K28),MC_Random_N10!$B28*(1-EN$1),0) -> 0 | EO28: =IF(EO$1*MC_Random_N10!$B28>=0.9*MAX(MC_Random_N10!$C28:$K28),MC_Random_N10!$B28*(1-EO$1),0) -> 0 | EP28: =IF(EP$1*MC_Random_N10!$B28>=0.9*MAX(MC_Random_N10!$C28:$K28),MC_Random_N10!$B28*(1-EP$1),0) -> 0 | EQ28: =IF(EQ$1*MC_Random_N10!$B28>=0.9*MAX(MC_Random_N10!$C28:$K28),MC_Random_N10!$B28*(1-EQ$1),0) -> 0 | ER28: =IF(ER$1*MC_Random_N10!$B28>=0.9*MAX(MC_Random_N10!$C28:$K28),MC_Random_N10!$B28*(1-ER$1),0) -> 0 | ... ET28: =IF(ET$1*MC_Random_N10!$B28>=0.9*MAX(MC_Random_N10!$C28:$K28),MC_Random_N10!$B28*(1-ET$1),0) -> 0 | FF28: 27 | FG28: =MAX(FG$1*MC_Random_N10!$B28,0.9*MAX(MC_Random_N10!$C28:$K28)) -> 0.85977437 | FH28: =MAX(FH$1*MC_Random_N10!$B28,0.9*MAX(MC_Random_N10!$C28:$K28)) -> 0.85977437 | FI28: =MAX(FI$1*MC_Random_N10!$B28,0.9*MAX(MC_Random_N10!$C28:$K28)) -> 0.85977437 | FJ28: =MAX(FJ$1*MC_Random_N10!$B28,0.9*MAX(MC_Random_N10!$C28:$K28)) -> 0.85977437 | FK28: =MAX(FK$1*MC_Random_N10!$B28,0.9*MAX(MC_Random_N10!$C28:$K28)) -> 0.85977437 | FL28: =MAX(FL$1*MC_Random_N10!$B28,0.9*MAX(MC_Random_N10!$C28:$K28)) -> 0.85977437 | FM28: =MAX(FM$1*MC_Random_N10!$B28,0.9*MAX(MC_Random_N10!$C28:$K28)) -> 0.85977437 | FN28: =MAX(FN$1*MC_Random_N10!$B28,0.9*MAX(MC_Random_N10!$C28:$K28)) -> 0.85977437 | ... FP28: =MAX(FP$1*MC_Random_N10!$B28,0.9*MAX(MC_Random_N10!$C28:$K28)) -> 0.85977437
... S1001: 1000 | T1001: =IF(T$1*MC_Random_N2!$B1001>=0.5*MC_Random_N2!$C1001,MC_Random_N2!$B1001*(1-T$1),0) -> 0 | U1001: =IF(U$1*MC_Random_N2!$B1001>=0.5*MC_Random_N2!$C1001,MC_Random_N2!$B1001*(1-U$1),0) -> 0 | V1001: =IF(V$1*MC_Random_N2!$B1001>=0.5*MC_Random_N2!$C1001,MC_Random_N2!$B1001*(1-V$1),0) -> 0 | W1001: =IF(W$1*MC_Random_N2!$B1001>=0.5*MC_Random_N2!$C1001,MC_Random_N2!$B1001*(1-W$1),0) -> 0 | X1001: =IF(X$1*MC_Random_N2!$B1001>=0.5*MC_Random_N2!$C1001,MC_Random_N2!$B1001*(1-X$1),0) -> 0.20669805 | Y1001: =IF(Y$1*MC_Random_N2!$B1001>=0.5*MC_Random_N2!$C1001,MC_Random_N2!$B1001*(1-Y$1),0) -> 0.16535844 | Z1001: =IF(Z$1*MC_Random_N2!$B1001>=0.5*MC_Random_N2!$C1001,MC_Random_N2!$B1001*(1-Z$1),0) -> 0.12401883 | AA1001: =IF(AA$1*MC_Random_N2!$B1001>=0.5*MC_Random_N2!$C1001,MC_Random_N2!$B1001*(1-AA$1),0) -> 0.082679221 | ... AC1001: =IF(AC$1*MC_Random_N2!$B1001>=0.5*MC_Random_N2!$C1001,MC_Random_N2!$B1001*(1-AC$1),0) -> 0 | AP1001: 1000 | AQ1001: =MAX(AQ$1*MC_Random_N2!$B1001,0.5*MC_Random_N2!$C1001) -> 0.17284521 | AR1001: =MAX(AR$1*MC_Random_N2!$B1001,0.5*MC_Random_N2!$C1001) -> 0.17284521 | AS1001: =MAX(AS$1*MC_Random_N2!$B1001,0.5*MC_Random_N2!$C1001) -> 0.17284521 | AT1001: =MAX(AT$1*MC_Random_N2!$B1001,0.5*MC_Random_N2!$C1001) -> 0.17284521 | AU1001: =MAX(AU$1*MC_Random_N2!$B1001,0.5*MC_Random_N2!$C1001) -> 0.20669805 | AV1001: =MAX(AV$1*MC_Random_N2!$B1001,0.5*MC_Random_N2!$C1001) -> 0.24803766 | AW1001: =MAX(AW$1*MC_Random_N2!$B1001,0.5*MC_Random_N2!$C1001) -> 0.28937727 | AX1001: =MAX(AX$1*MC_Random_N2!$B1001,0.5*MC_Random_N2!$C1001) -> 0.33071688 | ... AZ1001: =MAX(AZ$1*MC_Random_N2!$B1001,0.5*MC_Random_N2!$C1001) -> 0.4133961 | CG1001: 1000 | CH1001: =IF(CH$1*MC_Random_N5!$B1001>=0.8*MAX(MC_Random_N5!$C1001:$F1001),MC_Random_N5!$B1001*(1-CH$1),0) -> 0 | CI1001: =IF(CI$1*MC_Random_N5!$B1001>=0.8*MAX(MC_Random_N5!$C1001:$F1001),MC_Random_N5!$B1001*(1-CI$1),0) -> 0 | CJ1001: =IF(CJ$1*MC_Random_N5!$B1001>=0.8*MAX(MC_Random_N5!$C1001:$F1001),MC_Random_N5!$B1001*(1-CJ$1),0) -> 0 | CK1001: =IF(CK$1*MC_Random_N5!$B1001>=0.8*MAX(MC_Random_N5!$C1001:$F1001),MC_Random_N5!$B1001*(1-CK$1),0) -> 0 | CL1001: =IF(CL$1*MC_Random_N5!$B1001>=0.8*MAX(MC_Random_N5!$C1001:$F1001),MC_Random_N5!$B1001*(1-CL$1),0) -> 0 | CM1001: =IF(CM$1*MC_Random_N5!$B1001>=0.8*MAX(MC_Random_N5!$C1001:$F1001),MC_Random_N5!$B1001*(1-CM$1),0) -> 0 | CN1001: =IF(CN$1*MC_Random_N5!$B1001>=0.8*MAX(MC_Random_N5!$C1001:$F1001),MC_Random_N5!$B1001*(1-CN$1),0) -> 0 | CO1001: =IF(CO$1*MC_Random_N5!$B1001>=0.8*MAX(MC_Random_N5!$C1001:$F1001),MC_Random_N5!$B1001*(1-CO$1),0) -> 0 | ... CQ1001: =IF(CQ$1*MC_Random_N5!$B1001>=0.8*MAX(MC_Random_N5!$C1001:$F1001),MC_Random_N5!$B1001*(1-CQ$1),0) -> 0 | DD1001: 1000 | DE1001: =MAX(DE$1*MC_Random_N5!$B1001,0.8*MAX(MC_Random_N5!$C1001:$F1001)) -> 0.62390674 | DF1001: =MAX(DF$1*MC_Random_N5!$B1001,0.8*MAX(MC_Random_N5!$C1001:$F1001)) -> 0.62390674 | DG1001: =MAX(DG$1*MC_Random_N5!$B1001,0.8*MAX(MC_Random_N5!$C1001:$F1001)) -> 0.62390674 | DH1001: =MAX(DH$1*MC_Random_N5!$B1001,0.8*MAX(MC_Random_N5!$C1001:$F1001)) -> 0.62390674 | DI1001: =MAX(DI$1*MC_Random_N5!$B1001,0.8*MAX(MC_Random_N5!$C1001:$F1001)) -> 0.62390674 | DJ1001: =MAX(DJ$1*MC_Random_N5!$B1001,0.8*MAX(MC_Random_N5!$C1001:$F1001)) -> 0.62390674 | DK1001: =MAX(DK$1*MC_Random_N5!$B1001,0.8*MAX(MC_Random_N5!$C1001:$F1001)) -> 0.62390674 | DL1001: =MAX(DL$1*MC_Random_N5!$B1001,0.8*MAX(MC_Random_N5!$C1001:$F1001)) -> 0.62390674 | ... DN1001: =MAX(DN$1*MC_Random_N5!$B1001,0.8*MAX(MC_Random_N5!$C1001:$F1001)) -> 0.62390674 | EJ1001: 1000 | EK1001: =IF(EK$1*MC_Random_N10!$B1001>=0.9*MAX(MC_Random_N10!$C1001:$K1001),MC_Random_N10!$B1001*(1-EK$1),0) -> 0 | EL1001: =IF(EL$1*MC_Random_N10!$B1001>=0.9*MAX(MC_Random_N10!$C1001:$K1001),MC_Random_N10!$B1001*(1-EL$1),0) -> 0 | EM1001: =IF(EM$1*MC_Random_N10!$B1001>=0.9*MAX(MC_Random_N10!$C1001:$K1001),MC_Random_N10!$B1001*(1-EM$1),0) -> 0 | EN1001: =IF(EN$1*MC_Random_N10!$B1001>=0.9*MAX(MC_Random_N10!$C1001:$K1001),MC_Random_N10!$B1001*(1-EN$1),0) -> 0 | EO1001: =IF(EO$1*MC_Random_N10!$B1001>=0.9*MAX(MC_Random_N10!$C1001:$K1001),MC_Random_N10!$B1001*(1-EO$1),0) -> 0 | EP1001: =IF(EP$1*MC_Random_N10!$B1001>=0.9*MAX(MC_Random_N10!$C1001:$K1001),MC_Random_N10!$B1001*(1-EP$1),0) -> 0 | EQ1001: =IF(EQ$1*MC_Random_N10!$B1001>=0.9*MAX(MC_Random_N10!$C1001:$K1001),MC_Random_N10!$B1001*(1-EQ$1),0) -> 0 | ER1001: =IF(ER$1*MC_Random_N10!$B1001>=0.9*MAX(MC_Random_N10!$C1001:$K1001),MC_Random_N10!$B1001*(1-ER$1),0) -> 0 | ... ET1001: =IF(ET$1*MC_Random_N10!$B1001>=0.9*MAX(MC_Random_N10!$C1001:$K1001),MC_Random_N10!$B1001*(1-ET$1),0) -> 0 | FF1001: 1000 | FG1001: =MAX(FG$1*MC_Random_N10!$B1001,0.9*MAX(MC_Random_N10!$C1001:$K1001)) -> 0.84218802 | FH1001: =MAX(FH$1*MC_Random_N10!$B1001,0.9*MAX(MC_Random_N10!$C1001:$K1001)) -> 0.84218802 | FI1001: =MAX(FI$1*MC_Random_N10!$B1001,0.9*MAX(MC_Random_N10!$C1001:$K1001)) -> 0.84218802 | FJ1001: =MAX(FJ$1*MC_Random_N10!$B1001,0.9*MAX(MC_Random_N10!$C1001:$K1001)) -> 0.84218802 | FK1001: =MAX(FK$1*MC_Random_N10!$B1001,0.9*MAX(MC_Random_N10!$C1001:$K1001)) -> 0.84218802 | FL1001: =MAX(FL$1*MC_Random_N10!$B1001,0.9*MAX(MC_Random_N10!$C1001:$K1001)) -> 0.84218802 | FM1001: =MAX(FM$1*MC_Random_N10!$B1001,0.9*MAX(MC_Random_N10!$C1001:$K1001)) -> 0.84218802 | FN1001: =MAX(FN$1*MC_Random_N10!$B1001,0.9*MAX(MC_Random_N10!$C1001:$K1001)) -> 0.84218802 | ... FP1001: =MAX(FP$1*MC_Random_N10!$B1001,0.9*MAX(MC_Random_N10!$C1001:$K1001)) -> 0.84218802
B1006: RESEARCH GUIDE | SAMPLE PATH AND SIMULATION OUTPUTS
B1008: SAMPLE PATH
B1009: Each bidder row records private valuation, submitted bid, winning indicator, payment and realized net surplus. The seller revenue output is the largest bid (first-price) or second-highest bid (second-price).
B1010: MONTE CARLO GRID
B1011: Each 1,000 x 10 grid contains 1,000 auction outcomes under each of ten bidder-1 strategies x=0.1 to 1.0. Rows are auction replications; columns are strategy alternatives.
B1012: STAT / AVERAGE
B1013: The ten adjacent averages estimate expected bidder-1 surplus ES_N(x) or expected seller revenue ER_N(x). They are mean simulated outcomes, not single-auction payoffs.
B1014: RESEARCH QUESTIONS
B1015: First-price: (a) N=2 optimal x and seller revenue, (b) buyer-versus-seller incentives, (c) N=5 and 10, (d) general N. Second-price: (a) N=2, (b) N=5 and 10, (c) general N, (d) revenue-equivalence comparison.
B1016: FULL EXPLANATIONS
B1017: See 08_CALCULATION_GUIDE and 01_RESEARCH_MODEL. Existing formulas, simulation grids and original charts are preserved.
B1018: FROZEN INPUTS
B1019: MC_Random_N2, MC_Random_N5 and MC_Random_N10 store fixed valuation vectors; the Monte Carlo outcome cells retain their original formulas.

Sheet 2_Second_Price
A1: INPUT | B1: N_a2 | C1: 10 | E1: Qa) | F1: SAMPLE PATH | G1: ID | H1: vi | I1: bi | J1: wi | K1: payi | L1: Si | N1: STAT | O1: S1(x) | P1: =L2 -> 0 | R1: DATA TABLE | S1: =P1 -> 0 | T1: 0.1 | U1: 0.2 | V1: 0.3 | W1: 0.4 | X1: 0.5 | Y1: 0.6 | Z1: 0.7 | AA1: 0.8 | AB1: 0.9 | AC1: 1 | AE1: 0.1 | AF1: ES(0.1) | AG1: =AVERAGE(T2:T1001) -> 0.035386972 | AN1: DATA TABLE | AO1: =P2 -> 0.061019363 | AP1: 0.1 | AQ1: 0.2 | AR1: 0.3 | AS1: 0.4 | AT1: 0.5 | AU1: 0.6 | AV1: 0.7 | AW1: 0.8 | AX1: 0.9 | AY1: 1 | BA1: 0.1 | BB1: ER(0.1) | BC1: =AVERAGE(AP2:AP1001) -> 0.048416209 | BF1: Qb) | BG1: N=5 | BH1: ID | BI1: vi | BJ1: bi | BK1: wi | BL1: payi | BM1: Si | BO1: STAT | BP1: S1(x) | BQ1: =BM2 -> 0 | BS1: DATA TABLE | BT1: =BQ1 -> 0 | BU1: 0.1 | BV1: 0.2 | BW1: 0.3 | BX1: 0.4 | BY1: 0.5 | BZ1: 0.6 | CA1: 0.7 | CB1: 0.8 | CC1: 0.9 | CD1: 1 | CF1: 0.1 | CG1: ES(0.1) | CH1: =AVERAGE(BU2:BU1001) -> 0 | CO1: DATA TABLE | CP1: =BQ2 -> 0.86757597 | CQ1: 0.1 | CR1: 0.2 | CS1: 0.3 | CT1: 0.4 | CU1: 0.5 | CV1: 0.6 | CW1: 0.7 | CX1: 0.8 | CY1: 0.9 | CZ1: 1 | DB1: 0.1 | DC1: ER(0.1) | DD1: =AVERAGE(CQ2:CQ1001) -> 0.60219858 | DG1: N=10 | DH1: SAMPLE PATH | DI1: ID | DJ1: vi | DK1: bi | DL1: wi | DM1: payi | DN1: Si | DP1: STAT | DQ1: S1(x) | DR1: =DN2 -> 0 | DT1: DATA TABLE | DU1: =DR1 -> 0 | DV1: 0.1 | DW1: 0.2 | DX1: 0.3 | DY1: 0.4 | DZ1: 0.5 | EA1: 0.6 | EB1: 0.7 | EC1: 0.8 | ED1: 0.9 | EE1: 1 | EG1: 0.1 | EH1: ES(0.1) | EI1: =AVERAGE(DV2:DV1001) -> 0 | EP1: DATA TABLE | EQ1: =DR2 -> 0.72640431 | ER1: 0.1 | ES1: 0.2 | ET1: 0.3 | EU1: 0.4 | EV1: 0.5 | EW1: 0.6 | EX1: 0.7 | EY1: 0.8 | EZ1: 0.9 | FA1: 1 | FC1: 0.1 | FD1: ER(0.1) | FE1: =AVERAGE(ER2:ER1001) -> 0.79808312 | FI1: Qc) | FJ1: In a second-price sealed-bid auction with independent private values, truthful bidding (x*=1.0) is a weakly dominant strategy. The N=2 simulation produced a sample maximum at x=0.8, which may reflect Monte Carlo sampling variation rather than a different theoretical optimum. | FS1: Qe) | FT1: n | FU1: First-price R_N(x*) | FV1: Second-price R_N(x*) | FW1: gain(Second − First)
B2: xi_2 | C2: 0.1 | G2: 1 | H2: =RAND() -> 0.61019363 | I2: =xi_2*H2 -> 0.061019363 | J2: =IF(I2=MAX(I2:I3),1,0) -> 0 | K2: =J2*LARGE(I2:I3,2) -> 0 | L2: =J2*(H2-K2) -> 0 | O2: R2(x) | P2: =LARGE(I2:I3,2) -> 0.061019363 | S2: {=_xlfn.SEQUENCE(1000)} -> 1 | T2: =IF(T$1*MC_Random_N2!$B2>=MC_Random_N2!$C2,MC_Random_N2!$B2-MC_Random_N2!$C2,0) -> 0 | U2: =IF(U$1*MC_Random_N2!$B2>=MC_Random_N2!$C2,MC_Random_N2!$B2-MC_Random_N2!$C2,0) -> 0 | V2: =IF(V$1*MC_Random_N2!$B2>=MC_Random_N2!$C2,MC_Random_N2!$B2-MC_Random_N2!$C2,0) -> 0 | W2: =IF(W$1*MC_Random_N2!$B2>=MC_Random_N2!$C2,MC_Random_N2!$B2-MC_Random_N2!$C2,0) -> 0 | X2: =IF(X$1*MC_Random_N2!$B2>=MC_Random_N2!$C2,MC_Random_N2!$B2-MC_Random_N2!$C2,0) -> 0 | Y2: =IF(Y$1*MC_Random_N2!$B2>=MC_Random_N2!$C2,MC_Random_N2!$B2-MC_Random_N2!$C2,0) -> 0 | Z2: =IF(Z$1*MC_Random_N2!$B2>=MC_Random_N2!$C2,MC_Random_N2!$B2-MC_Random_N2!$C2,0) -> 0 | AA2: =IF(AA$1*MC_Random_N2!$B2>=MC_Random_N2!$C2,MC_Random_N2!$B2-MC_Random_N2!$C2,0) -> 0 | ... AC2: =IF(AC$1*MC_Random_N2!$B2>=MC_Random_N2!$C2,MC_Random_N2!$B2-MC_Random_N2!$C2,0) -> 0 | AE2: 0.2 | AF2: ES(0.2) | AG2: =AVERAGE(U2:U1001) -> 0.060613734 | AO2: {=_xlfn.SEQUENCE(1000)} -> 1 | AP2: =IF(AP$1*MC_Random_N2!$B2>=MC_Random_N2!$C2,MC_Random_N2!$C2,AP$1*MC_Random_N2!$B2) -> 0.049211421 | AQ2: =IF(AQ$1*MC_Random_N2!$B2>=MC_Random_N2!$C2,MC_Random_N2!$C2,AQ$1*MC_Random_N2!$B2) -> 0.098422842 | AR2: =IF(AR$1*MC_Random_N2!$B2>=MC_Random_N2!$C2,MC_Random_N2!$C2,AR$1*MC_Random_N2!$B2) -> 0.14763426 | AS2: =IF(AS$1*MC_Random_N2!$B2>=MC_Random_N2!$C2,MC_Random_N2!$C2,AS$1*MC_Random_N2!$B2) -> 0.19684568 | AT2: =IF(AT$1*MC_Random_N2!$B2>=MC_Random_N2!$C2,MC_Random_N2!$C2,AT$1*MC_Random_N2!$B2) -> 0.24605711 | AU2: =IF(AU$1*MC_Random_N2!$B2>=MC_Random_N2!$C2,MC_Random_N2!$C2,AU$1*MC_Random_N2!$B2) -> 0.29526853 | AV2: =IF(AV$1*MC_Random_N2!$B2>=MC_Random_N2!$C2,MC_Random_N2!$C2,AV$1*MC_Random_N2!$B2) -> 0.34447995 | AW2: =IF(AW$1*MC_Random_N2!$B2>=MC_Random_N2!$C2,MC_Random_N2!$C2,AW$1*MC_Random_N2!$B2) -> 0.39369137 | ... AY2: =IF(AY$1*MC_Random_N2!$B2>=MC_Random_N2!$C2,MC_Random_N2!$C2,AY$1*MC_Random_N2!$B2) -> 0.49211421 | BA2: 0.2 | BB2: ER(0.2) | BC2: =AVERAGE(AQ2:AQ1001) -> 0.093323496 | BH2: 1 | BI2: =RAND() -> 0.67546263 | BJ2: =xi_2*BI2 -> 0.067546263 | BK2: =IF(BJ2=MAX($BJ$2:$BJ$6),1,0) -> 0 | BL2: =BK2*LARGE($BJ$2:$BJ$6,2) -> 0 | BM2: =BK2*(BI2-BL2) -> 0 | BP2: R2(x) | BQ2: =LARGE(BJ2:BJ6,2) -> 0.86757597 | BT2: {=_xlfn.SEQUENCE(1000)} -> 1 | BU2: =IF(BU$1*MC_Random_N5!$B2>=MAX(MC_Random_N5!$C2:$F2),MC_Random_N5!$B2-MAX(MC_Random_N5!$C2:$F2),0) -> 0 | BV2: =IF(BV$1*MC_Random_N5!$B2>=MAX(MC_Random_N5!$C2:$F2),MC_Random_N5!$B2-MAX(MC_Random_N5!$C2:$F2),0) -> 0 | BW2: =IF(BW$1*MC_Random_N5!$B2>=MAX(MC_Random_N5!$C2:$F2),MC_Random_N5!$B2-MAX(MC_Random_N5!$C2:$F2),0) -> 0 | BX2: =IF(BX$1*MC_Random_N5!$B2>=MAX(MC_Random_N5!$C2:$F2),MC_Random_N5!$B2-MAX(MC_Random_N5!$C2:$F2),0) -> 0 | BY2: =IF(BY$1*MC_Random_N5!$B2>=MAX(MC_Random_N5!$C2:$F2),MC_Random_N5!$B2-MAX(MC_Random_N5!$C2:$F2),0) -> 0 | BZ2: =IF(BZ$1*MC_Random_N5!$B2>=MAX(MC_Random_N5!$C2:$F2),MC_Random_N5!$B2-MAX(MC_Random_N5!$C2:$F2),0) -> 0 | CA2: =IF(CA$1*MC_Random_N5!$B2>=MAX(MC_Random_N5!$C2:$F2),MC_Random_N5!$B2-MAX(MC_Random_N5!$C2:$F2),0) -> 0 | CB2: =IF(CB$1*MC_Random_N5!$B2>=MAX(MC_Random_N5!$C2:$F2),MC_Random_N5!$B2-MAX(MC_Random_N5!$C2:$F2),0) -> 0 | ... CD2: =IF(CD$1*MC_Random_N5!$B2>=MAX(MC_Random_N5!$C2:$F2),MC_Random_N5!$B2-MAX(MC_Random_N5!$C2:$F2),0) -> 0 | CF2: 0.2 | CG2: ES(0.2) | CH2: =AVERAGE(BV2:BV1001) -> 0 | CP2: {=_xlfn.SEQUENCE(1000)} -> 1 | CQ2: =LARGE(CHOOSE({1,2,3,4,5},CQ$1*MC_Random_N5!$B2,MC_Random_N5!$C2,MC_Random_N5!$D2,MC_Random_N5!$E2,MC_Random_N5!$F2),2) -> 0.68332533 | CR2: =LARGE(CHOOSE({1,2,3,4,5},CR$1*MC_Random_N5!$B2,MC_Random_N5!$C2,MC_Random_N5!$D2,MC_Random_N5!$E2,MC_Random_N5!$F2),2) -> 0.68332533 | CS2: =LARGE(CHOOSE({1,2,3,4,5},CS$1*MC_Random_N5!$B2,MC_Random_N5!$C2,MC_Random_N5!$D2,MC_Random_N5!$E2,MC_Random_N5!$F2),2) -> 0.68332533 | CT2: =LARGE(CHOOSE({1,2,3,4,5},CT$1*MC_Random_N5!$B2,MC_Random_N5!$C2,MC_Random_N5!$D2,MC_Random_N5!$E2,MC_Random_N5!$F2),2) -> 0.68332533 | CU2: =LARGE(CHOOSE({1,2,3,4,5},CU$1*MC_Random_N5!$B2,MC_Random_N5!$C2,MC_Random_N5!$D2,MC_Random_N5!$E2,MC_Random_N5!$F2),2) -> 0.68332533 | CV2: =LARGE(CHOOSE({1,2,3,4,5},CV$1*MC_Random_N5!$B2,MC_Random_N5!$C2,MC_Random_N5!$D2,MC_Random_N5!$E2,MC_Random_N5!$F2),2) -> 0.68332533 | CW2: =LARGE(CHOOSE({1,2,3,4,5},CW$1*MC_Random_N5!$B2,MC_Random_N5!$C2,MC_Random_N5!$D2,MC_Random_N5!$E2,MC_Random_N5!$F2),2) -> 0.68332533 | CX2: =LARGE(CHOOSE({1,2,3,4,5},CX$1*MC_Random_N5!$B2,MC_Random_N5!$C2,MC_Random_N5!$D2,MC_Random_N5!$E2,MC_Random_N5!$F2),2) -> 0.68332533 | ... CZ2: =LARGE(CHOOSE({1,2,3,4,5},CZ$1*MC_Random_N5!$B2,MC_Random_N5!$C2,MC_Random_N5!$D2,MC_Random_N5!$E2,MC_Random_N5!$F2),2) -> 0.68332533 | DB2: 0.2 | DC2: ER(0.2) | DD2: =AVERAGE(CR2:CR1001) -> 0.60252339 | DI2: {=_xlfn.SEQUENCE(10)} -> 1 | DJ2: =RAND() -> 0.72927204 | DK2: =xi_2*DJ2 -> 0.072927204 | DL2: =IF(DK2=MAX($DK$2:$DK$11),1,0) -> 0 | DM2: =DL2*LARGE($DK$2:$DK$11,2) -> 0 | DN2: =DL2*(DJ2-DM2) -> 0 | DQ2: R2(x) | DR2: =LARGE(DK2:DK11,2) -> 0.72640431 | DU2: {=_xlfn.SEQUENCE(1000)} -> 1 | DV2: =IF(DV$1*MC_Random_N10!$B2>=MAX(MC_Random_N10!$C2:$K2),MC_Random_N10!$B2-MAX(MC_Random_N10!$C2:$K2),0) -> 0 | DW2: =IF(DW$1*MC_Random_N10!$B2>=MAX(MC_Random_N10!$C2:$K2),MC_Random_N10!$B2-MAX(MC_Random_N10!$C2:$K2),0) -> 0 | DX2: =IF(DX$1*MC_Random_N10!$B2>=MAX(MC_Random_N10!$C2:$K2),MC_Random_N10!$B2-MAX(MC_Random_N10!$C2:$K2),0) -> 0 | DY2: =IF(DY$1*MC_Random_N10!$B2>=MAX(MC_Random_N10!$C2:$K2),MC_Random_N10!$B2-MAX(MC_Random_N10!$C2:$K2),0) -> 0 | DZ2: =IF(DZ$1*MC_Random_N10!$B2>=MAX(MC_Random_N10!$C2:$K2),MC_Random_N10!$B2-MAX(MC_Random_N10!$C2:$K2),0) -> 0 | EA2: =IF(EA$1*MC_Random_N10!$B2>=MAX(MC_Random_N10!$C2:$K2),MC_Random_N10!$B2-MAX(MC_Random_N10!$C2:$K2),0) -> 0 | EB2: =IF(EB$1*MC_Random_N10!$B2>=MAX(MC_Random_N10!$C2:$K2),MC_Random_N10!$B2-MAX(MC_Random_N10!$C2:$K2),0) -> 0 | EC2: =IF(EC$1*MC_Random_N10!$B2>=MAX(MC_Random_N10!$C2:$K2),MC_Random_N10!$B2-MAX(MC_Random_N10!$C2:$K2),0) -> 0 | ... EE2: =IF(EE$1*MC_Random_N10!$B2>=MAX(MC_Random_N10!$C2:$K2),MC_Random_N10!$B2-MAX(MC_Random_N10!$C2:$K2),0) -> 0 | EG2: 0.2 | EH2: ES(0.2) | EI2: =AVERAGE(DW2:DW1001) -> 0 | EQ2: {=_xlfn.SEQUENCE(1000)} -> 1 | ER2: =MAX(LARGE(MC_Random_N10!$C2:$K2,2),MIN(ER$1*MC_Random_N10!$B2,MAX(MC_Random_N10!$C2:$K2))) -> 0.83875427 | ES2: =MAX(LARGE(MC_Random_N10!$C2:$K2,2),MIN(ES$1*MC_Random_N10!$B2,MAX(MC_Random_N10!$C2:$K2))) -> 0.83875427 | ET2: =MAX(LARGE(MC_Random_N10!$C2:$K2,2),MIN(ET$1*MC_Random_N10!$B2,MAX(MC_Random_N10!$C2:$K2))) -> 0.83875427 | EU2: =MAX(LARGE(MC_Random_N10!$C2:$K2,2),MIN(EU$1*MC_Random_N10!$B2,MAX(MC_Random_N10!$C2:$K2))) -> 0.83875427 | EV2: =MAX(LARGE(MC_Random_N10!$C2:$K2,2),MIN(EV$1*MC_Random_N10!$B2,MAX(MC_Random_N10!$C2:$K2))) -> 0.83875427 | EW2: =MAX(LARGE(MC_Random_N10!$C2:$K2,2),MIN(EW$1*MC_Random_N10!$B2,MAX(MC_Random_N10!$C2:$K2))) -> 0.83875427 | EX2: =MAX(LARGE(MC_Random_N10!$C2:$K2,2),MIN(EX$1*MC_Random_N10!$B2,MAX(MC_Random_N10!$C2:$K2))) -> 0.83875427 | EY2: =MAX(LARGE(MC_Random_N10!$C2:$K2,2),MIN(EY$1*MC_Random_N10!$B2,MAX(MC_Random_N10!$C2:$K2))) -> 0.83875427 | ... FA2: =MAX(LARGE(MC_Random_N10!$C2:$K2,2),MIN(FA$1*MC_Random_N10!$B2,MAX(MC_Random_N10!$C2:$K2))) -> 0.83875427 | FC2: 0.2 | FD2: ER(0.2) | FE2: =AVERAGE(ES2:ES1001) -> 0.79808312 | FJ2: Under the standard symmetric independent-private-values model with risk-neutral bidders, first-price and second-price auctions have equal expected seller revenue in equilibrium. The simulated revenue comparison should be interpreted in light of Monte Carlo uncertainty and the assumed bidding strategies. | FT2: 2 | FU2: ='1_First_Price'!BD5 -> 0.33432021 | FV2: =BC10 -> 0.33939048 | FW2: =FV2-FU2 -> 0.0050702705
B3: K_2 | C3: 1000 | G3: 2 | H3: =RAND() -> 0.57177886 | I3: =H3 -> 0.57177886 | J3: =IF(I3=MAX(I2:I3),1,0) -> 1 | K3: =J3*LARGE(I2:I3,2) -> 0.061019363 | L3: =J3*(H3-K3) -> 0.5107595 | S3: 2 | T3: =IF(T$1*MC_Random_N2!$B3>=MC_Random_N2!$C3,MC_Random_N2!$B3-MC_Random_N2!$C3,0) -> 0 | U3: =IF(U$1*MC_Random_N2!$B3>=MC_Random_N2!$C3,MC_Random_N2!$B3-MC_Random_N2!$C3,0) -> 0 | V3: =IF(V$1*MC_Random_N2!$B3>=MC_Random_N2!$C3,MC_Random_N2!$B3-MC_Random_N2!$C3,0) -> 0 | W3: =IF(W$1*MC_Random_N2!$B3>=MC_Random_N2!$C3,MC_Random_N2!$B3-MC_Random_N2!$C3,0) -> 0 | X3: =IF(X$1*MC_Random_N2!$B3>=MC_Random_N2!$C3,MC_Random_N2!$B3-MC_Random_N2!$C3,0) -> 0 | Y3: =IF(Y$1*MC_Random_N2!$B3>=MC_Random_N2!$C3,MC_Random_N2!$B3-MC_Random_N2!$C3,0) -> 0 | Z3: =IF(Z$1*MC_Random_N2!$B3>=MC_Random_N2!$C3,MC_Random_N2!$B3-MC_Random_N2!$C3,0) -> 0 | AA3: =IF(AA$1*MC_Random_N2!$B3>=MC_Random_N2!$C3,MC_Random_N2!$B3-MC_Random_N2!$C3,0) -> 0 | ... AC3: =IF(AC$1*MC_Random_N2!$B3>=MC_Random_N2!$C3,MC_Random_N2!$B3-MC_Random_N2!$C3,0) -> 0 | AE3: 0.3 | AF3: ES(0.3) | AG3: =AVERAGE(V2:V1001) -> 0.081304682 | AO3: 2 | AP3: =IF(AP$1*MC_Random_N2!$B3>=MC_Random_N2!$C3,MC_Random_N2!$C3,AP$1*MC_Random_N2!$B3) -> 0.015731968 | AQ3: =IF(AQ$1*MC_Random_N2!$B3>=MC_Random_N2!$C3,MC_Random_N2!$C3,AQ$1*MC_Random_N2!$B3) -> 0.031463937 | AR3: =IF(AR$1*MC_Random_N2!$B3>=MC_Random_N2!$C3,MC_Random_N2!$C3,AR$1*MC_Random_N2!$B3) -> 0.047195905 | AS3: =IF(AS$1*MC_Random_N2!$B3>=MC_Random_N2!$C3,MC_Random_N2!$C3,AS$1*MC_Random_N2!$B3) -> 0.062927873 | AT3: =IF(AT$1*MC_Random_N2!$B3>=MC_Random_N2!$C3,MC_Random_N2!$C3,AT$1*MC_Random_N2!$B3) -> 0.078659841 | AU3: =IF(AU$1*MC_Random_N2!$B3>=MC_Random_N2!$C3,MC_Random_N2!$C3,AU$1*MC_Random_N2!$B3) -> 0.09439181 | AV3: =IF(AV$1*MC_Random_N2!$B3>=MC_Random_N2!$C3,MC_Random_N2!$C3,AV$1*MC_Random_N2!$B3) -> 0.11012378 | AW3: =IF(AW$1*MC_Random_N2!$B3>=MC_Random_N2!$C3,MC_Random_N2!$C3,AW$1*MC_Random_N2!$B3) -> 0.12585575 | ... AY3: =IF(AY$1*MC_Random_N2!$B3>=MC_Random_N2!$C3,MC_Random_N2!$C3,AY$1*MC_Random_N2!$B3) -> 0.15731968 | BA3: 0.3 | BB3: ER(0.3) | BC3: =AVERAGE(AR2:AR1001) -> 0.13572913 | BH3: 2 | BI3: =RAND() -> 0.86757597 | BJ3: =BI3 -> 0.86757597 | BK3: =IF(BJ3=MAX($BJ$2:$BJ$6),1,0) -> 0 | BL3: =BK3*LARGE($BJ$2:$BJ$6,2) -> 0 | BM3: =BK3*(BI3-BL3) -> 0 | BT3: 2 | BU3: =IF(BU$1*MC_Random_N5!$B3>=MAX(MC_Random_N5!$C3:$F3),MC_Random_N5!$B3-MAX(MC_Random_N5!$C3:$F3),0) -> 0 | BV3: =IF(BV$1*MC_Random_N5!$B3>=MAX(MC_Random_N5!$C3:$F3),MC_Random_N5!$B3-MAX(MC_Random_N5!$C3:$F3),0) -> 0 | BW3: =IF(BW$1*MC_Random_N5!$B3>=MAX(MC_Random_N5!$C3:$F3),MC_Random_N5!$B3-MAX(MC_Random_N5!$C3:$F3),0) -> 0 | BX3: =IF(BX$1*MC_Random_N5!$B3>=MAX(MC_Random_N5!$C3:$F3),MC_Random_N5!$B3-MAX(MC_Random_N5!$C3:$F3),0) -> 0 | BY3: =IF(BY$1*MC_Random_N5!$B3>=MAX(MC_Random_N5!$C3:$F3),MC_Random_N5!$B3-MAX(MC_Random_N5!$C3:$F3),0) -> 0 | BZ3: =IF(BZ$1*MC_Random_N5!$B3>=MAX(MC_Random_N5!$C3:$F3),MC_Random_N5!$B3-MAX(MC_Random_N5!$C3:$F3),0) -> 0 | CA3: =IF(CA$1*MC_Random_N5!$B3>=MAX(MC_Random_N5!$C3:$F3),MC_Random_N5!$B3-MAX(MC_Random_N5!$C3:$F3),0) -> 0 | CB3: =IF(CB$1*MC_Random_N5!$B3>=MAX(MC_Random_N5!$C3:$F3),MC_Random_N5!$B3-MAX(MC_Random_N5!$C3:$F3),0) -> 0 | ... CD3: =IF(CD$1*MC_Random_N5!$B3>=MAX(MC_Random_N5!$C3:$F3),MC_Random_N5!$B3-MAX(MC_Random_N5!$C3:$F3),0) -> 0 | CF3: 0.3 | CG3: ES(0.3) | CH3: =AVERAGE(BW2:BW1001) -> 0.0019759686 | CP3: 2 | CQ3: =LARGE(CHOOSE({1,2,3,4,5},CQ$1*MC_Random_N5!$B3,MC_Random_N5!$C3,MC_Random_N5!$D3,MC_Random_N5!$E3,MC_Random_N5!$F3),2) -> 0.75122079 | CR3: =LARGE(CHOOSE({1,2,3,4,5},CR$1*MC_Random_N5!$B3,MC_Random_N5!$C3,MC_Random_N5!$D3,MC_Random_N5!$E3,MC_Random_N5!$F3),2) -> 0.75122079 | CS3: =LARGE(CHOOSE({1,2,3,4,5},CS$1*MC_Random_N5!$B3,MC_Random_N5!$C3,MC_Random_N5!$D3,MC_Random_N5!$E3,MC_Random_N5!$F3),2) -> 0.75122079 | CT3: =LARGE(CHOOSE({1,2,3,4,5},CT$1*MC_Random_N5!$B3,MC_Random_N5!$C3,MC_Random_N5!$D3,MC_Random_N5!$E3,MC_Random_N5!$F3),2) -> 0.75122079 | CU3: =LARGE(CHOOSE({1,2,3,4,5},CU$1*MC_Random_N5!$B3,MC_Random_N5!$C3,MC_Random_N5!$D3,MC_Random_N5!$E3,MC_Random_N5!$F3),2) -> 0.75122079 | CV3: =LARGE(CHOOSE({1,2,3,4,5},CV$1*MC_Random_N5!$B3,MC_Random_N5!$C3,MC_Random_N5!$D3,MC_Random_N5!$E3,MC_Random_N5!$F3),2) -> 0.75122079 | CW3: =LARGE(CHOOSE({1,2,3,4,5},CW$1*MC_Random_N5!$B3,MC_Random_N5!$C3,MC_Random_N5!$D3,MC_Random_N5!$E3,MC_Random_N5!$F3),2) -> 0.75122079 | CX3: =LARGE(CHOOSE({1,2,3,4,5},CX$1*MC_Random_N5!$B3,MC_Random_N5!$C3,MC_Random_N5!$D3,MC_Random_N5!$E3,MC_Random_N5!$F3),2) -> 0.75122079 | ... CZ3: =LARGE(CHOOSE({1,2,3,4,5},CZ$1*MC_Random_N5!$B3,MC_Random_N5!$C3,MC_Random_N5!$D3,MC_Random_N5!$E3,MC_Random_N5!$F3),2) -> 0.75122079 | DB3: 0.3 | DC3: ER(0.3) | DD3: =AVERAGE(CS2:CS1001) -> 0.60348685 | DI3: 2 | DJ3: =RAND() -> 0.088106657 | DK3: =DJ3 -> 0.088106657 | DL3: =IF(DK3=MAX($DK$2:$DK$11),1,0) -> 0 | DM3: =DL3*LARGE($DK$2:$DK$11,2) -> 0 | DN3: =DL3*(DJ3-DM3) -> 0 | DU3: 2 | DV3: =IF(DV$1*MC_Random_N10!$B3>=MAX(MC_Random_N10!$C3:$K3),MC_Random_N10!$B3-MAX(MC_Random_N10!$C3:$K3),0) -> 0 | DW3: =IF(DW$1*MC_Random_N10!$B3>=MAX(MC_Random_N10!$C3:$K3),MC_Random_N10!$B3-MAX(MC_Random_N10!$C3:$K3),0) -> 0 | DX3: =IF(DX$1*MC_Random_N10!$B3>=MAX(MC_Random_N10!$C3:$K3),MC_Random_N10!$B3-MAX(MC_Random_N10!$C3:$K3),0) -> 0 | DY3: =IF(DY$1*MC_Random_N10!$B3>=MAX(MC_Random_N10!$C3:$K3),MC_Random_N10!$B3-MAX(MC_Random_N10!$C3:$K3),0) -> 0 | DZ3: =IF(DZ$1*MC_Random_N10!$B3>=MAX(MC_Random_N10!$C3:$K3),MC_Random_N10!$B3-MAX(MC_Random_N10!$C3:$K3),0) -> 0 | EA3: =IF(EA$1*MC_Random_N10!$B3>=MAX(MC_Random_N10!$C3:$K3),MC_Random_N10!$B3-MAX(MC_Random_N10!$C3:$K3),0) -> 0 | EB3: =IF(EB$1*MC_Random_N10!$B3>=MAX(MC_Random_N10!$C3:$K3),MC_Random_N10!$B3-MAX(MC_Random_N10!$C3:$K3),0) -> 0 | EC3: =IF(EC$1*MC_Random_N10!$B3>=MAX(MC_Random_N10!$C3:$K3),MC_Random_N10!$B3-MAX(MC_Random_N10!$C3:$K3),0) -> 0 | ... EE3: =IF(EE$1*MC_Random_N10!$B3>=MAX(MC_Random_N10!$C3:$K3),MC_Random_N10!$B3-MAX(MC_Random_N10!$C3:$K3),0) -> 0 | EG3: 0.3 | EH3: ES(0.3) | EI3: =AVERAGE(DX2:DX1001) -> 0 | EQ3: 2 | ER3: =MAX(LARGE(MC_Random_N10!$C3:$K3,2),MIN(ER$1*MC_Random_N10!$B3,MAX(MC_Random_N10!$C3:$K3))) -> 0.76954677 | ES3: =MAX(LARGE(MC_Random_N10!$C3:$K3,2),MIN(ES$1*MC_Random_N10!$B3,MAX(MC_Random_N10!$C3:$K3))) -> 0.76954677 | ET3: =MAX(LARGE(MC_Random_N10!$C3:$K3,2),MIN(ET$1*MC_Random_N10!$B3,MAX(MC_Random_N10!$C3:$K3))) -> 0.76954677 | EU3: =MAX(LARGE(MC_Random_N10!$C3:$K3,2),MIN(EU$1*MC_Random_N10!$B3,MAX(MC_Random_N10!$C3:$K3))) -> 0.76954677 | EV3: =MAX(LARGE(MC_Random_N10!$C3:$K3,2),MIN(EV$1*MC_Random_N10!$B3,MAX(MC_Random_N10!$C3:$K3))) -> 0.76954677 | EW3: =MAX(LARGE(MC_Random_N10!$C3:$K3,2),MIN(EW$1*MC_Random_N10!$B3,MAX(MC_Random_N10!$C3:$K3))) -> 0.76954677 | EX3: =MAX(LARGE(MC_Random_N10!$C3:$K3,2),MIN(EX$1*MC_Random_N10!$B3,MAX(MC_Random_N10!$C3:$K3))) -> 0.76954677 | EY3: =MAX(LARGE(MC_Random_N10!$C3:$K3,2),MIN(EY$1*MC_Random_N10!$B3,MAX(MC_Random_N10!$C3:$K3))) -> 0.76954677 | ... FA3: =MAX(LARGE(MC_Random_N10!$C3:$K3,2),MIN(FA$1*MC_Random_N10!$B3,MAX(MC_Random_N10!$C3:$K3))) -> 0.76954677 | FC3: 0.3 | FD3: ER(0.3) | FE3: =AVERAGE(ET2:ET1001) -> 0.79808312 | FT3: 5 | FU3: ='1_First_Price'!DR8 -> 0.66273906 | FV3: =DD10 -> 0.66793117 | FW3: =FV3-FU3 -> 0.0051921109
B4: N_c12 | C4: 5 | S4: 3 | T4: =IF(T$1*MC_Random_N2!$B4>=MC_Random_N2!$C4,MC_Random_N2!$B4-MC_Random_N2!$C4,0) -> 0 | U4: =IF(U$1*MC_Random_N2!$B4>=MC_Random_N2!$C4,MC_Random_N2!$B4-MC_Random_N2!$C4,0) -> 0 | V4: =IF(V$1*MC_Random_N2!$B4>=MC_Random_N2!$C4,MC_Random_N2!$B4-MC_Random_N2!$C4,0) -> 0 | W4: =IF(W$1*MC_Random_N2!$B4>=MC_Random_N2!$C4,MC_Random_N2!$B4-MC_Random_N2!$C4,0) -> 0 | X4: =IF(X$1*MC_Random_N2!$B4>=MC_Random_N2!$C4,MC_Random_N2!$B4-MC_Random_N2!$C4,0) -> 0 | Y4: =IF(Y$1*MC_Random_N2!$B4>=MC_Random_N2!$C4,MC_Random_N2!$B4-MC_Random_N2!$C4,0) -> 0 | Z4: =IF(Z$1*MC_Random_N2!$B4>=MC_Random_N2!$C4,MC_Random_N2!$B4-MC_Random_N2!$C4,0) -> 0 | AA4: =IF(AA$1*MC_Random_N2!$B4>=MC_Random_N2!$C4,MC_Random_N2!$B4-MC_Random_N2!$C4,0) -> 0 | ... AC4: =IF(AC$1*MC_Random_N2!$B4>=MC_Random_N2!$C4,MC_Random_N2!$B4-MC_Random_N2!$C4,0) -> 0 | AE4: 0.4 | AF4: ES(0.4) | AG4: =AVERAGE(W2:W1001) -> 0.10768029 | AO4: 3 | AP4: =IF(AP$1*MC_Random_N2!$B4>=MC_Random_N2!$C4,MC_Random_N2!$C4,AP$1*MC_Random_N2!$B4) -> 0.040907831 | AQ4: =IF(AQ$1*MC_Random_N2!$B4>=MC_Random_N2!$C4,MC_Random_N2!$C4,AQ$1*MC_Random_N2!$B4) -> 0.081815662 | AR4: =IF(AR$1*MC_Random_N2!$B4>=MC_Random_N2!$C4,MC_Random_N2!$C4,AR$1*MC_Random_N2!$B4) -> 0.12272349 | AS4: =IF(AS$1*MC_Random_N2!$B4>=MC_Random_N2!$C4,MC_Random_N2!$C4,AS$1*MC_Random_N2!$B4) -> 0.16363132 | AT4: =IF(AT$1*MC_Random_N2!$B4>=MC_Random_N2!$C4,MC_Random_N2!$C4,AT$1*MC_Random_N2!$B4) -> 0.20453916 | AU4: =IF(AU$1*MC_Random_N2!$B4>=MC_Random_N2!$C4,MC_Random_N2!$C4,AU$1*MC_Random_N2!$B4) -> 0.24544699 | AV4: =IF(AV$1*MC_Random_N2!$B4>=MC_Random_N2!$C4,MC_Random_N2!$C4,AV$1*MC_Random_N2!$B4) -> 0.28635482 | AW4: =IF(AW$1*MC_Random_N2!$B4>=MC_Random_N2!$C4,MC_Random_N2!$C4,AW$1*MC_Random_N2!$B4) -> 0.32726265 | ... AY4: =IF(AY$1*MC_Random_N2!$B4>=MC_Random_N2!$C4,MC_Random_N2!$C4,AY$1*MC_Random_N2!$B4) -> 0.40907831 | BA4: 0.4 | BB4: ER(0.4) | BC4: =AVERAGE(AS2:AS1001) -> 0.17487213 | BH4: 3 | BI4: =RAND() -> 0.99318201 | BJ4: =BI4 -> 0.99318201 | BK4: =IF(BJ4=MAX($BJ$2:$BJ$6),1,0) -> 1 | BL4: =BK4*LARGE($BJ$2:$BJ$6,2) -> 0.86757597 | BM4: =BK4*(BI4-BL4) -> 0.12560604 | BT4: 3 | BU4: =IF(BU$1*MC_Random_N5!$B4>=MAX(MC_Random_N5!$C4:$F4),MC_Random_N5!$B4-MAX(MC_Random_N5!$C4:$F4),0) -> 0 | BV4: =IF(BV$1*MC_Random_N5!$B4>=MAX(MC_Random_N5!$C4:$F4),MC_Random_N5!$B4-MAX(MC_Random_N5!$C4:$F4),0) -> 0 | BW4: =IF(BW$1*MC_Random_N5!$B4>=MAX(MC_Random_N5!$C4:$F4),MC_Random_N5!$B4-MAX(MC_Random_N5!$C4:$F4),0) -> 0 | BX4: =IF(BX$1*MC_Random_N5!$B4>=MAX(MC_Random_N5!$C4:$F4),MC_Random_N5!$B4-MAX(MC_Random_N5!$C4:$F4),0) -> 0 | BY4: =IF(BY$1*MC_Random_N5!$B4>=MAX(MC_Random_N5!$C4:$F4),MC_Random_N5!$B4-MAX(MC_Random_N5!$C4:$F4),0) -> 0 | BZ4: =IF(BZ$1*MC_Random_N5!$B4>=MAX(MC_Random_N5!$C4:$F4),MC_Random_N5!$B4-MAX(MC_Random_N5!$C4:$F4),0) -> 0 | CA4: =IF(CA$1*MC_Random_N5!$B4>=MAX(MC_Random_N5!$C4:$F4),MC_Random_N5!$B4-MAX(MC_Random_N5!$C4:$F4),0) -> 0 | CB4: =IF(CB$1*MC_Random_N5!$B4>=MAX(MC_Random_N5!$C4:$F4),MC_Random_N5!$B4-MAX(MC_Random_N5!$C4:$F4),0) -> 0 | ... CD4: =IF(CD$1*MC_Random_N5!$B4>=MAX(MC_Random_N5!$C4:$F4),MC_Random_N5!$B4-MAX(MC_Random_N5!$C4:$F4),0) -> 0.077819017 | CF4: 0.4 | CG4: ES(0.4) | CH4: =AVERAGE(BX2:BX1001) -> 0.0025339204 | CP4: 3 | CQ4: =LARGE(CHOOSE({1,2,3,4,5},CQ$1*MC_Random_N5!$B4,MC_Random_N5!$C4,MC_Random_N5!$D4,MC_Random_N5!$E4,MC_Random_N5!$F4),2) -> 0.29684413 | CR4: =LARGE(CHOOSE({1,2,3,4,5},CR$1*MC_Random_N5!$B4,MC_Random_N5!$C4,MC_Random_N5!$D4,MC_Random_N5!$E4,MC_Random_N5!$F4),2) -> 0.29684413 | CS4: =LARGE(CHOOSE({1,2,3,4,5},CS$1*MC_Random_N5!$B4,MC_Random_N5!$C4,MC_Random_N5!$D4,MC_Random_N5!$E4,MC_Random_N5!$F4),2) -> 0.29684413 | CT4: =LARGE(CHOOSE({1,2,3,4,5},CT$1*MC_Random_N5!$B4,MC_Random_N5!$C4,MC_Random_N5!$D4,MC_Random_N5!$E4,MC_Random_N5!$F4),2) -> 0.32375931 | CU4: =LARGE(CHOOSE({1,2,3,4,5},CU$1*MC_Random_N5!$B4,MC_Random_N5!$C4,MC_Random_N5!$D4,MC_Random_N5!$E4,MC_Random_N5!$F4),2) -> 0.40469914 | CV4: =LARGE(CHOOSE({1,2,3,4,5},CV$1*MC_Random_N5!$B4,MC_Random_N5!$C4,MC_Random_N5!$D4,MC_Random_N5!$E4,MC_Random_N5!$F4),2) -> 0.48563897 | CW4: =LARGE(CHOOSE({1,2,3,4,5},CW$1*MC_Random_N5!$B4,MC_Random_N5!$C4,MC_Random_N5!$D4,MC_Random_N5!$E4,MC_Random_N5!$F4),2) -> 0.5665788 | CX4: =LARGE(CHOOSE({1,2,3,4,5},CX$1*MC_Random_N5!$B4,MC_Random_N5!$C4,MC_Random_N5!$D4,MC_Random_N5!$E4,MC_Random_N5!$F4),2) -> 0.64751862 | ... CZ4: =LARGE(CHOOSE({1,2,3,4,5},CZ$1*MC_Random_N5!$B4,MC_Random_N5!$C4,MC_Random_N5!$D4,MC_Random_N5!$E4,MC_Random_N5!$F4),2) -> 0.73157926 | DB4: 0.4 | DC4: ER(0.4) | DD4: =AVERAGE(CT2:CT1001) -> 0.60610822 | DI4: 3 | DJ4: =RAND() -> 0.60134294 | DK4: =DJ4 -> 0.60134294 | DL4: =IF(DK4=MAX($DK$2:$DK$11),1,0) -> 0 | DM4: =DL4*LARGE($DK$2:$DK$11,2) -> 0 | DN4: =DL4*(DJ4-DM4) -> 0 | DU4: 3 | DV4: =IF(DV$1*MC_Random_N10!$B4>=MAX(MC_Random_N10!$C4:$K4),MC_Random_N10!$B4-MAX(MC_Random_N10!$C4:$K4),0) -> 0 | DW4: =IF(DW$1*MC_Random_N10!$B4>=MAX(MC_Random_N10!$C4:$K4),MC_Random_N10!$B4-MAX(MC_Random_N10!$C4:$K4),0) -> 0 | DX4: =IF(DX$1*MC_Random_N10!$B4>=MAX(MC_Random_N10!$C4:$K4),MC_Random_N10!$B4-MAX(MC_Random_N10!$C4:$K4),0) -> 0 | DY4: =IF(DY$1*MC_Random_N10!$B4>=MAX(MC_Random_N10!$C4:$K4),MC_Random_N10!$B4-MAX(MC_Random_N10!$C4:$K4),0) -> 0 | DZ4: =IF(DZ$1*MC_Random_N10!$B4>=MAX(MC_Random_N10!$C4:$K4),MC_Random_N10!$B4-MAX(MC_Random_N10!$C4:$K4),0) -> 0 | EA4: =IF(EA$1*MC_Random_N10!$B4>=MAX(MC_Random_N10!$C4:$K4),MC_Random_N10!$B4-MAX(MC_Random_N10!$C4:$K4),0) -> 0 | EB4: =IF(EB$1*MC_Random_N10!$B4>=MAX(MC_Random_N10!$C4:$K4),MC_Random_N10!$B4-MAX(MC_Random_N10!$C4:$K4),0) -> 0 | EC4: =IF(EC$1*MC_Random_N10!$B4>=MAX(MC_Random_N10!$C4:$K4),MC_Random_N10!$B4-MAX(MC_Random_N10!$C4:$K4),0) -> 0 | ... EE4: =IF(EE$1*MC_Random_N10!$B4>=MAX(MC_Random_N10!$C4:$K4),MC_Random_N10!$B4-MAX(MC_Random_N10!$C4:$K4),0) -> 0 | EG4: 0.4 | EH4: ES(0.4) | EI4: =AVERAGE(DY2:DY1001) -> 0 | EQ4: 3 | ER4: =MAX(LARGE(MC_Random_N10!$C4:$K4,2),MIN(ER$1*MC_Random_N10!$B4,MAX(MC_Random_N10!$C4:$K4))) -> 0.95463562 | ES4: =MAX(LARGE(MC_Random_N10!$C4:$K4,2),MIN(ES$1*MC_Random_N10!$B4,MAX(MC_Random_N10!$C4:$K4))) -> 0.95463562 | ET4: =MAX(LARGE(MC_Random_N10!$C4:$K4,2),MIN(ET$1*MC_Random_N10!$B4,MAX(MC_Random_N10!$C4:$K4))) -> 0.95463562 | EU4: =MAX(LARGE(MC_Random_N10!$C4:$K4,2),MIN(EU$1*MC_Random_N10!$B4,MAX(MC_Random_N10!$C4:$K4))) -> 0.95463562 | EV4: =MAX(LARGE(MC_Random_N10!$C4:$K4,2),MIN(EV$1*MC_Random_N10!$B4,MAX(MC_Random_N10!$C4:$K4))) -> 0.95463562 | EW4: =MAX(LARGE(MC_Random_N10!$C4:$K4,2),MIN(EW$1*MC_Random_N10!$B4,MAX(MC_Random_N10!$C4:$K4))) -> 0.95463562 | EX4: =MAX(LARGE(MC_Random_N10!$C4:$K4,2),MIN(EX$1*MC_Random_N10!$B4,MAX(MC_Random_N10!$C4:$K4))) -> 0.95463562 | EY4: =MAX(LARGE(MC_Random_N10!$C4:$K4,2),MIN(EY$1*MC_Random_N10!$B4,MAX(MC_Random_N10!$C4:$K4))) -> 0.95463562 | ... FA4: =MAX(LARGE(MC_Random_N10!$C4:$K4,2),MIN(FA$1*MC_Random_N10!$B4,MAX(MC_Random_N10!$C4:$K4))) -> 0.95463562 | FC4: 0.4 | FD4: ER(0.4) | FE4: =AVERAGE(EU2:EU1001) -> 0.79808312 | FT4: 10 | FU4: ='1_First_Price'!FT9 -> 0.8185027 | FV4: =FE10 -> 0.81785241 | FW4: =FV4-FU4 -> -0.0006502915
B5: N_c22 | C5: 10 | S5: 4 | T5: =IF(T$1*MC_Random_N2!$B5>=MC_Random_N2!$C5,MC_Random_N2!$B5-MC_Random_N2!$C5,0) -> 0 | U5: =IF(U$1*MC_Random_N2!$B5>=MC_Random_N2!$C5,MC_Random_N2!$B5-MC_Random_N2!$C5,0) -> 0 | V5: =IF(V$1*MC_Random_N2!$B5>=MC_Random_N2!$C5,MC_Random_N2!$B5-MC_Random_N2!$C5,0) -> 0 | W5: =IF(W$1*MC_Random_N2!$B5>=MC_Random_N2!$C5,MC_Random_N2!$B5-MC_Random_N2!$C5,0) -> 0 | X5: =IF(X$1*MC_Random_N2!$B5>=MC_Random_N2!$C5,MC_Random_N2!$B5-MC_Random_N2!$C5,0) -> 0.37170788 | Y5: =IF(Y$1*MC_Random_N2!$B5>=MC_Random_N2!$C5,MC_Random_N2!$B5-MC_Random_N2!$C5,0) -> 0.37170788 | Z5: =IF(Z$1*MC_Random_N2!$B5>=MC_Random_N2!$C5,MC_Random_N2!$B5-MC_Random_N2!$C5,0) -> 0.37170788 | AA5: =IF(AA$1*MC_Random_N2!$B5>=MC_Random_N2!$C5,MC_Random_N2!$B5-MC_Random_N2!$C5,0) -> 0.37170788 | ... AC5: =IF(AC$1*MC_Random_N2!$B5>=MC_Random_N2!$C5,MC_Random_N2!$B5-MC_Random_N2!$C5,0) -> 0.37170788 | AE5: 0.5 | AF5: ES(0.5) | AG5: =AVERAGE(X2:X1001) -> 0.12445908 | AO5: 4 | AP5: =IF(AP$1*MC_Random_N2!$B5>=MC_Random_N2!$C5,MC_Random_N2!$C5,AP$1*MC_Random_N2!$B5) -> 0.072680825 | AQ5: =IF(AQ$1*MC_Random_N2!$B5>=MC_Random_N2!$C5,MC_Random_N2!$C5,AQ$1*MC_Random_N2!$B5) -> 0.14536165 | AR5: =IF(AR$1*MC_Random_N2!$B5>=MC_Random_N2!$C5,MC_Random_N2!$C5,AR$1*MC_Random_N2!$B5) -> 0.21804247 | AS5: =IF(AS$1*MC_Random_N2!$B5>=MC_Random_N2!$C5,MC_Random_N2!$C5,AS$1*MC_Random_N2!$B5) -> 0.2907233 | AT5: =IF(AT$1*MC_Random_N2!$B5>=MC_Random_N2!$C5,MC_Random_N2!$C5,AT$1*MC_Random_N2!$B5) -> 0.35510036 | AU5: =IF(AU$1*MC_Random_N2!$B5>=MC_Random_N2!$C5,MC_Random_N2!$C5,AU$1*MC_Random_N2!$B5) -> 0.35510036 | AV5: =IF(AV$1*MC_Random_N2!$B5>=MC_Random_N2!$C5,MC_Random_N2!$C5,AV$1*MC_Random_N2!$B5) -> 0.35510036 | AW5: =IF(AW$1*MC_Random_N2!$B5>=MC_Random_N2!$C5,MC_Random_N2!$C5,AW$1*MC_Random_N2!$B5) -> 0.35510036 | ... AY5: =IF(AY$1*MC_Random_N2!$B5>=MC_Random_N2!$C5,MC_Random_N2!$C5,AY$1*MC_Random_N2!$B5) -> 0.35510036 | BA5: 0.5 | BB5: ER(0.5) | BC5: =AVERAGE(AT2:AT1001) -> 0.21045066 | BH5: 4 | BI5: =RAND() -> 0.5048692 | BJ5: =BI5 -> 0.5048692 | BK5: =IF(BJ5=MAX($BJ$2:$BJ$6),1,0) -> 0 | BL5: =BK5*LARGE($BJ$2:$BJ$6,2) -> 0 | BM5: =BK5*(BI5-BL5) -> 0 | BT5: 4 | BU5: =IF(BU$1*MC_Random_N5!$B5>=MAX(MC_Random_N5!$C5:$F5),MC_Random_N5!$B5-MAX(MC_Random_N5!$C5:$F5),0) -> 0 | BV5: =IF(BV$1*MC_Random_N5!$B5>=MAX(MC_Random_N5!$C5:$F5),MC_Random_N5!$B5-MAX(MC_Random_N5!$C5:$F5),0) -> 0 | BW5: =IF(BW$1*MC_Random_N5!$B5>=MAX(MC_Random_N5!$C5:$F5),MC_Random_N5!$B5-MAX(MC_Random_N5!$C5:$F5),0) -> 0 | BX5: =IF(BX$1*MC_Random_N5!$B5>=MAX(MC_Random_N5!$C5:$F5),MC_Random_N5!$B5-MAX(MC_Random_N5!$C5:$F5),0) -> 0 | BY5: =IF(BY$1*MC_Random_N5!$B5>=MAX(MC_Random_N5!$C5:$F5),MC_Random_N5!$B5-MAX(MC_Random_N5!$C5:$F5),0) -> 0 | BZ5: =IF(BZ$1*MC_Random_N5!$B5>=MAX(MC_Random_N5!$C5:$F5),MC_Random_N5!$B5-MAX(MC_Random_N5!$C5:$F5),0) -> 0 | CA5: =IF(CA$1*MC_Random_N5!$B5>=MAX(MC_Random_N5!$C5:$F5),MC_Random_N5!$B5-MAX(MC_Random_N5!$C5:$F5),0) -> 0 | CB5: =IF(CB$1*MC_Random_N5!$B5>=MAX(MC_Random_N5!$C5:$F5),MC_Random_N5!$B5-MAX(MC_Random_N5!$C5:$F5),0) -> 0 | ... CD5: =IF(CD$1*MC_Random_N5!$B5>=MAX(MC_Random_N5!$C5:$F5),MC_Random_N5!$B5-MAX(MC_Random_N5!$C5:$F5),0) -> 0.14307792 | CF5: 0.5 | CG5: ES(0.5) | CH5: =AVERAGE(BY2:BY1001) -> 0.0065111039 | CP5: 4 | CQ5: =LARGE(CHOOSE({1,2,3,4,5},CQ$1*MC_Random_N5!$B5,MC_Random_N5!$C5,MC_Random_N5!$D5,MC_Random_N5!$E5,MC_Random_N5!$F5),2) -> 0.53412379 | CR5: =LARGE(CHOOSE({1,2,3,4,5},CR$1*MC_Random_N5!$B5,MC_Random_N5!$C5,MC_Random_N5!$D5,MC_Random_N5!$E5,MC_Random_N5!$F5),2) -> 0.53412379 | CS5: =LARGE(CHOOSE({1,2,3,4,5},CS$1*MC_Random_N5!$B5,MC_Random_N5!$C5,MC_Random_N5!$D5,MC_Random_N5!$E5,MC_Random_N5!$F5),2) -> 0.53412379 | CT5: =LARGE(CHOOSE({1,2,3,4,5},CT$1*MC_Random_N5!$B5,MC_Random_N5!$C5,MC_Random_N5!$D5,MC_Random_N5!$E5,MC_Random_N5!$F5),2) -> 0.53412379 | CU5: =LARGE(CHOOSE({1,2,3,4,5},CU$1*MC_Random_N5!$B5,MC_Random_N5!$C5,MC_Random_N5!$D5,MC_Random_N5!$E5,MC_Random_N5!$F5),2) -> 0.53412379 | CV5: =LARGE(CHOOSE({1,2,3,4,5},CV$1*MC_Random_N5!$B5,MC_Random_N5!$C5,MC_Random_N5!$D5,MC_Random_N5!$E5,MC_Random_N5!$F5),2) -> 0.53443004 | CW5: =LARGE(CHOOSE({1,2,3,4,5},CW$1*MC_Random_N5!$B5,MC_Random_N5!$C5,MC_Random_N5!$D5,MC_Random_N5!$E5,MC_Random_N5!$F5),2) -> 0.62350171 | CX5: =LARGE(CHOOSE({1,2,3,4,5},CX$1*MC_Random_N5!$B5,MC_Random_N5!$C5,MC_Random_N5!$D5,MC_Random_N5!$E5,MC_Random_N5!$F5),2) -> 0.71257338 | ... CZ5: =LARGE(CHOOSE({1,2,3,4,5},CZ$1*MC_Random_N5!$B5,MC_Random_N5!$C5,MC_Random_N5!$D5,MC_Random_N5!$E5,MC_Random_N5!$F5),2) -> 0.7476388 | DB5: 0.5 | DC5: ER(0.5) | DD5: =AVERAGE(CU2:CU1001) -> 0.61056193 | DI5: 4 | DJ5: =RAND() -> 0.70761306 | DK5: =DJ5 -> 0.70761306 | DL5: =IF(DK5=MAX($DK$2:$DK$11),1,0) -> 0 | DM5: =DL5*LARGE($DK$2:$DK$11,2) -> 0 | DN5: =DL5*(DJ5-DM5) -> 0 | DU5: 4 | DV5: =IF(DV$1*MC_Random_N10!$B5>=MAX(MC_Random_N10!$C5:$K5),MC_Random_N10!$B5-MAX(MC_Random_N10!$C5:$K5),0) -> 0 | DW5: =IF(DW$1*MC_Random_N10!$B5>=MAX(MC_Random_N10!$C5:$K5),MC_Random_N10!$B5-MAX(MC_Random_N10!$C5:$K5),0) -> 0 | DX5: =IF(DX$1*MC_Random_N10!$B5>=MAX(MC_Random_N10!$C5:$K5),MC_Random_N10!$B5-MAX(MC_Random_N10!$C5:$K5),0) -> 0 | DY5: =IF(DY$1*MC_Random_N10!$B5>=MAX(MC_Random_N10!$C5:$K5),MC_Random_N10!$B5-MAX(MC_Random_N10!$C5:$K5),0) -> 0 | DZ5: =IF(DZ$1*MC_Random_N10!$B5>=MAX(MC_Random_N10!$C5:$K5),MC_Random_N10!$B5-MAX(MC_Random_N10!$C5:$K5),0) -> 0 | EA5: =IF(EA$1*MC_Random_N10!$B5>=MAX(MC_Random_N10!$C5:$K5),MC_Random_N10!$B5-MAX(MC_Random_N10!$C5:$K5),0) -> 0 | EB5: =IF(EB$1*MC_Random_N10!$B5>=MAX(MC_Random_N10!$C5:$K5),MC_Random_N10!$B5-MAX(MC_Random_N10!$C5:$K5),0) -> 0 | EC5: =IF(EC$1*MC_Random_N10!$B5>=MAX(MC_Random_N10!$C5:$K5),MC_Random_N10!$B5-MAX(MC_Random_N10!$C5:$K5),0) -> 0 | ... EE5: =IF(EE$1*MC_Random_N10!$B5>=MAX(MC_Random_N10!$C5:$K5),MC_Random_N10!$B5-MAX(MC_Random_N10!$C5:$K5),0) -> 0 | EG5: 0.5 | EH5: ES(0.5) | EI5: =AVERAGE(DZ2:DZ1001) -> 0 | EQ5: 4 | ER5: =MAX(LARGE(MC_Random_N10!$C5:$K5,2),MIN(ER$1*MC_Random_N10!$B5,MAX(MC_Random_N10!$C5:$K5))) -> 0.82910139 | ES5: =MAX(LARGE(MC_Random_N10!$C5:$K5,2),MIN(ES$1*MC_Random_N10!$B5,MAX(MC_Random_N10!$C5:$K5))) -> 0.82910139 | ET5: =MAX(LARGE(MC_Random_N10!$C5:$K5,2),MIN(ET$1*MC_Random_N10!$B5,MAX(MC_Random_N10!$C5:$K5))) -> 0.82910139 | EU5: =MAX(LARGE(MC_Random_N10!$C5:$K5,2),MIN(EU$1*MC_Random_N10!$B5,MAX(MC_Random_N10!$C5:$K5))) -> 0.82910139 | EV5: =MAX(LARGE(MC_Random_N10!$C5:$K5,2),MIN(EV$1*MC_Random_N10!$B5,MAX(MC_Random_N10!$C5:$K5))) -> 0.82910139 | EW5: =MAX(LARGE(MC_Random_N10!$C5:$K5,2),MIN(EW$1*MC_Random_N10!$B5,MAX(MC_Random_N10!$C5:$K5))) -> 0.82910139 | EX5: =MAX(LARGE(MC_Random_N10!$C5:$K5,2),MIN(EX$1*MC_Random_N10!$B5,MAX(MC_Random_N10!$C5:$K5))) -> 0.82910139 | EY5: =MAX(LARGE(MC_Random_N10!$C5:$K5,2),MIN(EY$1*MC_Random_N10!$B5,MAX(MC_Random_N10!$C5:$K5))) -> 0.82910139 | ... FA5: =MAX(LARGE(MC_Random_N10!$C5:$K5,2),MIN(FA$1*MC_Random_N10!$B5,MAX(MC_Random_N10!$C5:$K5))) -> 0.82910139 | FC5: 0.5 | FD5: ER(0.5) | FE5: =AVERAGE(EV2:EV1001) -> 0.79809006
S6: 5 | T6: =IF(T$1*MC_Random_N2!$B6>=MC_Random_N2!$C6,MC_Random_N2!$B6-MC_Random_N2!$C6,0) -> 0 | U6: =IF(U$1*MC_Random_N2!$B6>=MC_Random_N2!$C6,MC_Random_N2!$B6-MC_Random_N2!$C6,0) -> 0 | V6: =IF(V$1*MC_Random_N2!$B6>=MC_Random_N2!$C6,MC_Random_N2!$B6-MC_Random_N2!$C6,0) -> 0 | W6: =IF(W$1*MC_Random_N2!$B6>=MC_Random_N2!$C6,MC_Random_N2!$B6-MC_Random_N2!$C6,0) -> 0 | X6: =IF(X$1*MC_Random_N2!$B6>=MC_Random_N2!$C6,MC_Random_N2!$B6-MC_Random_N2!$C6,0) -> 0 | Y6: =IF(Y$1*MC_Random_N2!$B6>=MC_Random_N2!$C6,MC_Random_N2!$B6-MC_Random_N2!$C6,0) -> 0 | Z6: =IF(Z$1*MC_Random_N2!$B6>=MC_Random_N2!$C6,MC_Random_N2!$B6-MC_Random_N2!$C6,0) -> 0 | AA6: =IF(AA$1*MC_Random_N2!$B6>=MC_Random_N2!$C6,MC_Random_N2!$B6-MC_Random_N2!$C6,0) -> 0 | ... AC6: =IF(AC$1*MC_Random_N2!$B6>=MC_Random_N2!$C6,MC_Random_N2!$B6-MC_Random_N2!$C6,0) -> 0 | AE6: 0.6 | AF6: ES(0.6) | AG6: =AVERAGE(Y2:Y1001) -> 0.13711171 | AO6: 5 | AP6: =IF(AP$1*MC_Random_N2!$B6>=MC_Random_N2!$C6,MC_Random_N2!$C6,AP$1*MC_Random_N2!$B6) -> 0.048931142 | AQ6: =IF(AQ$1*MC_Random_N2!$B6>=MC_Random_N2!$C6,MC_Random_N2!$C6,AQ$1*MC_Random_N2!$B6) -> 0.097862284 | AR6: =IF(AR$1*MC_Random_N2!$B6>=MC_Random_N2!$C6,MC_Random_N2!$C6,AR$1*MC_Random_N2!$B6) -> 0.14679343 | AS6: =IF(AS$1*MC_Random_N2!$B6>=MC_Random_N2!$C6,MC_Random_N2!$C6,AS$1*MC_Random_N2!$B6) -> 0.19572457 | AT6: =IF(AT$1*MC_Random_N2!$B6>=MC_Random_N2!$C6,MC_Random_N2!$C6,AT$1*MC_Random_N2!$B6) -> 0.24465571 | AU6: =IF(AU$1*MC_Random_N2!$B6>=MC_Random_N2!$C6,MC_Random_N2!$C6,AU$1*MC_Random_N2!$B6) -> 0.29358685 | AV6: =IF(AV$1*MC_Random_N2!$B6>=MC_Random_N2!$C6,MC_Random_N2!$C6,AV$1*MC_Random_N2!$B6) -> 0.342518 | AW6: =IF(AW$1*MC_Random_N2!$B6>=MC_Random_N2!$C6,MC_Random_N2!$C6,AW$1*MC_Random_N2!$B6) -> 0.39144914 | ... AY6: =IF(AY$1*MC_Random_N2!$B6>=MC_Random_N2!$C6,MC_Random_N2!$C6,AY$1*MC_Random_N2!$B6) -> 0.48931142 | BA6: 0.6 | BB6: ER(0.6) | BC6: =AVERAGE(AU2:AU1001) -> 0.24279704 | BH6: 5 | BI6: =RAND() -> 0.15399092 | BJ6: =BI6 -> 0.15399092 | BK6: =IF(BJ6=MAX($BJ$2:$BJ$6),1,0) -> 0 | BL6: =BK6*LARGE($BJ$2:$BJ$6,2) -> 0 | BM6: =BK6*(BI6-BL6) -> 0 | BT6: 5 | BU6: =IF(BU$1*MC_Random_N5!$B6>=MAX(MC_Random_N5!$C6:$F6),MC_Random_N5!$B6-MAX(MC_Random_N5!$C6:$F6),0) -> 0 | BV6: =IF(BV$1*MC_Random_N5!$B6>=MAX(MC_Random_N5!$C6:$F6),MC_Random_N5!$B6-MAX(MC_Random_N5!$C6:$F6),0) -> 0 | BW6: =IF(BW$1*MC_Random_N5!$B6>=MAX(MC_Random_N5!$C6:$F6),MC_Random_N5!$B6-MAX(MC_Random_N5!$C6:$F6),0) -> 0 | BX6: =IF(BX$1*MC_Random_N5!$B6>=MAX(MC_Random_N5!$C6:$F6),MC_Random_N5!$B6-MAX(MC_Random_N5!$C6:$F6),0) -> 0 | BY6: =IF(BY$1*MC_Random_N5!$B6>=MAX(MC_Random_N5!$C6:$F6),MC_Random_N5!$B6-MAX(MC_Random_N5!$C6:$F6),0) -> 0 | BZ6: =IF(BZ$1*MC_Random_N5!$B6>=MAX(MC_Random_N5!$C6:$F6),MC_Random_N5!$B6-MAX(MC_Random_N5!$C6:$F6),0) -> 0 | CA6: =IF(CA$1*MC_Random_N5!$B6>=MAX(MC_Random_N5!$C6:$F6),MC_Random_N5!$B6-MAX(MC_Random_N5!$C6:$F6),0) -> 0.2383537 | CB6: =IF(CB$1*MC_Random_N5!$B6>=MAX(MC_Random_N5!$C6:$F6),MC_Random_N5!$B6-MAX(MC_Random_N5!$C6:$F6),0) -> 0.2383537 | ... CD6: =IF(CD$1*MC_Random_N5!$B6>=MAX(MC_Random_N5!$C6:$F6),MC_Random_N5!$B6-MAX(MC_Random_N5!$C6:$F6),0) -> 0.2383537 | CF6: 0.6 | CG6: ES(0.6) | CH6: =AVERAGE(BZ2:BZ1001) -> 0.011294193 | CP6: 5 | CQ6: =LARGE(CHOOSE({1,2,3,4,5},CQ$1*MC_Random_N5!$B6,MC_Random_N5!$C6,MC_Random_N5!$D6,MC_Random_N5!$E6,MC_Random_N5!$F6),2) -> 0.39928028 | CR6: =LARGE(CHOOSE({1,2,3,4,5},CR$1*MC_Random_N5!$B6,MC_Random_N5!$C6,MC_Random_N5!$D6,MC_Random_N5!$E6,MC_Random_N5!$F6),2) -> 0.39928028 | CS6: =LARGE(CHOOSE({1,2,3,4,5},CS$1*MC_Random_N5!$B6,MC_Random_N5!$C6,MC_Random_N5!$D6,MC_Random_N5!$E6,MC_Random_N5!$F6),2) -> 0.39928028 | CT6: =LARGE(CHOOSE({1,2,3,4,5},CT$1*MC_Random_N5!$B6,MC_Random_N5!$C6,MC_Random_N5!$D6,MC_Random_N5!$E6,MC_Random_N5!$F6),2) -> 0.39928028 | CU6: =LARGE(CHOOSE({1,2,3,4,5},CU$1*MC_Random_N5!$B6,MC_Random_N5!$C6,MC_Random_N5!$D6,MC_Random_N5!$E6,MC_Random_N5!$F6),2) -> 0.39928028 | CV6: =LARGE(CHOOSE({1,2,3,4,5},CV$1*MC_Random_N5!$B6,MC_Random_N5!$C6,MC_Random_N5!$D6,MC_Random_N5!$E6,MC_Random_N5!$F6),2) -> 0.39928028 | CW6: =LARGE(CHOOSE({1,2,3,4,5},CW$1*MC_Random_N5!$B6,MC_Random_N5!$C6,MC_Random_N5!$D6,MC_Random_N5!$E6,MC_Random_N5!$F6),2) -> 0.4094467 | CX6: =LARGE(CHOOSE({1,2,3,4,5},CX$1*MC_Random_N5!$B6,MC_Random_N5!$C6,MC_Random_N5!$D6,MC_Random_N5!$E6,MC_Random_N5!$F6),2) -> 0.4094467 | ... CZ6: =LARGE(CHOOSE({1,2,3,4,5},CZ$1*MC_Random_N5!$B6,MC_Random_N5!$C6,MC_Random_N5!$D6,MC_Random_N5!$E6,MC_Random_N5!$F6),2) -> 0.4094467 | DB6: 0.6 | DC6: ER(0.6) | DD6: =AVERAGE(CV2:CV1001) -> 0.61763816 | DI6: 5 | DJ6: =RAND() -> 0.73223935 | DK6: =DJ6 -> 0.73223935 | DL6: =IF(DK6=MAX($DK$2:$DK$11),1,0) -> 1 | DM6: =DL6*LARGE($DK$2:$DK$11,2) -> 0.72640431 | DN6: =DL6*(DJ6-DM6) -> 0.0058350384 | DU6: 5 | DV6: =IF(DV$1*MC_Random_N10!$B6>=MAX(MC_Random_N10!$C6:$K6),MC_Random_N10!$B6-MAX(MC_Random_N10!$C6:$K6),0) -> 0 | DW6: =IF(DW$1*MC_Random_N10!$B6>=MAX(MC_Random_N10!$C6:$K6),MC_Random_N10!$B6-MAX(MC_Random_N10!$C6:$K6),0) -> 0 | DX6: =IF(DX$1*MC_Random_N10!$B6>=MAX(MC_Random_N10!$C6:$K6),MC_Random_N10!$B6-MAX(MC_Random_N10!$C6:$K6),0) -> 0 | DY6: =IF(DY$1*MC_Random_N10!$B6>=MAX(MC_Random_N10!$C6:$K6),MC_Random_N10!$B6-MAX(MC_Random_N10!$C6:$K6),0) -> 0 | DZ6: =IF(DZ$1*MC_Random_N10!$B6>=MAX(MC_Random_N10!$C6:$K6),MC_Random_N10!$B6-MAX(MC_Random_N10!$C6:$K6),0) -> 0 | EA6: =IF(EA$1*MC_Random_N10!$B6>=MAX(MC_Random_N10!$C6:$K6),MC_Random_N10!$B6-MAX(MC_Random_N10!$C6:$K6),0) -> 0 | EB6: =IF(EB$1*MC_Random_N10!$B6>=MAX(MC_Random_N10!$C6:$K6),MC_Random_N10!$B6-MAX(MC_Random_N10!$C6:$K6),0) -> 0 | EC6: =IF(EC$1*MC_Random_N10!$B6>=MAX(MC_Random_N10!$C6:$K6),MC_Random_N10!$B6-MAX(MC_Random_N10!$C6:$K6),0) -> 0 | ... EE6: =IF(EE$1*MC_Random_N10!$B6>=MAX(MC_Random_N10!$C6:$K6),MC_Random_N10!$B6-MAX(MC_Random_N10!$C6:$K6),0) -> 0 | EG6: 0.6 | EH6: ES(0.6) | EI6: =AVERAGE(EA2:EA1001) -> 0.00042070766 | EQ6: 5 | ER6: =MAX(LARGE(MC_Random_N10!$C6:$K6,2),MIN(ER$1*MC_Random_N10!$B6,MAX(MC_Random_N10!$C6:$K6))) -> 0.72255701 | ES6: =MAX(LARGE(MC_Random_N10!$C6:$K6,2),MIN(ES$1*MC_Random_N10!$B6,MAX(MC_Random_N10!$C6:$K6))) -> 0.72255701 | ET6: =MAX(LARGE(MC_Random_N10!$C6:$K6,2),MIN(ET$1*MC_Random_N10!$B6,MAX(MC_Random_N10!$C6:$K6))) -> 0.72255701 | EU6: =MAX(LARGE(MC_Random_N10!$C6:$K6,2),MIN(EU$1*MC_Random_N10!$B6,MAX(MC_Random_N10!$C6:$K6))) -> 0.72255701 | EV6: =MAX(LARGE(MC_Random_N10!$C6:$K6,2),MIN(EV$1*MC_Random_N10!$B6,MAX(MC_Random_N10!$C6:$K6))) -> 0.72255701 | EW6: =MAX(LARGE(MC_Random_N10!$C6:$K6,2),MIN(EW$1*MC_Random_N10!$B6,MAX(MC_Random_N10!$C6:$K6))) -> 0.72255701 | EX6: =MAX(LARGE(MC_Random_N10!$C6:$K6,2),MIN(EX$1*MC_Random_N10!$B6,MAX(MC_Random_N10!$C6:$K6))) -> 0.72255701 | EY6: =MAX(LARGE(MC_Random_N10!$C6:$K6,2),MIN(EY$1*MC_Random_N10!$B6,MAX(MC_Random_N10!$C6:$K6))) -> 0.72255701 | ... FA6: =MAX(LARGE(MC_Random_N10!$C6:$K6,2),MIN(FA$1*MC_Random_N10!$B6,MAX(MC_Random_N10!$C6:$K6))) -> 0.79320109 | FC6: 0.6 | FD6: ER(0.6) | FE6: =AVERAGE(EW2:EW1001) -> 0.79849484 | FT6: Under the standard independent-private-values model with symmetric, risk-neutral bidders, first-price and second-price auctions generate equivalent expected seller revenue in equilibrium. Any differences observed in the Monte Carlo simulation should be evaluated in light of sampling variation and the assumed bidding strategies. Therefore, the simulation does not provide sufficient evidence to conclude that either mechanism consistently generates higher expected revenue.
